Workbook
Name RateYears: tblRates[year_of_income]

Sheet Start Here
A1: Division 7A loan review: s 109N terms and s 109E minimum yearly repayment
A3: 1. On Register, paste one amalgamated loan per row over the example rows, using the same columns as the CSV the command line tool reads. Booleans are true, false or unknown; a blank is unknown. Rates are fractions (8.77 per cent is 0.0877). Years are written 2026-27.
A4: 2. On Summary, choose the year of income to review. The s 109N gate reads each loan's benchmark from the year the loan was made; the repayment uses the chosen year's rate.
A5: 3. Read the calculated columns on Register: each s 109N(1) limb, the gate verdict, the s 109E(6) repayment, the shortfall and the experimental exposure. REFUSED and UNKNOWN are answers, never a number; the reason column says why.
A6: 4. Review Checks: BLOCKED means the register cannot be read (a bad year label, a value that is not true, false or unknown, text where a number belongs, a formula pasted into an input, or no reviewed rate for the year). REVIEW means a loan is not on s 109N terms, a repayment is short, a row is undecided, or a repayment figure is refused (read the reason; refusal alone is not a breach). PASS means nothing exposed, nothing undecided.
A7: 5. A rising benchmark rate raises the minimum yearly repayment on existing complying loans, not just on new ones: s 109E(6) uses the current year's rate.
A8: 6. Experimental review aid. Not a Division 7A determination. The shortfall is not the dividend (s 109Y, s 109Q and s 109RB are not modelled) and s 109R is not applied.
A10: Overall status
A11: ='Review Checks'!B10 -> REVIEW
A13: div7a-loan-review workbook, engine 0.3.1. Macro-free. Not advice; see DISCLAIMER.md in the repository.

Sheet Register
A1: loan_id | B1: borrower_reference | C1: year_loan_made | D1: written_agreement | E1: terms_in_place_before_lodgment_day | F1: maximum_term_years | G1: secured_by_registered_mortgage_over_real_property | H1: security_coverage_at_first_made | I1: interest_rate_for_years_after_year_loan_made | J1: amalgamated_loan_unpaid_at_end_of_previous_year | K1: remaining_term_years | L1: payments_applied_during_the_year | M1: out_of_scope_reason | N1: year_of_income_being_tested | O1: Status | P1: Floor_year | Q1: Floor_rate | R1: Limb_a_written | S1: Limb_lodgment | T1: Limb_b_rate | U1: Limb_secured | V1: Allowed_term_raw | W1: Limb_c_term | X1: Gate_verdict | Y1: Max_term_allowed | Z1: Term_used | AA1: MYR_raw | AB1: MYR_verdict | AC1: MYR_reason | AD1: MYR_required | AE1: Shortfall | AF1: Exposure | AG1: Undecided | AH1: Guard | AI1: Input_problem | AJ1: Sample_row | AK1: Year_made_text | AL1: Year_tested_text
A2: L-101 | B2: SYN-SHAREHOLDER-A | C2: 2023-24 | D2: true | E2: true | F2: 7 | G2: false | H2: unknown | I2: 0.0827 | J2: 120000 | K2: 3 | L2: 45000 | O2: =IF(TRIM(tblLoans[[#This Row],[out_of_scope_reason]]&"")<>"","SKIPPED",IF(IFERROR(VALUE(LEFT(tblLoans[[#This Row],[Year_made_text]],4))<1998,FALSE),"SKIPPED","REVIEWED")) -> REVIEWED | P2: =IF(OR(LOWER(TRIM(tblLoans[[#This Row],[Year_tested_text]]&""))={"","-","?","n/a","na","unk","unknown"}),tblLoans[[#This Row],[Year_made_text]],tblLoans[[#This Row],[Year_tested_text]]) -> 2023-24 | Q2: =IFERROR(INDEX(tblRates[rate],MATCH(tblLoans[[#This Row],[Floor_year]],tblRates[year_of_income],0)),"") -> 0.0827 | R2: =IF(OR(LOWER(TRIM(tblLoans[[#This Row],[written_agreement]]&""))={"","-","?","n/a","na","unk","unknown"}),"UNKNOWN",IF(OR(LOWER(TRIM(tblLoans[[#This Row],[written_agreement]]&""))={"1","t","true","y","yes"}),"PASS",IF(OR(LOWER(TRIM(tblLoans[[#This Row],[written_agreement]]&""))={"0","f","false","n","no"}),"FAIL","UNKNOWN"))) -> PASS | S2: =IF(OR(LOWER(TRIM(tblLoans[[#This Row],[terms_in_place_before_lodgment_day]]&""))={"","-","?","n/a","na","unk","unknown"}),"UNKNOWN",IF(OR(LOWER(TRIM(tblLoans[[#This Row],[terms_in_place_before_lodgment_day]]&""))={"1","t","true","y","yes"}),"PASS",IF(OR(LOWER(TRIM(tblLoans[[#This Row],[terms_in_place_before_lodgment_day]]&""))={"0","f","false","n","no"}),"FAIL","UNKNOWN"))) -> PASS | T2: =IF(NOT(ISNUMBER(tblLoans[[#This Row],[interest_rate_for_years_after_year_loan_made]])),"UNKNOWN",IF(tblLoans[[#This Row],[Floor_rate]]="","UNKNOWN",IF(tblLoans[[#This Row],[interest_rate_for_years_after_year_loan_made]]>=tblLoans[[#This Row],[Floor_rate]],"PASS","FAIL"))) -> PASS | U2: =IF(OR(LOWER(TRIM(tblLoans[[#This Row],[secured_by_registered_mortgage_over_real_property]]&""))={"","-","?","n/a","na","unk","unknown"}),"UNKNOWN",IF(OR(LOWER(TRIM(tblLoans[[#This Row],[secured_by_registered_mortgage_over_real_property]]&""))={"1","t","true","y","yes"}),"PASS",IF(OR(LOWER(TRIM(tblLoans[[#This Row],[secured_by_registered_mortgage_over_real_property]]&""))={"0","f","false","n","no"}),"FAIL","UNKNOWN"))) -> FAIL | V2: =IF(tblLoans[[#This Row],[Limb_secured]]="FAIL",7,IF(tblLoans[[#This Row],[Limb_secured]]="PASS",IF(ISNUMBER(tblLoans[[#This Row],[security_coverage_at_first_made]]),IF(tblLoans[[#This Row],[security_coverage_at_first_made]]>=1.1,25,7),""),"")) -> 7 | W2: =IF(NOT(ISNUMBER(tblLoans[[#This Row],[maximum_term_years]])),"UNKNOWN",IF(tblLoans[[#This Row],[Allowed_term_raw]]="",IF(tblLoans[[#This Row],[maximum_term_years]]<=7,"PASS","UNKNOWN"),IF(tblLoans[[#This Row],[maximum_term_years]]<=tblLoans[[#This Row],[Allowed_term_raw]],"PASS","FAIL"))) -> PASS | X2: =IF(tblLoans[[#This Row],[Status]]="SKIPPED","",IF(OR(LOWER(TRIM(tblLoans[[#This Row],[Floor_year]]&""))={"","-","?","n/a","na","unk","unknown"}),"UNKNOWN",IF(OR(tblLoans[[#This Row],[Limb_a_written]]="FAIL",tblLoans[[#This Row],[Limb_lodgment]]="FAIL",tblLoans[[#This Row],[Limb_b_rate]]="FAIL",tblLoans[[#This Row],[Limb_c_term]]="FAIL"),"NOT_COMPLYING",IF(OR(tblLoans[[#This Row],[Limb_a_written]]="UNKNOWN",tblLoans[[#This Row],[Limb_lodgment]]="UNKNOWN",tblLoans[[#This Row],[Limb_b_rate]]="UNKNOWN",tblLoans[[#This Row],[Limb_c_term]]="UNKNOWN"),"UNKNOWN","COMPLYING")))) -> COMPLYING | Y2: =IF(OR(tblLoans[[#This Row],[Status]]="SKIPPED",OR(LOWER(TRIM(tblLoans[[#This Row],[Floor_year]]&""))={"","-","?","n/a","na","unk","unknown"})),"",IF(tblLoans[[#This Row],[Allowed_term_raw]]<>"",tblLoans[[#This Row],[Allowed_term_raw]],IF(AND(ISNUMBER(tblLoans[[#This Row],[maximum_term_years]]),tblLoans[[#This Row],[maximum_term_years]]<=7),7,""))) -> 7 | Z2: =IF(tblLoans[[#This Row],[Status]]="SKIPPED","",IF(ISNUMBER(tblLoans[[#This Row],[remaining_term_years]]),ROUNDUP(tblLoans[[#This Row],[remaining_term_years]],0),"")) -> 3 | AA2: =IF(AND(ISNUMBER(tblLoans[[#This Row],[amalgamated_loan_unpaid_at_end_of_previous_year]]),ISNUMBER(Summary!$B$3),Summary!$B$3>0,ISNUMBER(tblLoans[[#This Row],[Term_used]]),tblLoans[[#This Row],[Term_used]]>0),ROUND(tblLoans[[#This Row],[amalgamated_loan_unpaid_at_end_of_previous_year]]*Summary!$B$3/(1-(1/(1+Summary!$B$3))^tblLoans[[#This Row],[Term_used]]),2),"") -> 47212.37 | AB2: =IF(tblLoans[[#This Row],[Status]]="SKIPPED","",IF(OR(tblLoans[[#This Row],[Gate_verdict]]<>"COMPLYING",AND(NOT(OR(LOWER(TRIM(tblLoans[[#This Row],[Year_made_text]]&""))={"","-","?","n/a","na","unk","unknown"})),tblLoans[[#This Row],[Floor_year]]<>tblLoans[[#This Row],[Year_made_text]]),tblLoans[[#This Row],[Year_made_text]]=Summary!$B$2,IFERROR(VALUE(LEFT(tblLoans[[#This Row],[Year_made_text]],4))>Summary!$B$4,FALSE),AND(ISNUMBER(tblLoans[[#This Row],[Term_used]]),tblLoans[[#This Row],[Term_used]]<=0),AND(ISNUMBER(Summary!$B$3),Summary!$B$3<=0)),"REFUSED",IF(OR(OR(LOWER(TRIM(tblLoans[[#This Row],[Year_made_text]]&""))={"","-","?","n/a","na","unk","unknown"}),NOT(ISNUMBER(Summary!$B$3)),NOT(ISNUMBER(tblLoans[[#This Row],[amalgamated_loan_unpaid_at_end_of_previous_year]])),NOT(ISNUMBER(tblLoans[[#This Row],[payments_applied_during_the_year]])),NOT(ISNUMBER(tblLoans[[#This Row],[Term_used]]))),"UNKNOWN",IF(tblLoans[[#This Row],[MYR_raw]]-ROUND(tblLoans[[#This Row],[payments_applied_during_the_year]],2)<=0,"MYR_MET","MYR_SHORT")))) -> MYR_SHORT | AC2: =IF(tblLoans[[#This Row],[MYR_verdict]]="REFUSED",IF(tblLoans[[#This Row],[Gate_verdict]]<>"COMPLYING","s 109N gate is "&tblLoans[[#This Row],[Gate_verdict]]&", so s 109E produces no repayment figure",IF(tblLoans[[#This Row],[Floor_year]]<>tblLoans[[#This Row],[Year_made_text]],"gate benchmark year differs from year_loan_made",IF(tblLoans[[#This Row],[Year_made_text]]=Summary!$B$2,"year of income is the year the loan was made (s 109E(1)(a), s 109P)",IF(IFERROR(VALUE(LEFT(tblLoans[[#This Row],[Year_made_text]],4))>Summary!$B$4,FALSE),"loan made after the year of income",IF(AND(ISNUMBER(tblLoans[[#This Row],[Term_used]]),tblLoans[[#This Row],[Term_used]]<=0),"nil remaining term under s 109E(6)","nil benchmark rate"))))),IF(tblLoans[[#This Row],[MYR_verdict]]="UNKNOWN",IF(OR(LOWER(TRIM(tblLoans[[#This Row],[Year_made_text]]&""))={"","-","?","n/a","na","unk","unknown"}),"year_loan_made not established",IF(NOT(ISNUMBER(Summary!$B$3)),"no reviewed benchmark rate for the year of income",IF(NOT(ISNUMBER(tblLoans[[#This Row],[amalgamated_loan_unpaid_at_end_of_previous_year]])),"unpaid balance at end of previous year not established",IF(NOT(ISNUMBER(tblLoans[[#This Row],[payments_applied_during_the_year]])),"payments applied not established","remaining term not established")))),"")) | AD2: =IF(OR(tblLoans[[#This Row],[MYR_verdict]]="MYR_MET",tblLoans[[#This Row],[MYR_verdict]]="MYR_SHORT"),tblLoans[[#This Row],[MYR_raw]],"") -> 47212.37 | AE2: =IF(OR(tblLoans[[#This Row],[MYR_verdict]]="MYR_MET",tblLoans[[#This Row],[MYR_verdict]]="MYR_SHORT"),MAX(0,ROUND(tblLoans[[#This Row],[MYR_raw]]-ROUND(tblLoans[[#This Row],[payments_applied_during_the_year]],2),2)),"") -> 2212.37 | AF2: =IF(tblLoans[[#This Row],[MYR_verdict]]="MYR_SHORT",tblLoans[[#This Row],[Shortfall]],"") -> 2212.37 | AG2: =IF(AND(tblLoans[[#This Row],[Status]]="REVIEWED",OR(tblLoans[[#This Row],[Gate_verdict]]="UNKNOWN",tblLoans[[#This Row],[MYR_verdict]]="UNKNOWN")),1,0) -> 0 | AH2: =IF(OR(_xlfn.ISFORMULA(tblLoans[[#This Row],[loan_id]]),_xlfn.ISFORMULA(tblLoans[[#This Row],[borrower_reference]]),_xlfn.ISFORMULA(tblLoans[[#This Row],[year_loan_made]]),_xlfn.ISFORMULA(tblLoans[[#This Row],[written_agreement]]),_xlfn.ISFORMULA(tblLoans[[#This Row],[terms_in_place_before_lodgment_day]]),_xlfn.ISFORMULA(tblLoans[[#This Row],[maximum_term_years]]),_xlfn.ISFORMULA(tblLoans[[#This Row],[secured_by_registered_mortgage_over_real_property]]),_xlfn.ISFORMULA(tblLoans[[#This Row],[security_coverage_at_first_made]]),_xlfn.ISFORMULA(tblLoans[[#This Row],[interest_rate_for_years_after_year_loan_made]]),_xlfn.ISFORMULA(tblLoans[[#This Row],[amalgamated_loan_unpaid_at_end_of_previous_year]]),_xlfn.ISFORMULA(tblLoans[[#This Row],[remaining_term_years]]),_xlfn.ISFORMULA(tblLoans[[#This Row],[payments_applied_during_the_year]]),_xlfn.ISFORMULA(tblLoans[[#This Row],[out_of_scope_reason]]),_xlfn.ISFORMULA(tblLoans[[#This Row],[year_of_income_being_tested]])),1,0) -> 0 | AI2: =IF(TRIM(tblLoans[[#This Row],[out_of_scope_reason]]&"")<>"","",TRIM(IF(OR(AND(NOT(OR(LOWER(TRIM(tblLoans[[#This Row],[Year_made_text]]&""))={"","-","?","n/a","na","unk","unknown"})),NOT(IFERROR(AND(LEN(tblLoans[[#This Row],[Year_made_text]])=7,MID(tblLoans[[#This Row],[Year_made_text]],5,1)="-",ISNUMBER(VALUE(MID(tblLoans[[#This Row],[Year_made_text]],1,1))),ISNUMBER(VALUE(MID(tblLoans[[#This Row],[Year_made_text]],2,1))),ISNUMBER(VALUE(MID(tblLoans[[#This Row],[Year_made_text]],3,1))),ISNUMBER(VALUE(MID(tblLoans[[#This Row],[Year_made_text]],4,1))),ISNUMBER(VALUE(MID(tblLoans[[#This Row],[Year_made_text]],6,1))),ISNUMBER(VALUE(MID(tblLoans[[#This Row],[Year_made_text]],7,1))),VALUE(RIGHT(tblLoans[[#This Row],[Year_made_text]],2))=MOD(VALUE(LEFT(tblLoans[[#This Row],[Year_made_text]],4))+1,100),VALUE(LEFT(tblLoans[[#This Row],[Year_made_text]],4))>=1900,VALUE(LEFT(tblLoans[[#This Row],[Year_made_text]],4))<=2100),FALSE))),AND(tblLoans[[#This Row],[Status]]="REVIEWED",AND(NOT(OR(LOWER(TRIM(tblLoans[[#This Row],[Year_tested_text]]&""))={"","-","?","n/a","na","unk","unknown"})),NOT(IFERROR(AND(LEN(tblLoans[[#This Row],[Year_tested_text]])=7,MID(tblLoans[[#This Row],[Year_tested_text]],5,1)="-",ISNUMBER(VALUE(MID(tblLoans[[#This Row],[Year_tested_text]],1,1))),ISNUMBER(VALUE(MID(tblLoans[[#This Row],[Year_tested_text]],2,1))),ISNUMBER(VALUE(MID(tblLoans[[#This Row],[Year_tested_text]],3,1))),ISNUMBER(VALUE(MID(tblLoans[[#This Row],[Year_tested_text]],4,1))),ISNUMBER(VALUE(MID(tblLoans[[#This Row],[Year_tested_text]],6,1))),ISNUMBER(VALUE(MID(tblLoans[[#This Row],[Year_tested_text]],7,1))),VALUE(RIGHT(tblLoans[[#This Row],[Year_tested_text]],2))=MOD(VALUE(LEFT(tblLoans[[#This Row],[Year_tested_text]],4))+1,100),VALUE(LEFT(tblLoans[[#This Row],[Year_tested_text]],4))>=1900,VALUE(LEFT(tblLoans[[#This Row],[Year_tested_text]],4))<=2100),FALSE))))),"year label ","")&IF(tblLoans[[#This Row],[Status]]<>"REVIEWED","",IF(OR(AND(NOT(OR(LOWER(TRIM(tblLoans[[#This Row],[written_agreement]]&""))={"","-","?","n/a","na","unk","unknown"})),NOT(OR(LOWER(TRIM(tblLoans[[#This Row],[written_agreement]]&""))={"0","1","f","false","n","no","t","true","y","yes"}))),AND(NOT(OR(LOWER(TRIM(tblLoans[[#This Row],[terms_in_place_before_lodgment_day]]&""))={"","-","?","n/a","na","unk","unknown"})),NOT(OR(LOWER(TRIM(tblLoans[[#This Row],[terms_in_place_before_lodgment_day]]&""))={"0","1","f","false","n","no","t","true","y","yes"}))),AND(NOT(OR(LOWER(TRIM(tblLoans[[#This Row],[secured_by_registered_mortgage_over_real_property]]&""))={"","-","?","n/a","na","unk","unknown"})),NOT(OR(LOWER(TRIM(tblLoans[[#This Row],[secured_by_registered_mortgage_over_real_property]]&""))={"0","1","f","false","n","no","t","true","y","yes"})))),"true/false/unknown ","")&IF(OR(AND(NOT(OR(LOWER(TRIM(tblLoans[[#This Row],[maximum_term_years]]&""))={"","-","?","n/a","na","unk","unknown"})),OR(NOT(ISNUMBER(tblLoans[[#This Row],[maximum_term_years]])),AND(ISNUMBER(tblLoans[[#This Row],[maximum_term_years]]),OR(tblLoans[[#This Row],[maximum_term_years]]<0)))),AND(NOT(OR(LOWER(TRIM(tblLoans[[#This Row],[security_coverage_at_first_made]]&""))={"","-","?","n/a","na","unk","unknown"})),OR(NOT(ISNUMBER(tblLoans[[#This Row],[security_coverage_at_first_made]])),AND(ISNUMBER(tblLoans[[#This Row],[security_coverage_at_first_made]]),OR(tblLoans[[#This Row],[security_coverage_at_first_made]]<0)))),AND(NOT(OR(LOWER(TRIM(tblLoans[[#This Row],[interest_rate_for_years_after_year_loan_made]]&""))={"","-","?","n/a","na","unk","unknown"})),OR(NOT(ISNUMBER(tblLoans[[#This Row],[interest_rate_for_years_after_year_loan_made]])),AND(ISNUMBER(tblLoans[[#This Row],[interest_rate_for_years_after_year_loan_made]]),OR(tblLoans[[#This Row],[interest_rate_for_years_after_year_loan_made]]<0,tblLoans[[#This Row],[interest_rate_for_years_after_year_loan_made]]>1)))),AND(NOT(OR(LOWER(TRIM(tblLoans[[#This Row],[amalgamated_loan_unpaid_at_end_of_previous_year]]&""))={"","-","?","n/a","na","unk","unknown"})),OR(NOT(ISNUMBER(tblLoans[[#This Row],[amalgamated_loan_unpaid_at_end_of_previous_year]])),AND(ISNUMBER(tblLoans[[#This Row],[amalgamated_loan_unpaid_at_end_of_previous_year]]),OR(tblLoans[[#This Row],[amalgamated_loan_unpaid_at_end_of_previous_year]]<0,ROUND(N(tblLoans[[#This Row],[amalgamated_loan_unpaid_at_end_of_previous_year]]),2)<>N(tblLoans[[#This Row],[amalgamated_loan_unpaid_at_end_of_previous_year]]),N(tblLoans[[#This Row],[amalgamated_loan_unpaid_at_end_of_previous_year]])>1000000000000)))),AND(NOT(OR(LOWER(TRIM(tblLoans[[#This Row],[remaining_term_years]]&""))={"","-","?","n/a","na","unk","unknown"})),OR(NOT(ISNUMBER(tblLoans[[#This Row],[remaining_term_years]])),AND(ISNUMBER(tblLoans[[#This Row],[remaining_term_years]]),OR(tblLoans[[#This Row],[remaining_term_years]]<0)))),AND(NOT(OR(LOWER(TRIM(tblLoans[[#This Row],[payments_applied_during_the_year]]&""))={"","-","?","n/a","na","unk","unknown"})),OR(NOT(ISNUMBER(tblLoans[[#This Row],[payments_applied_during_the_year]])),AND(ISNUMBER(tblLoans[[#This Row],[payments_applied_during_the_year]]),OR(tblLoans[[#This Row],[payments_applied_during_the_year]]<0,ROUND(N(tblLoans[[#This Row],[payments_applied_during_the_year]]),2)<>N(tblLoans[[#This Row],[payments_applied_during_the_year]]),N(tblLoans[[#This Row],[payments_applied_during_the_year]])>1000000000000))))),"number ","")))) | AJ2: =IF(SUMPRODUCT((tblLoans[[#This Row],[loan_id]]&""={"L-101","L-102","L-103","L-104","L-105","L-106","L-107","L-108"})*(tblLoans[[#This Row],[Year_made_text]]&""={"2023-24","2022-23","2021-22","2024-25","2019-20","2020-21","2023-24","1996-97"}))>0,1,0) -> 1 | AK2: =TRIM(SUBSTITUTE(SUBSTITUTE(SUBSTITUTE(SUBSTITUTE(SUBSTITUTE(SUBSTITUTE(SUBSTITUTE(SUBSTITUTE(SUBSTITUTE(SUBSTITUTE(SUBSTITUTE(SUBSTITUTE(SUBSTITUTE(SUBSTITUTE(SUBSTITUTE(SUBSTITUTE(SUBSTITUTE(SUBSTITUTE(SUBSTITUTE(SUBSTITUTE(SUBSTITUTE(SUBSTITUTE(SUBSTITUTE(SUBSTITUTE(SUBSTITUTE(SUBSTITUTE(SUBSTITUTE(SUBSTITUTE(tblLoans[[#This Row],[year_loan_made]]&"",_xlfn.UNICHAR(9)," "),_xlfn.UNICHAR(10)," "),_xlfn.UNICHAR(11)," "),_xlfn.UNICHAR(12)," "),_xlfn.UNICHAR(13)," "),_xlfn.UNICHAR(28)," "),_xlfn.UNICHAR(29)," "),_xlfn.UNICHAR(30)," "),_xlfn.UNICHAR(31)," "),_xlfn.UNICHAR(133)," "),_xlfn.UNICHAR(160)," "),_xlfn.UNICHAR(5760)," "),_xlfn.UNICHAR(8192)," "),_xlfn.UNICHAR(8193)," "),_xlfn.UNICHAR(8194)," "),_xlfn.UNICHAR(8195)," "),_xlfn.UNICHAR(8196)," "),_xlfn.UNICHAR(8197)," "),_xlfn.UNICHAR(8198)," "),_xlfn.UNICHAR(8199)," "),_xlfn.UNICHAR(8200)," "),_xlfn.UNICHAR(8201)," "),_xlfn.UNICHAR(8202)," "),_xlfn.UNICHAR(8232)," "),_xlfn.UNICHAR(8233)," "),_xlfn.UNICHAR(8239)," "),_xlfn.UNICHAR(8287)," "),_xlfn.UNICHAR(12288)," ")) -> 2023-24 | AL2: =TRIM(SUBSTITUTE(SUBSTITUTE(SUBSTITUTE(SUBSTITUTE(SUBSTITUTE(SUBSTITUTE(SUBSTITUTE(SUBSTITUTE(SUBSTITUTE(SUBSTITUTE(SUBSTITUTE(SUBSTITUTE(SUBSTITUTE(SUBSTITUTE(SUBSTITUTE(SUBSTITUTE(SUBSTITUTE(SUBSTITUTE(SUBSTITUTE(SUBSTITUTE(SUBSTITUTE(SUBSTITUTE(SUBSTITUTE(SUBSTITUTE(SUBSTITUTE(SUBSTITUTE(SUBSTITUTE(SUBSTITUTE(tblLoans[[#This Row],[year_of_income_being_tested]]&"",_xlfn.UNICHAR(9)," "),_xlfn.UNICHAR(10)," "),_xlfn.UNICHAR(11)," "),_xlfn.UNICHAR(12)," "),_xlfn.UNICHAR(13)," "),_xlfn.UNICHAR(28)," "),_xlfn.UNICHAR(29)," "),_xlfn.UNICHAR(30)," "),_xlfn.UNICHAR(31)," "),_xlfn.UNICHAR(133)," "),_xlfn.UNICHAR(160)," "),_xlfn.UNICHAR(5760)," "),_xlfn.UNICHAR(8192)," "),_xlfn.UNICHAR(8193)," "),_xlfn.UNICHAR(8194)," "),_xlfn.UNICHAR(8195)," "),_xlfn.UNICHAR(8196)," "),_xlfn.UNICHAR(8197)," "),_xlfn.UNICHAR(8198)," "),_xlfn.UNICHAR(8199)," "),_xlfn.UNICHAR(8200)," "),_xlfn.UNICHAR(8201)," "),_xlfn.UNICHAR(8202)," "),_xlfn.UNICHAR(8232)," "),_xlfn.UNICHAR(8233)," "),_xlfn.UNICHAR(8239)," "),_xlfn.UNICHAR(8287)," "),_xlfn.UNICHAR(12288)," "))
A3: L-102 | B3: SYN-ASSOCIATE-B | C3: 2022-23 | D3: true | E3: true | F3: 7 | G3: false | H3: unknown | I3: 0.04 | J3: 90000 | K3: 4 | L3: 20000 | O3: =IF(TRIM(tblLoans[[#This Row],[out_of_scope_reason]]&"")<>"","SKIPPED",IF(IFERROR(VALUE(LEFT(tblLoans[[#This Row],[Year_made_text]],4))<1998,FALSE),"SKIPPED","REVIEWED")) -> REVIEWED | P3: =IF(OR(LOWER(TRIM(tblLoans[[#This Row],[Year_tested_text]]&""))={"","-","?","n/a","na","unk","unknown"}),tblLoans[[#This Row],[Year_made_text]],tblLoans[[#This Row],[Year_tested_text]]) -> 2022-23 | Q3: =IFERROR(INDEX(tblRates[rate],MATCH(tblLoans[[#This Row],[Floor_year]],tblRates[year_of_income],0)),"") -> 0.0477 | R3: =IF(OR(LOWER(TRIM(tblLoans[[#This Row],[written_agreement]]&""))={"","-","?","n/a","na","unk","unknown"}),"UNKNOWN",IF(OR(LOWER(TRIM(tblLoans[[#This Row],[written_agreement]]&""))={"1","t","true","y","yes"}),"PASS",IF(OR(LOWER(TRIM(tblLoans[[#This Row],[written_agreement]]&""))={"0","f","false","n","no"}),"FAIL","UNKNOWN"))) -> PASS | S3: =IF(OR(LOWER(TRIM(tblLoans[[#This Row],[terms_in_place_before_lodgment_day]]&""))={"","-","?","n/a","na","unk","unknown"}),"UNKNOWN",IF(OR(LOWER(TRIM(tblLoans[[#This Row],[terms_in_place_before_lodgment_day]]&""))={"1","t","true","y","yes"}),"PASS",IF(OR(LOWER(TRIM(tblLoans[[#This Row],[terms_in_place_before_lodgment_day]]&""))={"0","f","false","n","no"}),"FAIL","UNKNOWN"))) -> PASS | T3: =IF(NOT(ISNUMBER(tblLoans[[#This Row],[interest_rate_for_years_after_year_loan_made]])),"UNKNOWN",IF(tblLoans[[#This Row],[Floor_rate]]="","UNKNOWN",IF(tblLoans[[#This Row],[interest_rate_for_years_after_year_loan_made]]>=tblLoans[[#This Row],[Floor_rate]],"PASS","FAIL"))) -> FAIL | U3: =IF(OR(LOWER(TRIM(tblLoans[[#This Row],[secured_by_registered_mortgage_over_real_property]]&""))={"","-","?","n/a","na","unk","unknown"}),"UNKNOWN",IF(OR(LOWER(TRIM(tblLoans[[#This Row],[secured_by_registered_mortgage_over_real_property]]&""))={"1","t","true","y","yes"}),"PASS",IF(OR(LOWER(TRIM(tblLoans[[#This Row],[secured_by_registered_mortgage_over_real_property]]&""))={"0","f","false","n","no"}),"FAIL","UNKNOWN"))) -> FAIL | V3: =IF(tblLoans[[#This Row],[Limb_secured]]="FAIL",7,IF(tblLoans[[#This Row],[Limb_secured]]="PASS",IF(ISNUMBER(tblLoans[[#This Row],[security_coverage_at_first_made]]),IF(tblLoans[[#This Row],[security_coverage_at_first_made]]>=1.1,25,7),""),"")) -> 7 | W3: =IF(NOT(ISNUMBER(tblLoans[[#This Row],[maximum_term_years]])),"UNKNOWN",IF(tblLoans[[#This Row],[Allowed_term_raw]]="",IF(tblLoans[[#This Row],[maximum_term_years]]<=7,"PASS","UNKNOWN"),IF(tblLoans[[#This Row],[maximum_term_years]]<=tblLoans[[#This Row],[Allowed_term_raw]],"PASS","FAIL"))) -> PASS | X3: =IF(tblLoans[[#This Row],[Status]]="SKIPPED","",IF(OR(LOWER(TRIM(tblLoans[[#This Row],[Floor_year]]&""))={"","-","?","n/a","na","unk","unknown"}),"UNKNOWN",IF(OR(tblLoans[[#This Row],[Limb_a_written]]="FAIL",tblLoans[[#This Row],[Limb_lodgment]]="FAIL",tblLoans[[#This Row],[Limb_b_rate]]="FAIL",tblLoans[[#This Row],[Limb_c_term]]="FAIL"),"NOT_COMPLYING",IF(OR(tblLoans[[#This Row],[Limb_a_written]]="UNKNOWN",tblLoans[[#This Row],[Limb_lodgment]]="UNKNOWN",tblLoans[[#This Row],[Limb_b_rate]]="UNKNOWN",tblLoans[[#This Row],[Limb_c_term]]="UNKNOWN"),"UNKNOWN","COMPLYING")))) -> NOT_COMPLYING | Y3: =IF(OR(tblLoans[[#This Row],[Status]]="SKIPPED",OR(LOWER(TRIM(tblLoans[[#This Row],[Floor_year]]&""))={"","-","?","n/a","na","unk","unknown"})),"",IF(tblLoans[[#This Row],[Allowed_term_raw]]<>"",tblLoans[[#This Row],[Allowed_term_raw]],IF(AND(ISNUMBER(tblLoans[[#This Row],[maximum_term_years]]),tblLoans[[#This Row],[maximum_term_years]]<=7),7,""))) -> 7 | Z3: =IF(tblLoans[[#This Row],[Status]]="SKIPPED","",IF(ISNUMBER(tblLoans[[#This Row],[remaining_term_years]]),ROUNDUP(tblLoans[[#This Row],[remaining_term_years]],0),"")) -> 4 | AA3: =IF(AND(ISNUMBER(tblLoans[[#This Row],[amalgamated_loan_unpaid_at_end_of_previous_year]]),ISNUMBER(Summary!$B$3),Summary!$B$3>0,ISNUMBER(tblLoans[[#This Row],[Term_used]]),tblLoans[[#This Row],[Term_used]]>0),ROUND(tblLoans[[#This Row],[amalgamated_loan_unpaid_at_end_of_previous_year]]*Summary!$B$3/(1-(1/(1+Summary!$B$3))^tblLoans[[#This Row],[Term_used]]),2),"") -> 27640.06 | AB3: =IF(tblLoans[[#This Row],[Status]]="SKIPPED","",IF(OR(tblLoans[[#This Row],[Gate_verdict]]<>"COMPLYING",AND(NOT(OR(LOWER(TRIM(tblLoans[[#This Row],[Year_made_text]]&""))={"","-","?","n/a","na","unk","unknown"})),tblLoans[[#This Row],[Floor_year]]<>tblLoans[[#This Row],[Year_made_text]]),tblLoans[[#This Row],[Year_made_text]]=Summary!$B$2,IFERROR(VALUE(LEFT(tblLoans[[#This Row],[Year_made_text]],4))>Summary!$B$4,FALSE),AND(ISNUMBER(tblLoans[[#This Row],[Term_used]]),tblLoans[[#This Row],[Term_used]]<=0),AND(ISNUMBER(Summary!$B$3),Summary!$B$3<=0)),"REFUSED",IF(OR(OR(LOWER(TRIM(tblLoans[[#This Row],[Year_made_text]]&""))={"","-","?","n/a","na","unk","unknown"}),NOT(ISNUMBER(Summary!$B$3)),NOT(ISNUMBER(tblLoans[[#This Row],[amalgamated_loan_unpaid_at_end_of_previous_year]])),NOT(ISNUMBER(tblLoans[[#This Row],[payments_applied_during_the_year]])),NOT(ISNUMBER(tblLoans[[#This Row],[Term_used]]))),"UNKNOWN",IF(tblLoans[[#This Row],[MYR_raw]]-ROUND(tblLoans[[#This Row],[payments_applied_during_the_year]],2)<=0,"MYR_MET","MYR_SHORT")))) -> REFUSED | AC3: =IF(tblLoans[[#This Row],[MYR_verdict]]="REFUSED",IF(tblLoans[[#This Row],[Gate_verdict]]<>"COMPLYING","s 109N gate is "&tblLoans[[#This Row],[Gate_verdict]]&", so s 109E produces no repayment figure",IF(tblLoans[[#This Row],[Floor_year]]<>tblLoans[[#This Row],[Year_made_text]],"gate benchmark year differs from year_loan_made",IF(tblLoans[[#This Row],[Year_made_text]]=Summary!$B$2,"year of income is the year the loan was made (s 109E(1)(a), s 109P)",IF(IFERROR(VALUE(LEFT(tblLoans[[#This Row],[Year_made_text]],4))>Summary!$B$4,FALSE),"loan made after the year of income",IF(AND(ISNUMBER(tblLoans[[#This Row],[Term_used]]),tblLoans[[#This Row],[Term_used]]<=0),"nil remaining term under s 109E(6)","nil benchmark rate"))))),IF(tblLoans[[#This Row],[MYR_verdict]]="UNKNOWN",IF(OR(LOWER(TRIM(tblLoans[[#This Row],[Year_made_text]]&""))={"","-","?","n/a","na","unk","unknown"}),"year_loan_made not established",IF(NOT(ISNUMBER(Summary!$B$3)),"no reviewed benchmark rate for the year of income",IF(NOT(ISNUMBER(tblLoans[[#This Row],[amalgamated_loan_unpaid_at_end_of_previous_year]])),"unpaid balance at end of previous year not established",IF(NOT(ISNUMBER(tblLoans[[#This Row],[payments_applied_during_the_year]])),"payments applied not established","remaining term not established")))),"")) -> s 109N gate is NOT_COMPLYING, so s 109E produces no repayment figure | AD3: =IF(OR(tblLoans[[#This Row],[MYR_verdict]]="MYR_MET",tblLoans[[#This Row],[MYR_verdict]]="MYR_SHORT"),tblLoans[[#This Row],[MYR_raw]],"") | AE3: =IF(OR(tblLoans[[#This Row],[MYR_verdict]]="MYR_MET",tblLoans[[#This Row],[MYR_verdict]]="MYR_SHORT"),MAX(0,ROUND(tblLoans[[#This Row],[MYR_raw]]-ROUND(tblLoans[[#This Row],[payments_applied_during_the_year]],2),2)),"") | AF3: =IF(tblLoans[[#This Row],[MYR_verdict]]="MYR_SHORT",tblLoans[[#This Row],[Shortfall]],"") | AG3: =IF(AND(tblLoans[[#This Row],[Status]]="REVIEWED",OR(tblLoans[[#This Row],[Gate_verdict]]="UNKNOWN",tblLoans[[#This Row],[MYR_verdict]]="UNKNOWN")),1,0) -> 0 | AH3: =IF(OR(_xlfn.ISFORMULA(tblLoans[[#This Row],[loan_id]]),_xlfn.ISFORMULA(tblLoans[[#This Row],[borrower_reference]]),_xlfn.ISFORMULA(tblLoans[[#This Row],[year_loan_made]]),_xlfn.ISFORMULA(tblLoans[[#This Row],[written_agreement]]),_xlfn.ISFORMULA(tblLoans[[#This Row],[terms_in_place_before_lodgment_day]]),_xlfn.ISFORMULA(tblLoans[[#This Row],[maximum_term_years]]),_xlfn.ISFORMULA(tblLoans[[#This Row],[secured_by_registered_mortgage_over_real_property]]),_xlfn.ISFORMULA(tblLoans[[#This Row],[security_coverage_at_first_made]]),_xlfn.ISFORMULA(tblLoans[[#This Row],[interest_rate_for_years_after_year_loan_made]]),_xlfn.ISFORMULA(tblLoans[[#This Row],[amalgamated_loan_unpaid_at_end_of_previous_year]]),_xlfn.ISFORMULA(tblLoans[[#This Row],[remaining_term_years]]),_xlfn.ISFORMULA(tblLoans[[#This Row],[payments_applied_during_the_year]]),_xlfn.ISFORMULA(tblLoans[[#This Row],[out_of_scope_reason]]),_xlfn.ISFORMULA(tblLoans[[#This Row],[year_of_income_being_tested]])),1,0) -> 0 | AI3: =IF(TRIM(tblLoans[[#This Row],[out_of_scope_reason]]&"")<>"","",TRIM(IF(OR(AND(NOT(OR(LOWER(TRIM(tblLoans[[#This Row],[Year_made_text]]&""))={"","-","?","n/a","na","unk","unknown"})),NOT(IFERROR(AND(LEN(tblLoans[[#This Row],[Year_made_text]])=7,MID(tblLoans[[#This Row],[Year_made_text]],5,1)="-",ISNUMBER(VALUE(MID(tblLoans[[#This Row],[Year_made_text]],1,1))),ISNUMBER(VALUE(MID(tblLoans[[#This Row],[Year_made_text]],2,1))),ISNUMBER(VALUE(MID(tblLoans[[#This Row],[Year_made_text]],3,1))),ISNUMBER(VALUE(MID(tblLoans[[#This Row],[Year_made_text]],4,1))),ISNUMBER(VALUE(MID(tblLoans[[#This Row],[Year_made_text]],6,1))),ISNUMBER(VALUE(MID(tblLoans[[#This Row],[Year_made_text]],7,1))),VALUE(RIGHT(tblLoans[[#This Row],[Year_made_text]],2))=MOD(VALUE(LEFT(tblLoans[[#This Row],[Year_made_text]],4))+1,100),VALUE(LEFT(tblLoans[[#This Row],[Year_made_text]],4))>=1900,VALUE(LEFT(tblLoans[[#This Row],[Year_made_text]],4))<=2100),FALSE))),AND(tblLoans[[#This Row],[Status]]="REVIEWED",AND(NOT(OR(LOWER(TRIM(tblLoans[[#This Row],[Year_tested_text]]&""))={"","-","?","n/a","na","unk","unknown"})),NOT(IFERROR(AND(LEN(tblLoans[[#This Row],[Year_tested_text]])=7,MID(tblLoans[[#This Row],[Year_tested_text]],5,1)="-",ISNUMBER(VALUE(MID(tblLoans[[#This Row],[Year_tested_text]],1,1))),ISNUMBER(VALUE(MID(tblLoans[[#This Row],[Year_tested_text]],2,1))),ISNUMBER(VALUE(MID(tblLoans[[#This Row],[Year_tested_text]],3,1))),ISNUMBER(VALUE(MID(tblLoans[[#This Row],[Year_tested_text]],4,1))),ISNUMBER(VALUE(MID(tblLoans[[#This Row],[Year_tested_text]],6,1))),ISNUMBER(VALUE(MID(tblLoans[[#This Row],[Year_tested_text]],7,1))),VALUE(RIGHT(tblLoans[[#This Row],[Year_tested_text]],2))=MOD(VALUE(LEFT(tblLoans[[#This Row],[Year_tested_text]],4))+1,100),VALUE(LEFT(tblLoans[[#This Row],[Year_tested_text]],4))>=1900,VALUE(LEFT(tblLoans[[#This Row],[Year_tested_text]],4))<=2100),FALSE))))),"year label ","")&IF(tblLoans[[#This Row],[Status]]<>"REVIEWED","",IF(OR(AND(NOT(OR(LOWER(TRIM(tblLoans[[#This Row],[written_agreement]]&""))={"","-","?","n/a","na","unk","unknown"})),NOT(OR(LOWER(TRIM(tblLoans[[#This Row],[written_agreement]]&""))={"0","1","f","false","n","no","t","true","y","yes"}))),AND(NOT(OR(LOWER(TRIM(tblLoans[[#This Row],[terms_in_place_before_lodgment_day]]&""))={"","-","?","n/a","na","unk","unknown"})),NOT(OR(LOWER(TRIM(tblLoans[[#This Row],[terms_in_place_before_lodgment_day]]&""))={"0","1","f","false","n","no","t","true","y","yes"}))),AND(NOT(OR(LOWER(TRIM(tblLoans[[#This Row],[secured_by_registered_mortgage_over_real_property]]&""))={"","-","?","n/a","na","unk","unknown"})),NOT(OR(LOWER(TRIM(tblLoans[[#This Row],[secured_by_registered_mortgage_over_real_property]]&""))={"0","1","f","false","n","no","t","true","y","yes"})))),"true/false/unknown ","")&IF(OR(AND(NOT(OR(LOWER(TRIM(tblLoans[[#This Row],[maximum_term_years]]&""))={"","-","?","n/a","na","unk","unknown"})),OR(NOT(ISNUMBER(tblLoans[[#This Row],[maximum_term_years]])),AND(ISNUMBER(tblLoans[[#This Row],[maximum_term_years]]),OR(tblLoans[[#This Row],[maximum_term_years]]<0)))),AND(NOT(OR(LOWER(TRIM(tblLoans[[#This Row],[security_coverage_at_first_made]]&""))={"","-","?","n/a","na","unk","unknown"})),OR(NOT(ISNUMBER(tblLoans[[#This Row],[security_coverage_at_first_made]])),AND(ISNUMBER(tblLoans[[#This Row],[security_coverage_at_first_made]]),OR(tblLoans[[#This Row],[security_coverage_at_first_made]]<0)))),AND(NOT(OR(LOWER(TRIM(tblLoans[[#This Row],[interest_rate_for_years_after_year_loan_made]]&""))={"","-","?","n/a","na","unk","unknown"})),OR(NOT(ISNUMBER(tblLoans[[#This Row],[interest_rate_for_years_after_year_loan_made]])),AND(ISNUMBER(tblLoans[[#This Row],[interest_rate_for_years_after_year_loan_made]]),OR(tblLoans[[#This Row],[interest_rate_for_years_after_year_loan_made]]<0,tblLoans[[#This Row],[interest_rate_for_years_after_year_loan_made]]>1)))),AND(NOT(OR(LOWER(TRIM(tblLoans[[#This Row],[amalgamated_loan_unpaid_at_end_of_previous_year]]&""))={"","-","?","n/a","na","unk","unknown"})),OR(NOT(ISNUMBER(tblLoans[[#This Row],[amalgamated_loan_unpaid_at_end_of_previous_year]])),AND(ISNUMBER(tblLoans[[#This Row],[amalgamated_loan_unpaid_at_end_of_previous_year]]),OR(tblLoans[[#This Row],[amalgamated_loan_unpaid_at_end_of_previous_year]]<0,ROUND(N(tblLoans[[#This Row],[amalgamated_loan_unpaid_at_end_of_previous_year]]),2)<>N(tblLoans[[#This Row],[amalgamated_loan_unpaid_at_end_of_previous_year]]),N(tblLoans[[#This Row],[amalgamated_loan_unpaid_at_end_of_previous_year]])>1000000000000)))),AND(NOT(OR(LOWER(TRIM(tblLoans[[#This Row],[remaining_term_years]]&""))={"","-","?","n/a","na","unk","unknown"})),OR(NOT(ISNUMBER(tblLoans[[#This Row],[remaining_term_years]])),AND(ISNUMBER(tblLoans[[#This Row],[remaining_term_years]]),OR(tblLoans[[#This Row],[remaining_term_years]]<0)))),AND(NOT(OR(LOWER(TRIM(tblLoans[[#This Row],[payments_applied_during_the_year]]&""))={"","-","?","n/a","na","unk","unknown"})),OR(NOT(ISNUMBER(tblLoans[[#This Row],[payments_applied_during_the_year]])),AND(ISNUMBER(tblLoans[[#This Row],[payments_applied_during_the_year]]),OR(tblLoans[[#This Row],[payments_applied_during_the_year]]<0,ROUND(N(tblLoans[[#This Row],[payments_applied_during_the_year]]),2)<>N(tblLoans[[#This Row],[payments_applied_during_the_year]]),N(tblLoans[[#This Row],[payments_applied_during_the_year]])>1000000000000))))),"number ","")))) | AJ3: =IF(SUMPRODUCT((tblLoans[[#This Row],[loan_id]]&""={"L-101","L-102","L-103","L-104","L-105","L-106","L-107","L-108"})*(tblLoans[[#This Row],[Year_made_text]]&""={"2023-24","2022-23","2021-22","2024-25","2019-20","2020-21","2023-24","1996-97"}))>0,1,0) -> 1 | AK3: =TRIM(SUBSTITUTE(SUBSTITUTE(SUBSTITUTE(SUBSTITUTE(SUBSTITUTE(SUBSTITUTE(SUBSTITUTE(SUBSTITUTE(SUBSTITUTE(SUBSTITUTE(SUBSTITUTE(SUBSTITUTE(SUBSTITUTE(SUBSTITUTE(SUBSTITUTE(SUBSTITUTE(SUBSTITUTE(SUBSTITUTE(SUBSTITUTE(SUBSTITUTE(SUBSTITUTE(SUBSTITUTE(SUBSTITUTE(SUBSTITUTE(SUBSTITUTE(SUBSTITUTE(SUBSTITUTE(SUBSTITUTE(tblLoans[[#This Row],[year_loan_made]]&"",_xlfn.UNICHAR(9)," "),_xlfn.UNICHAR(10)," "),_xlfn.UNICHAR(11)," "),_xlfn.UNICHAR(12)," "),_xlfn.UNICHAR(13)," "),_xlfn.UNICHAR(28)," "),_xlfn.UNICHAR(29)," "),_xlfn.UNICHAR(30)," "),_xlfn.UNICHAR(31)," "),_xlfn.UNICHAR(133)," "),_xlfn.UNICHAR(160)," "),_xlfn.UNICHAR(5760)," "),_xlfn.UNICHAR(8192)," "),_xlfn.UNICHAR(8193)," "),_xlfn.UNICHAR(8194)," "),_xlfn.UNICHAR(8195)," "),_xlfn.UNICHAR(8196)," "),_xlfn.UNICHAR(8197)," "),_xlfn.UNICHAR(8198)," "),_xlfn.UNICHAR(8199)," "),_xlfn.UNICHAR(8200)," "),_xlfn.UNICHAR(8201)," "),_xlfn.UNICHAR(8202)," "),_xlfn.UNICHAR(8232)," "),_xlfn.UNICHAR(8233)," "),_xlfn.UNICHAR(8239)," "),_xlfn.UNICHAR(8287)," "),_xlfn.UNICHAR(12288)," ")) -> 2022-23 | AL3: =TRIM(SUBSTITUTE(SUBSTITUTE(SUBSTITUTE(SUBSTITUTE(SUBSTITUTE(SUBSTITUTE(SUBSTITUTE(SUBSTITUTE(SUBSTITUTE(SUBSTITUTE(SUBSTITUTE(SUBSTITUTE(SUBSTITUTE(SUBSTITUTE(SUBSTITUTE(SUBSTITUTE(SUBSTITUTE(SUBSTITUTE(SUBSTITUTE(SUBSTITUTE(SUBSTITUTE(SUBSTITUTE(SUBSTITUTE(SUBSTITUTE(SUBSTITUTE(SUBSTITUTE(SUBSTITUTE(SUBSTITUTE(tblLoans[[#This Row],[year_of_income_being_tested]]&"",_xlfn.UNICHAR(9)," "),_xlfn.UNICHAR(10)," "),_xlfn.UNICHAR(11)," "),_xlfn.UNICHAR(12)," "),_xlfn.UNICHAR(13)," "),_xlfn.UNICHAR(28)," "),_xlfn.UNICHAR(29)," "),_xlfn.UNICHAR(30)," "),_xlfn.UNICHAR(31)," "),_xlfn.UNICHAR(133)," "),_xlfn.UNICHAR(160)," "),_xlfn.UNICHAR(5760)," "),_xlfn.UNICHAR(8192)," "),_xlfn.UNICHAR(8193)," "),_xlfn.UNICHAR(8194)," "),_xlfn.UNICHAR(8195)," "),_xlfn.UNICHAR(8196)," "),_xlfn.UNICHAR(8197)," "),_xlfn.UNICHAR(8198)," "),_xlfn.UNICHAR(8199)," "),_xlfn.UNICHAR(8200)," "),_xlfn.UNICHAR(8201)," "),_xlfn.UNICHAR(8202)," "),_xlfn.UNICHAR(8232)," "),_xlfn.UNICHAR(8233)," "),_xlfn.UNICHAR(8239)," "),_xlfn.UNICHAR(8287)," "),_xlfn.UNICHAR(12288)," "))
A4: L-103 | B4: SYN-SHAREHOLDER-C | C4: 2021-22 | D4: unknown | E4: true | F4: 7 | G4: false | H4: unknown | I4: 0.0452 | J4: 50000 | K4: 2 | L4: 15000 | O4: =IF(TRIM(tblLoans[[#This Row],[out_of_scope_reason]]&"")<>"","SKIPPED",IF(IFERROR(VALUE(LEFT(tblLoans[[#This Row],[Year_made_text]],4))<1998,FALSE),"SKIPPED","REVIEWED")) -> REVIEWED | P4: =IF(OR(LOWER(TRIM(tblLoans[[#This Row],[Year_tested_text]]&""))={"","-","?","n/a","na","unk","unknown"}),tblLoans[[#This Row],[Year_made_text]],tblLoans[[#This Row],[Year_tested_text]]) -> 2021-22 | Q4: =IFERROR(INDEX(tblRates[rate],MATCH(tblLoans[[#This Row],[Floor_year]],tblRates[year_of_income],0)),"") -> 0.0452 | R4: =IF(OR(LOWER(TRIM(tblLoans[[#This Row],[written_agreement]]&""))={"","-","?","n/a","na","unk","unknown"}),"UNKNOWN",IF(OR(LOWER(TRIM(tblLoans[[#This Row],[written_agreement]]&""))={"1","t","true","y","yes"}),"PASS",IF(OR(LOWER(TRIM(tblLoans[[#This Row],[written_agreement]]&""))={"0","f","false","n","no"}),"FAIL","UNKNOWN"))) -> UNKNOWN | S4: =IF(OR(LOWER(TRIM(tblLoans[[#This Row],[terms_in_place_before_lodgment_day]]&""))={"","-","?","n/a","na","unk","unknown"}),"UNKNOWN",IF(OR(LOWER(TRIM(tblLoans[[#This Row],[terms_in_place_before_lodgment_day]]&""))={"1","t","true","y","yes"}),"PASS",IF(OR(LOWER(TRIM(tblLoans[[#This Row],[terms_in_place_before_lodgment_day]]&""))={"0","f","false","n","no"}),"FAIL","UNKNOWN"))) -> PASS | T4: =IF(NOT(ISNUMBER(tblLoans[[#This Row],[interest_rate_for_years_after_year_loan_made]])),"UNKNOWN",IF(tblLoans[[#This Row],[Floor_rate]]="","UNKNOWN",IF(tblLoans[[#This Row],[interest_rate_for_years_after_year_loan_made]]>=tblLoans[[#This Row],[Floor_rate]],"PASS","FAIL"))) -> PASS | U4: =IF(OR(LOWER(TRIM(tblLoans[[#This Row],[secured_by_registered_mortgage_over_real_property]]&""))={"","-","?","n/a","na","unk","unknown"}),"UNKNOWN",IF(OR(LOWER(TRIM(tblLoans[[#This Row],[secured_by_registered_mortgage_over_real_property]]&""))={"1","t","true","y","yes"}),"PASS",IF(OR(LOWER(TRIM(tblLoans[[#This Row],[secured_by_registered_mortgage_over_real_property]]&""))={"0","f","false","n","no"}),"FAIL","UNKNOWN"))) -> FAIL | V4: =IF(tblLoans[[#This Row],[Limb_secured]]="FAIL",7,IF(tblLoans[[#This Row],[Limb_secured]]="PASS",IF(ISNUMBER(tblLoans[[#This Row],[security_coverage_at_first_made]]),IF(tblLoans[[#This Row],[security_coverage_at_first_made]]>=1.1,25,7),""),"")) -> 7 | W4: =IF(NOT(ISNUMBER(tblLoans[[#This Row],[maximum_term_years]])),"UNKNOWN",IF(tblLoans[[#This Row],[Allowed_term_raw]]="",IF(tblLoans[[#This Row],[maximum_term_years]]<=7,"PASS","UNKNOWN"),IF(tblLoans[[#This Row],[maximum_term_years]]<=tblLoans[[#This Row],[Allowed_term_raw]],"PASS","FAIL"))) -> PASS | X4: =IF(tblLoans[[#This Row],[Status]]="SKIPPED","",IF(OR(LOWER(TRIM(tblLoans[[#This Row],[Floor_year]]&""))={"","-","?","n/a","na","unk","unknown"}),"UNKNOWN",IF(OR(tblLoans[[#This Row],[Limb_a_written]]="FAIL",tblLoans[[#This Row],[Limb_lodgment]]="FAIL",tblLoans[[#This Row],[Limb_b_rate]]="FAIL",tblLoans[[#This Row],[Limb_c_term]]="FAIL"),"NOT_COMPLYING",IF(OR(tblLoans[[#This Row],[Limb_a_written]]="UNKNOWN",tblLoans[[#This Row],[Limb_lodgment]]="UNKNOWN",tblLoans[[#This Row],[Limb_b_rate]]="UNKNOWN",tblLoans[[#This Row],[Limb_c_term]]="UNKNOWN"),"UNKNOWN","COMPLYING")))) -> UNKNOWN | Y4: =IF(OR(tblLoans[[#This Row],[Status]]="SKIPPED",OR(LOWER(TRIM(tblLoans[[#This Row],[Floor_year]]&""))={"","-","?","n/a","na","unk","unknown"})),"",IF(tblLoans[[#This Row],[Allowed_term_raw]]<>"",tblLoans[[#This Row],[Allowed_term_raw]],IF(AND(ISNUMBER(tblLoans[[#This Row],[maximum_term_years]]),tblLoans[[#This Row],[maximum_term_years]]<=7),7,""))) -> 7 | Z4: =IF(tblLoans[[#This Row],[Status]]="SKIPPED","",IF(ISNUMBER(tblLoans[[#This Row],[remaining_term_years]]),ROUNDUP(tblLoans[[#This Row],[remaining_term_years]],0),"")) -> 2 | AA4: =IF(AND(ISNUMBER(tblLoans[[#This Row],[amalgamated_loan_unpaid_at_end_of_previous_year]]),ISNUMBER(Summary!$B$3),Summary!$B$3>0,ISNUMBER(tblLoans[[#This Row],[Term_used]]),tblLoans[[#This Row],[Term_used]]>0),ROUND(tblLoans[[#This Row],[amalgamated_loan_unpaid_at_end_of_previous_year]]*Summary!$B$3/(1-(1/(1+Summary!$B$3))^tblLoans[[#This Row],[Term_used]]),2),"") -> 28334.8 | AB4: =IF(tblLoans[[#This Row],[Status]]="SKIPPED","",IF(OR(tblLoans[[#This Row],[Gate_verdict]]<>"COMPLYING",AND(NOT(OR(LOWER(TRIM(tblLoans[[#This Row],[Year_made_text]]&""))={"","-","?","n/a","na","unk","unknown"})),tblLoans[[#This Row],[Floor_year]]<>tblLoans[[#This Row],[Year_made_text]]),tblLoans[[#This Row],[Year_made_text]]=Summary!$B$2,IFERROR(VALUE(LEFT(tblLoans[[#This Row],[Year_made_text]],4))>Summary!$B$4,FALSE),AND(ISNUMBER(tblLoans[[#This Row],[Term_used]]),tblLoans[[#This Row],[Term_used]]<=0),AND(ISNUMBER(Summary!$B$3),Summary!$B$3<=0)),"REFUSED",IF(OR(OR(LOWER(TRIM(tblLoans[[#This Row],[Year_made_text]]&""))={"","-","?","n/a","na","unk","unknown"}),NOT(ISNUMBER(Summary!$B$3)),NOT(ISNUMBER(tblLoans[[#This Row],[amalgamated_loan_unpaid_at_end_of_previous_year]])),NOT(ISNUMBER(tblLoans[[#This Row],[payments_applied_during_the_year]])),NOT(ISNUMBER(tblLoans[[#This Row],[Term_used]]))),"UNKNOWN",IF(tblLoans[[#This Row],[MYR_raw]]-ROUND(tblLoans[[#This Row],[payments_applied_during_the_year]],2)<=0,"MYR_MET","MYR_SHORT")))) -> REFUSED | AC4: =IF(tblLoans[[#This Row],[MYR_verdict]]="REFUSED",IF(tblLoans[[#This Row],[Gate_verdict]]<>"COMPLYING","s 109N gate is "&tblLoans[[#This Row],[Gate_verdict]]&", so s 109E produces no repayment figure",IF(tblLoans[[#This Row],[Floor_year]]<>tblLoans[[#This Row],[Year_made_text]],"gate benchmark year differs from year_loan_made",IF(tblLoans[[#This Row],[Year_made_text]]=Summary!$B$2,"year of income is the year the loan was made (s 109E(1)(a), s 109P)",IF(IFERROR(VALUE(LEFT(tblLoans[[#This Row],[Year_made_text]],4))>Summary!$B$4,FALSE),"loan made after the year of income",IF(AND(ISNUMBER(tblLoans[[#This Row],[Term_used]]),tblLoans[[#This Row],[Term_used]]<=0),"nil remaining term under s 109E(6)","nil benchmark rate"))))),IF(tblLoans[[#This Row],[MYR_verdict]]="UNKNOWN",IF(OR(LOWER(TRIM(tblLoans[[#This Row],[Year_made_text]]&""))={"","-","?","n/a","na","unk","unknown"}),"year_loan_made not established",IF(NOT(ISNUMBER(Summary!$B$3)),"no reviewed benchmark rate for the year of income",IF(NOT(ISNUMBER(tblLoans[[#This Row],[amalgamated_loan_unpaid_at_end_of_previous_year]])),"unpaid balance at end of previous year not established",IF(NOT(ISNUMBER(tblLoans[[#This Row],[payments_applied_during_the_year]])),"payments applied not established","remaining term not established")))),"")) -> s 109N gate is UNKNOWN, so s 109E produces no repayment figure | AD4: =IF(OR(tblLoans[[#This Row],[MYR_verdict]]="MYR_MET",tblLoans[[#This Row],[MYR_verdict]]="MYR_SHORT"),tblLoans[[#This Row],[MYR_raw]],"") | AE4: =IF(OR(tblLoans[[#This Row],[MYR_verdict]]="MYR_MET",tblLoans[[#This Row],[MYR_verdict]]="MYR_SHORT"),MAX(0,ROUND(tblLoans[[#This Row],[MYR_raw]]-ROUND(tblLoans[[#This Row],[payments_applied_during_the_year]],2),2)),"") | AF4: =IF(tblLoans[[#This Row],[MYR_verdict]]="MYR_SHORT",tblLoans[[#This Row],[Shortfall]],"") | AG4: =IF(AND(tblLoans[[#This Row],[Status]]="REVIEWED",OR(tblLoans[[#This Row],[Gate_verdict]]="UNKNOWN",tblLoans[[#This Row],[MYR_verdict]]="UNKNOWN")),1,0) -> 1 | AH4: =IF(OR(_xlfn.ISFORMULA(tblLoans[[#This Row],[loan_id]]),_xlfn.ISFORMULA(tblLoans[[#This Row],[borrower_reference]]),_xlfn.ISFORMULA(tblLoans[[#This Row],[year_loan_made]]),_xlfn.ISFORMULA(tblLoans[[#This Row],[written_agreement]]),_xlfn.ISFORMULA(tblLoans[[#This Row],[terms_in_place_before_lodgment_day]]),_xlfn.ISFORMULA(tblLoans[[#This Row],[maximum_term_years]]),_xlfn.ISFORMULA(tblLoans[[#This Row],[secured_by_registered_mortgage_over_real_property]]),_xlfn.ISFORMULA(tblLoans[[#This Row],[security_coverage_at_first_made]]),_xlfn.ISFORMULA(tblLoans[[#This Row],[interest_rate_for_years_after_year_loan_made]]),_xlfn.ISFORMULA(tblLoans[[#This Row],[amalgamated_loan_unpaid_at_end_of_previous_year]]),_xlfn.ISFORMULA(tblLoans[[#This Row],[remaining_term_years]]),_xlfn.ISFORMULA(tblLoans[[#This Row],[payments_applied_during_the_year]]),_xlfn.ISFORMULA(tblLoans[[#This Row],[out_of_scope_reason]]),_xlfn.ISFORMULA(tblLoans[[#This Row],[year_of_income_being_tested]])),1,0) -> 0 | AI4: =IF(TRIM(tblLoans[[#This Row],[out_of_scope_reason]]&"")<>"","",TRIM(IF(OR(AND(NOT(OR(LOWER(TRIM(tblLoans[[#This Row],[Year_made_text]]&""))={"","-","?","n/a","na","unk","unknown"})),NOT(IFERROR(AND(LEN(tblLoans[[#This Row],[Year_made_text]])=7,MID(tblLoans[[#This Row],[Year_made_text]],5,1)="-",ISNUMBER(VALUE(MID(tblLoans[[#This Row],[Year_made_text]],1,1))),ISNUMBER(VALUE(MID(tblLoans[[#This Row],[Year_made_text]],2,1))),ISNUMBER(VALUE(MID(tblLoans[[#This Row],[Year_made_text]],3,1))),ISNUMBER(VALUE(MID(tblLoans[[#This Row],[Year_made_text]],4,1))),ISNUMBER(VALUE(MID(tblLoans[[#This Row],[Year_made_text]],6,1))),ISNUMBER(VALUE(MID(tblLoans[[#This Row],[Year_made_text]],7,1))),VALUE(RIGHT(tblLoans[[#This Row],[Year_made_text]],2))=MOD(VALUE(LEFT(tblLoans[[#This Row],[Year_made_text]],4))+1,100),VALUE(LEFT(tblLoans[[#This Row],[Year_made_text]],4))>=1900,VALUE(LEFT(tblLoans[[#This Row],[Year_made_text]],4))<=2100),FALSE))),AND(tblLoans[[#This Row],[Status]]="REVIEWED",AND(NOT(OR(LOWER(TRIM(tblLoans[[#This Row],[Year_tested_text]]&""))={"","-","?","n/a","na","unk","unknown"})),NOT(IFERROR(AND(LEN(tblLoans[[#This Row],[Year_tested_text]])=7,MID(tblLoans[[#This Row],[Year_tested_text]],5,1)="-",ISNUMBER(VALUE(MID(tblLoans[[#This Row],[Year_tested_text]],1,1))),ISNUMBER(VALUE(MID(tblLoans[[#This Row],[Year_tested_text]],2,1))),ISNUMBER(VALUE(MID(tblLoans[[#This Row],[Year_tested_text]],3,1))),ISNUMBER(VALUE(MID(tblLoans[[#This Row],[Year_tested_text]],4,1))),ISNUMBER(VALUE(MID(tblLoans[[#This Row],[Year_tested_text]],6,1))),ISNUMBER(VALUE(MID(tblLoans[[#This Row],[Year_tested_text]],7,1))),VALUE(RIGHT(tblLoans[[#This Row],[Year_tested_text]],2))=MOD(VALUE(LEFT(tblLoans[[#This Row],[Year_tested_text]],4))+1,100),VALUE(LEFT(tblLoans[[#This Row],[Year_tested_text]],4))>=1900,VALUE(LEFT(tblLoans[[#This Row],[Year_tested_text]],4))<=2100),FALSE))))),"year label ","")&IF(tblLoans[[#This Row],[Status]]<>"REVIEWED","",IF(OR(AND(NOT(OR(LOWER(TRIM(tblLoans[[#This Row],[written_agreement]]&""))={"","-","?","n/a","na","unk","unknown"})),NOT(OR(LOWER(TRIM(tblLoans[[#This Row],[written_agreement]]&""))={"0","1","f","false","n","no","t","true","y","yes"}))),AND(NOT(OR(LOWER(TRIM(tblLoans[[#This Row],[terms_in_place_before_lodgment_day]]&""))={"","-","?","n/a","na","unk","unknown"})),NOT(OR(LOWER(TRIM(tblLoans[[#This Row],[terms_in_place_before_lodgment_day]]&""))={"0","1","f","false","n","no","t","true","y","yes"}))),AND(NOT(OR(LOWER(TRIM(tblLoans[[#This Row],[secured_by_registered_mortgage_over_real_property]]&""))={"","-","?","n/a","na","unk","unknown"})),NOT(OR(LOWER(TRIM(tblLoans[[#This Row],[secured_by_registered_mortgage_over_real_property]]&""))={"0","1","f","false","n","no","t","true","y","yes"})))),"true/false/unknown ","")&IF(OR(AND(NOT(OR(LOWER(TRIM(tblLoans[[#This Row],[maximum_term_years]]&""))={"","-","?","n/a","na","unk","unknown"})),OR(NOT(ISNUMBER(tblLoans[[#This Row],[maximum_term_years]])),AND(ISNUMBER(tblLoans[[#This Row],[maximum_term_years]]),OR(tblLoans[[#This Row],[maximum_term_years]]<0)))),AND(NOT(OR(LOWER(TRIM(tblLoans[[#This Row],[security_coverage_at_first_made]]&""))={"","-","?","n/a","na","unk","unknown"})),OR(NOT(ISNUMBER(tblLoans[[#This Row],[security_coverage_at_first_made]])),AND(ISNUMBER(tblLoans[[#This Row],[security_coverage_at_first_made]]),OR(tblLoans[[#This Row],[security_coverage_at_first_made]]<0)))),AND(NOT(OR(LOWER(TRIM(tblLoans[[#This Row],[interest_rate_for_years_after_year_loan_made]]&""))={"","-","?","n/a","na","unk","unknown"})),OR(NOT(ISNUMBER(tblLoans[[#This Row],[interest_rate_for_years_after_year_loan_made]])),AND(ISNUMBER(tblLoans[[#This Row],[interest_rate_for_years_after_year_loan_made]]),OR(tblLoans[[#This Row],[interest_rate_for_years_after_year_loan_made]]<0,tblLoans[[#This Row],[interest_rate_for_years_after_year_loan_made]]>1)))),AND(NOT(OR(LOWER(TRIM(tblLoans[[#This Row],[amalgamated_loan_unpaid_at_end_of_previous_year]]&""))={"","-","?","n/a","na","unk","unknown"})),OR(NOT(ISNUMBER(tblLoans[[#This Row],[amalgamated_loan_unpaid_at_end_of_previous_year]])),AND(ISNUMBER(tblLoans[[#This Row],[amalgamated_loan_unpaid_at_end_of_previous_year]]),OR(tblLoans[[#This Row],[amalgamated_loan_unpaid_at_end_of_previous_year]]<0,ROUND(N(tblLoans[[#This Row],[amalgamated_loan_unpaid_at_end_of_previous_year]]),2)<>N(tblLoans[[#This Row],[amalgamated_loan_unpaid_at_end_of_previous_year]]),N(tblLoans[[#This Row],[amalgamated_loan_unpaid_at_end_of_previous_year]])>1000000000000)))),AND(NOT(OR(LOWER(TRIM(tblLoans[[#This Row],[remaining_term_years]]&""))={"","-","?","n/a","na","unk","unknown"})),OR(NOT(ISNUMBER(tblLoans[[#This Row],[remaining_term_years]])),AND(ISNUMBER(tblLoans[[#This Row],[remaining_term_years]]),OR(tblLoans[[#This Row],[remaining_term_years]]<0)))),AND(NOT(OR(LOWER(TRIM(tblLoans[[#This Row],[payments_applied_during_the_year]]&""))={"","-","?","n/a","na","unk","unknown"})),OR(NOT(ISNUMBER(tblLoans[[#This Row],[payments_applied_during_the_year]])),AND(ISNUMBER(tblLoans[[#This Row],[payments_applied_during_the_year]]),OR(tblLoans[[#This Row],[payments_applied_during_the_year]]<0,ROUND(N(tblLoans[[#This Row],[payments_applied_during_the_year]]),2)<>N(tblLoans[[#This Row],[payments_applied_during_the_year]]),N(tblLoans[[#This Row],[payments_applied_during_the_year]])>1000000000000))))),"number ","")))) | AJ4: =IF(SUMPRODUCT((tblLoans[[#This Row],[loan_id]]&""={"L-101","L-102","L-103","L-104","L-105","L-106","L-107","L-108"})*(tblLoans[[#This Row],[Year_made_text]]&""={"2023-24","2022-23","2021-22","2024-25","2019-20","2020-21","2023-24","1996-97"}))>0,1,0) -> 1 | AK4: =TRIM(SUBSTITUTE(SUBSTITUTE(SUBSTITUTE(SUBSTITUTE(SUBSTITUTE(SUBSTITUTE(SUBSTITUTE(SUBSTITUTE(SUBSTITUTE(SUBSTITUTE(SUBSTITUTE(SUBSTITUTE(SUBSTITUTE(SUBSTITUTE(SUBSTITUTE(SUBSTITUTE(SUBSTITUTE(SUBSTITUTE(SUBSTITUTE(SUBSTITUTE(SUBSTITUTE(SUBSTITUTE(SUBSTITUTE(SUBSTITUTE(SUBSTITUTE(SUBSTITUTE(SUBSTITUTE(SUBSTITUTE(tblLoans[[#This Row],[year_loan_made]]&"",_xlfn.UNICHAR(9)," "),_xlfn.UNICHAR(10)," "),_xlfn.UNICHAR(11)," "),_xlfn.UNICHAR(12)," "),_xlfn.UNICHAR(13)," "),_xlfn.UNICHAR(28)," "),_xlfn.UNICHAR(29)," "),_xlfn.UNICHAR(30)," "),_xlfn.UNICHAR(31)," "),_xlfn.UNICHAR(133)," "),_xlfn.UNICHAR(160)," "),_xlfn.UNICHAR(5760)," "),_xlfn.UNICHAR(8192)," "),_xlfn.UNICHAR(8193)," "),_xlfn.UNICHAR(8194)," "),_xlfn.UNICHAR(8195)," "),_xlfn.UNICHAR(8196)," "),_xlfn.UNICHAR(8197)," "),_xlfn.UNICHAR(8198)," "),_xlfn.UNICHAR(8199)," "),_xlfn.UNICHAR(8200)," "),_xlfn.UNICHAR(8201)," "),_xlfn.UNICHAR(8202)," "),_xlfn.UNICHAR(8232)," "),_xlfn.UNICHAR(8233)," "),_xlfn.UNICHAR(8239)," "),_xlfn.UNICHAR(8287)," "),_xlfn.UNICHAR(12288)," ")) -> 2021-22 | AL4: =TRIM(SUBSTITUTE(SUBSTITUTE(SUBSTITUTE(SUBSTITUTE(SUBSTITUTE(SUBSTITUTE(SUBSTITUTE(SUBSTITUTE(SUBSTITUTE(SUBSTITUTE(SUBSTITUTE(SUBSTITUTE(SUBSTITUTE(SUBSTITUTE(SUBSTITUTE(SUBSTITUTE(SUBSTITUTE(SUBSTITUTE(SUBSTITUTE(SUBSTITUTE(SUBSTITUTE(SUBSTITUTE(SUBSTITUTE(SUBSTITUTE(SUBSTITUTE(SUBSTITUTE(SUBSTITUTE(SUBSTITUTE(tblLoans[[#This Row],[year_of_income_being_tested]]&"",_xlfn.UNICHAR(9)," "),_xlfn.UNICHAR(10)," "),_xlfn.UNICHAR(11)," "),_xlfn.UNICHAR(12)," "),_xlfn.UNICHAR(13)," "),_xlfn.UNICHAR(28)," "),_xlfn.UNICHAR(29)," "),_xlfn.UNICHAR(30)," "),_xlfn.UNICHAR(31)," "),_xlfn.UNICHAR(133)," "),_xlfn.UNICHAR(160)," "),_xlfn.UNICHAR(5760)," "),_xlfn.UNICHAR(8192)," "),_xlfn.UNICHAR(8193)," "),_xlfn.UNICHAR(8194)," "),_xlfn.UNICHAR(8195)," "),_xlfn.UNICHAR(8196)," "),_xlfn.UNICHAR(8197)," "),_xlfn.UNICHAR(8198)," "),_xlfn.UNICHAR(8199)," "),_xlfn.UNICHAR(8200)," "),_xlfn.UNICHAR(8201)," "),_xlfn.UNICHAR(8202)," "),_xlfn.UNICHAR(8232)," "),_xlfn.UNICHAR(8233)," "),_xlfn.UNICHAR(8239)," "),_xlfn.UNICHAR(8287)," "),_xlfn.UNICHAR(12288)," "))
A5: L-104 | B5: SYN-ASSOCIATE-D | C5: 2024-25 | D5: true | E5: true | F5: 7 | G5: false | H5: unknown | I5: 0.0877 | J5: 88000 | K5: 5 | L5: unknown | O5: =IF(TRIM(tblLoans[[#This Row],[out_of_scope_reason]]&"")<>"","SKIPPED",IF(IFERROR(VALUE(LEFT(tblLoans[[#This Row],[Year_made_text]],4))<1998,FALSE),"SKIPPED","REVIEWED")) -> REVIEWED | P5: =IF(OR(LOWER(TRIM(tblLoans[[#This Row],[Year_tested_text]]&""))={"","-","?","n/a","na","unk","unknown"}),tblLoans[[#This Row],[Year_made_text]],tblLoans[[#This Row],[Year_tested_text]]) -> 2024-25 | Q5: =IFERROR(INDEX(tblRates[rate],MATCH(tblLoans[[#This Row],[Floor_year]],tblRates[year_of_income],0)),"") -> 0.0877 | R5: =IF(OR(LOWER(TRIM(tblLoans[[#This Row],[written_agreement]]&""))={"","-","?","n/a","na","unk","unknown"}),"UNKNOWN",IF(OR(LOWER(TRIM(tblLoans[[#This Row],[written_agreement]]&""))={"1","t","true","y","yes"}),"PASS",IF(OR(LOWER(TRIM(tblLoans[[#This Row],[written_agreement]]&""))={"0","f","false","n","no"}),"FAIL","UNKNOWN"))) -> PASS | S5: =IF(OR(LOWER(TRIM(tblLoans[[#This Row],[terms_in_place_before_lodgment_day]]&""))={"","-","?","n/a","na","unk","unknown"}),"UNKNOWN",IF(OR(LOWER(TRIM(tblLoans[[#This Row],[terms_in_place_before_lodgment_day]]&""))={"1","t","true","y","yes"}),"PASS",IF(OR(LOWER(TRIM(tblLoans[[#This Row],[terms_in_place_before_lodgment_day]]&""))={"0","f","false","n","no"}),"FAIL","UNKNOWN"))) -> PASS | T5: =IF(NOT(ISNUMBER(tblLoans[[#This Row],[interest_rate_for_years_after_year_loan_made]])),"UNKNOWN",IF(tblLoans[[#This Row],[Floor_rate]]="","UNKNOWN",IF(tblLoans[[#This Row],[interest_rate_for_years_after_year_loan_made]]>=tblLoans[[#This Row],[Floor_rate]],"PASS","FAIL"))) -> PASS | U5: =IF(OR(LOWER(TRIM(tblLoans[[#This Row],[secured_by_registered_mortgage_over_real_property]]&""))={"","-","?","n/a","na","unk","unknown"}),"UNKNOWN",IF(OR(LOWER(TRIM(tblLoans[[#This Row],[secured_by_registered_mortgage_over_real_property]]&""))={"1","t","true","y","yes"}),"PASS",IF(OR(LOWER(TRIM(tblLoans[[#This Row],[secured_by_registered_mortgage_over_real_property]]&""))={"0","f","false","n","no"}),"FAIL","UNKNOWN"))) -> FAIL | V5: =IF(tblLoans[[#This Row],[Limb_secured]]="FAIL",7,IF(tblLoans[[#This Row],[Limb_secured]]="PASS",IF(ISNUMBER(tblLoans[[#This Row],[security_coverage_at_first_made]]),IF(tblLoans[[#This Row],[security_coverage_at_first_made]]>=1.1,25,7),""),"")) -> 7 | W5: =IF(NOT(ISNUMBER(tblLoans[[#This Row],[maximum_term_years]])),"UNKNOWN",IF(tblLoans[[#This Row],[Allowed_term_raw]]="",IF(tblLoans[[#This Row],[maximum_term_years]]<=7,"PASS","UNKNOWN"),IF(tblLoans[[#This Row],[maximum_term_years]]<=tblLoans[[#This Row],[Allowed_term_raw]],"PASS","FAIL"))) -> PASS | X5: =IF(tblLoans[[#This Row],[Status]]="SKIPPED","",IF(OR(LOWER(TRIM(tblLoans[[#This Row],[Floor_year]]&""))={"","-","?","n/a","na","unk","unknown"}),"UNKNOWN",IF(OR(tblLoans[[#This Row],[Limb_a_written]]="FAIL",tblLoans[[#This Row],[Limb_lodgment]]="FAIL",tblLoans[[#This Row],[Limb_b_rate]]="FAIL",tblLoans[[#This Row],[Limb_c_term]]="FAIL"),"NOT_COMPLYING",IF(OR(tblLoans[[#This Row],[Limb_a_written]]="UNKNOWN",tblLoans[[#This Row],[Limb_lodgment]]="UNKNOWN",tblLoans[[#This Row],[Limb_b_rate]]="UNKNOWN",tblLoans[[#This Row],[Limb_c_term]]="UNKNOWN"),"UNKNOWN","COMPLYING")))) -> COMPLYING | Y5: =IF(OR(tblLoans[[#This Row],[Status]]="SKIPPED",OR(LOWER(TRIM(tblLoans[[#This Row],[Floor_year]]&""))={"","-","?","n/a","na","unk","unknown"})),"",IF(tblLoans[[#This Row],[Allowed_term_raw]]<>"",tblLoans[[#This Row],[Allowed_term_raw]],IF(AND(ISNUMBER(tblLoans[[#This Row],[maximum_term_years]]),tblLoans[[#This Row],[maximum_term_years]]<=7),7,""))) -> 7 | Z5: =IF(tblLoans[[#This Row],[Status]]="SKIPPED","",IF(ISNUMBER(tblLoans[[#This Row],[remaining_term_years]]),ROUNDUP(tblLoans[[#This Row],[remaining_term_years]],0),"")) -> 5 | AA5: =IF(AND(ISNUMBER(tblLoans[[#This Row],[amalgamated_loan_unpaid_at_end_of_previous_year]]),ISNUMBER(Summary!$B$3),Summary!$B$3>0,ISNUMBER(tblLoans[[#This Row],[Term_used]]),tblLoans[[#This Row],[Term_used]]>0),ROUND(tblLoans[[#This Row],[amalgamated_loan_unpaid_at_end_of_previous_year]]*Summary!$B$3/(1-(1/(1+Summary!$B$3))^tblLoans[[#This Row],[Term_used]]),2),"") -> 22489.28 | AB5: =IF(tblLoans[[#This Row],[Status]]="SKIPPED","",IF(OR(tblLoans[[#This Row],[Gate_verdict]]<>"COMPLYING",AND(NOT(OR(LOWER(TRIM(tblLoans[[#This Row],[Year_made_text]]&""))={"","-","?","n/a","na","unk","unknown"})),tblLoans[[#This Row],[Floor_year]]<>tblLoans[[#This Row],[Year_made_text]]),tblLoans[[#This Row],[Year_made_text]]=Summary!$B$2,IFERROR(VALUE(LEFT(tblLoans[[#This Row],[Year_made_text]],4))>Summary!$B$4,FALSE),AND(ISNUMBER(tblLoans[[#This Row],[Term_used]]),tblLoans[[#This Row],[Term_used]]<=0),AND(ISNUMBER(Summary!$B$3),Summary!$B$3<=0)),"REFUSED",IF(OR(OR(LOWER(TRIM(tblLoans[[#This Row],[Year_made_text]]&""))={"","-","?","n/a","na","unk","unknown"}),NOT(ISNUMBER(Summary!$B$3)),NOT(ISNUMBER(tblLoans[[#This Row],[amalgamated_loan_unpaid_at_end_of_previous_year]])),NOT(ISNUMBER(tblLoans[[#This Row],[payments_applied_during_the_year]])),NOT(ISNUMBER(tblLoans[[#This Row],[Term_used]]))),"UNKNOWN",IF(tblLoans[[#This Row],[MYR_raw]]-ROUND(tblLoans[[#This Row],[payments_applied_during_the_year]],2)<=0,"MYR_MET","MYR_SHORT")))) -> UNKNOWN | AC5: =IF(tblLoans[[#This Row],[MYR_verdict]]="REFUSED",IF(tblLoans[[#This Row],[Gate_verdict]]<>"COMPLYING","s 109N gate is "&tblLoans[[#This Row],[Gate_verdict]]&", so s 109E produces no repayment figure",IF(tblLoans[[#This Row],[Floor_year]]<>tblLoans[[#This Row],[Year_made_text]],"gate benchmark year differs from year_loan_made",IF(tblLoans[[#This Row],[Year_made_text]]=Summary!$B$2,"year of income is the year the loan was made (s 109E(1)(a), s 109P)",IF(IFERROR(VALUE(LEFT(tblLoans[[#This Row],[Year_made_text]],4))>Summary!$B$4,FALSE),"loan made after the year of income",IF(AND(ISNUMBER(tblLoans[[#This Row],[Term_used]]),tblLoans[[#This Row],[Term_used]]<=0),"nil remaining term under s 109E(6)","nil benchmark rate"))))),IF(tblLoans[[#This Row],[MYR_verdict]]="UNKNOWN",IF(OR(LOWER(TRIM(tblLoans[[#This Row],[Year_made_text]]&""))={"","-","?","n/a","na","unk","unknown"}),"year_loan_made not established",IF(NOT(ISNUMBER(Summary!$B$3)),"no reviewed benchmark rate for the year of income",IF(NOT(ISNUMBER(tblLoans[[#This Row],[amalgamated_loan_unpaid_at_end_of_previous_year]])),"unpaid balance at end of previous year not established",IF(NOT(ISNUMBER(tblLoans[[#This Row],[payments_applied_during_the_year]])),"payments applied not established","remaining term not established")))),"")) -> payments applied not established | AD5: =IF(OR(tblLoans[[#This Row],[MYR_verdict]]="MYR_MET",tblLoans[[#This Row],[MYR_verdict]]="MYR_SHORT"),tblLoans[[#This Row],[MYR_raw]],"") | AE5: =IF(OR(tblLoans[[#This Row],[MYR_verdict]]="MYR_MET",tblLoans[[#This Row],[MYR_verdict]]="MYR_SHORT"),MAX(0,ROUND(tblLoans[[#This Row],[MYR_raw]]-ROUND(tblLoans[[#This Row],[payments_applied_during_the_year]],2),2)),"") | AF5: =IF(tblLoans[[#This Row],[MYR_verdict]]="MYR_SHORT",tblLoans[[#This Row],[Shortfall]],"") | AG5: =IF(AND(tblLoans[[#This Row],[Status]]="REVIEWED",OR(tblLoans[[#This Row],[Gate_verdict]]="UNKNOWN",tblLoans[[#This Row],[MYR_verdict]]="UNKNOWN")),1,0) -> 1 | AH5: =IF(OR(_xlfn.ISFORMULA(tblLoans[[#This Row],[loan_id]]),_xlfn.ISFORMULA(tblLoans[[#This Row],[borrower_reference]]),_xlfn.ISFORMULA(tblLoans[[#This Row],[year_loan_made]]),_xlfn.ISFORMULA(tblLoans[[#This Row],[written_agreement]]),_xlfn.ISFORMULA(tblLoans[[#This Row],[terms_in_place_before_lodgment_day]]),_xlfn.ISFORMULA(tblLoans[[#This Row],[maximum_term_years]]),_xlfn.ISFORMULA(tblLoans[[#This Row],[secured_by_registered_mortgage_over_real_property]]),_xlfn.ISFORMULA(tblLoans[[#This Row],[security_coverage_at_first_made]]),_xlfn.ISFORMULA(tblLoans[[#This Row],[interest_rate_for_years_after_year_loan_made]]),_xlfn.ISFORMULA(tblLoans[[#This Row],[amalgamated_loan_unpaid_at_end_of_previous_year]]),_xlfn.ISFORMULA(tblLoans[[#This Row],[remaining_term_years]]),_xlfn.ISFORMULA(tblLoans[[#This Row],[payments_applied_during_the_year]]),_xlfn.ISFORMULA(tblLoans[[#This Row],[out_of_scope_reason]]),_xlfn.ISFORMULA(tblLoans[[#This Row],[year_of_income_being_tested]])),1,0) -> 0 | AI5: =IF(TRIM(tblLoans[[#This Row],[out_of_scope_reason]]&"")<>"","",TRIM(IF(OR(AND(NOT(OR(LOWER(TRIM(tblLoans[[#This Row],[Year_made_text]]&""))={"","-","?","n/a","na","unk","unknown"})),NOT(IFERROR(AND(LEN(tblLoans[[#This Row],[Year_made_text]])=7,MID(tblLoans[[#This Row],[Year_made_text]],5,1)="-",ISNUMBER(VALUE(MID(tblLoans[[#This Row],[Year_made_text]],1,1))),ISNUMBER(VALUE(MID(tblLoans[[#This Row],[Year_made_text]],2,1))),ISNUMBER(VALUE(MID(tblLoans[[#This Row],[Year_made_text]],3,1))),ISNUMBER(VALUE(MID(tblLoans[[#This Row],[Year_made_text]],4,1))),ISNUMBER(VALUE(MID(tblLoans[[#This Row],[Year_made_text]],6,1))),ISNUMBER(VALUE(MID(tblLoans[[#This Row],[Year_made_text]],7,1))),VALUE(RIGHT(tblLoans[[#This Row],[Year_made_text]],2))=MOD(VALUE(LEFT(tblLoans[[#This Row],[Year_made_text]],4))+1,100),VALUE(LEFT(tblLoans[[#This Row],[Year_made_text]],4))>=1900,VALUE(LEFT(tblLoans[[#This Row],[Year_made_text]],4))<=2100),FALSE))),AND(tblLoans[[#This Row],[Status]]="REVIEWED",AND(NOT(OR(LOWER(TRIM(tblLoans[[#This Row],[Year_tested_text]]&""))={"","-","?","n/a","na","unk","unknown"})),NOT(IFERROR(AND(LEN(tblLoans[[#This Row],[Year_tested_text]])=7,MID(tblLoans[[#This Row],[Year_tested_text]],5,1)="-",ISNUMBER(VALUE(MID(tblLoans[[#This Row],[Year_tested_text]],1,1))),ISNUMBER(VALUE(MID(tblLoans[[#This Row],[Year_tested_text]],2,1))),ISNUMBER(VALUE(MID(tblLoans[[#This Row],[Year_tested_text]],3,1))),ISNUMBER(VALUE(MID(tblLoans[[#This Row],[Year_tested_text]],4,1))),ISNUMBER(VALUE(MID(tblLoans[[#This Row],[Year_tested_text]],6,1))),ISNUMBER(VALUE(MID(tblLoans[[#This Row],[Year_tested_text]],7,1))),VALUE(RIGHT(tblLoans[[#This Row],[Year_tested_text]],2))=MOD(VALUE(LEFT(tblLoans[[#This Row],[Year_tested_text]],4))+1,100),VALUE(LEFT(tblLoans[[#This Row],[Year_tested_text]],4))>=1900,VALUE(LEFT(tblLoans[[#This Row],[Year_tested_text]],4))<=2100),FALSE))))),"year label ","")&IF(tblLoans[[#This Row],[Status]]<>"REVIEWED","",IF(OR(AND(NOT(OR(LOWER(TRIM(tblLoans[[#This Row],[written_agreement]]&""))={"","-","?","n/a","na","unk","unknown"})),NOT(OR(LOWER(TRIM(tblLoans[[#This Row],[written_agreement]]&""))={"0","1","f","false","n","no","t","true","y","yes"}))),AND(NOT(OR(LOWER(TRIM(tblLoans[[#This Row],[terms_in_place_before_lodgment_day]]&""))={"","-","?","n/a","na","unk","unknown"})),NOT(OR(LOWER(TRIM(tblLoans[[#This Row],[terms_in_place_before_lodgment_day]]&""))={"0","1","f","false","n","no","t","true","y","yes"}))),AND(NOT(OR(LOWER(TRIM(tblLoans[[#This Row],[secured_by_registered_mortgage_over_real_property]]&""))={"","-","?","n/a","na","unk","unknown"})),NOT(OR(LOWER(TRIM(tblLoans[[#This Row],[secured_by_registered_mortgage_over_real_property]]&""))={"0","1","f","false","n","no","t","true","y","yes"})))),"true/false/unknown ","")&IF(OR(AND(NOT(OR(LOWER(TRIM(tblLoans[[#This Row],[maximum_term_years]]&""))={"","-","?","n/a","na","unk","unknown"})),OR(NOT(ISNUMBER(tblLoans[[#This Row],[maximum_term_years]])),AND(ISNUMBER(tblLoans[[#This Row],[maximum_term_years]]),OR(tblLoans[[#This Row],[maximum_term_years]]<0)))),AND(NOT(OR(LOWER(TRIM(tblLoans[[#This Row],[security_coverage_at_first_made]]&""))={"","-","?","n/a","na","unk","unknown"})),OR(NOT(ISNUMBER(tblLoans[[#This Row],[security_coverage_at_first_made]])),AND(ISNUMBER(tblLoans[[#This Row],[security_coverage_at_first_made]]),OR(tblLoans[[#This Row],[security_coverage_at_first_made]]<0)))),AND(NOT(OR(LOWER(TRIM(tblLoans[[#This Row],[interest_rate_for_years_after_year_loan_made]]&""))={"","-","?","n/a","na","unk","unknown"})),OR(NOT(ISNUMBER(tblLoans[[#This Row],[interest_rate_for_years_after_year_loan_made]])),AND(ISNUMBER(tblLoans[[#This Row],[interest_rate_for_years_after_year_loan_made]]),OR(tblLoans[[#This Row],[interest_rate_for_years_after_year_loan_made]]<0,tblLoans[[#This Row],[interest_rate_for_years_after_year_loan_made]]>1)))),AND(NOT(OR(LOWER(TRIM(tblLoans[[#This Row],[amalgamated_loan_unpaid_at_end_of_previous_year]]&""))={"","-","?","n/a","na","unk","unknown"})),OR(NOT(ISNUMBER(tblLoans[[#This Row],[amalgamated_loan_unpaid_at_end_of_previous_year]])),AND(ISNUMBER(tblLoans[[#This Row],[amalgamated_loan_unpaid_at_end_of_previous_year]]),OR(tblLoans[[#This Row],[amalgamated_loan_unpaid_at_end_of_previous_year]]<0,ROUND(N(tblLoans[[#This Row],[amalgamated_loan_unpaid_at_end_of_previous_year]]),2)<>N(tblLoans[[#This Row],[amalgamated_loan_unpaid_at_end_of_previous_year]]),N(tblLoans[[#This Row],[amalgamated_loan_unpaid_at_end_of_previous_year]])>1000000000000)))),AND(NOT(OR(LOWER(TRIM(tblLoans[[#This Row],[remaining_term_years]]&""))={"","-","?","n/a","na","unk","unknown"})),OR(NOT(ISNUMBER(tblLoans[[#This Row],[remaining_term_years]])),AND(ISNUMBER(tblLoans[[#This Row],[remaining_term_years]]),OR(tblLoans[[#This Row],[remaining_term_years]]<0)))),AND(NOT(OR(LOWER(TRIM(tblLoans[[#This Row],[payments_applied_during_the_year]]&""))={"","-","?","n/a","na","unk","unknown"})),OR(NOT(ISNUMBER(tblLoans[[#This Row],[payments_applied_during_the_year]])),AND(ISNUMBER(tblLoans[[#This Row],[payments_applied_during_the_year]]),OR(tblLoans[[#This Row],[payments_applied_during_the_year]]<0,ROUND(N(tblLoans[[#This Row],[payments_applied_during_the_year]]),2)<>N(tblLoans[[#This Row],[payments_applied_during_the_year]]),N(tblLoans[[#This Row],[payments_applied_during_the_year]])>1000000000000))))),"number ","")))) | AJ5: =IF(SUMPRODUCT((tblLoans[[#This Row],[loan_id]]&""={"L-101","L-102","L-103","L-104","L-105","L-106","L-107","L-108"})*(tblLoans[[#This Row],[Year_made_text]]&""={"2023-24","2022-23","2021-22","2024-25","2019-20","2020-21","2023-24","1996-97"}))>0,1,0) -> 1 | AK5: =TRIM(SUBSTITUTE(SUBSTITUTE(SUBSTITUTE(SUBSTITUTE(SUBSTITUTE(SUBSTITUTE(SUBSTITUTE(SUBSTITUTE(SUBSTITUTE(SUBSTITUTE(SUBSTITUTE(SUBSTITUTE(SUBSTITUTE(SUBSTITUTE(SUBSTITUTE(SUBSTITUTE(SUBSTITUTE(SUBSTITUTE(SUBSTITUTE(SUBSTITUTE(SUBSTITUTE(SUBSTITUTE(SUBSTITUTE(SUBSTITUTE(SUBSTITUTE(SUBSTITUTE(SUBSTITUTE(SUBSTITUTE(tblLoans[[#This Row],[year_loan_made]]&"",_xlfn.UNICHAR(9)," "),_xlfn.UNICHAR(10)," "),_xlfn.UNICHAR(11)," "),_xlfn.UNICHAR(12)," "),_xlfn.UNICHAR(13)," "),_xlfn.UNICHAR(28)," "),_xlfn.UNICHAR(29)," "),_xlfn.UNICHAR(30)," "),_xlfn.UNICHAR(31)," "),_xlfn.UNICHAR(133)," "),_xlfn.UNICHAR(160)," "),_xlfn.UNICHAR(5760)," "),_xlfn.UNICHAR(8192)," "),_xlfn.UNICHAR(8193)," "),_xlfn.UNICHAR(8194)," "),_xlfn.UNICHAR(8195)," "),_xlfn.UNICHAR(8196)," "),_xlfn.UNICHAR(8197)," "),_xlfn.UNICHAR(8198)," "),_xlfn.UNICHAR(8199)," "),_xlfn.UNICHAR(8200)," "),_xlfn.UNICHAR(8201)," "),_xlfn.UNICHAR(8202)," "),_xlfn.UNICHAR(8232)," "),_xlfn.UNICHAR(8233)," "),_xlfn.UNICHAR(8239)," "),_xlfn.UNICHAR(8287)," "),_xlfn.UNICHAR(12288)," ")) -> 2024-25 | AL5: =TRIM(SUBSTITUTE(SUBSTITUTE(SUBSTITUTE(SUBSTITUTE(SUBSTITUTE(SUBSTITUTE(SUBSTITUTE(SUBSTITUTE(SUBSTITUTE(SUBSTITUTE(SUBSTITUTE(SUBSTITUTE(SUBSTITUTE(SUBSTITUTE(SUBSTITUTE(SUBSTITUTE(SUBSTITUTE(SUBSTITUTE(SUBSTITUTE(SUBSTITUTE(SUBSTITUTE(SUBSTITUTE(SUBSTITUTE(SUBSTITUTE(SUBSTITUTE(SUBSTITUTE(SUBSTITUTE(SUBSTITUTE(tblLoans[[#This Row],[year_of_income_being_tested]]&"",_xlfn.UNICHAR(9)," "),_xlfn.UNICHAR(10)," "),_xlfn.UNICHAR(11)," "),_xlfn.UNICHAR(12)," "),_xlfn.UNICHAR(13)," "),_xlfn.UNICHAR(28)," "),_xlfn.UNICHAR(29)," "),_xlfn.UNICHAR(30)," "),_xlfn.UNICHAR(31)," "),_xlfn.UNICHAR(133)," "),_xlfn.UNICHAR(160)," "),_xlfn.UNICHAR(5760)," "),_xlfn.UNICHAR(8192)," "),_xlfn.UNICHAR(8193)," "),_xlfn.UNICHAR(8194)," "),_xlfn.UNICHAR(8195)," "),_xlfn.UNICHAR(8196)," "),_xlfn.UNICHAR(8197)," "),_xlfn.UNICHAR(8198)," "),_xlfn.UNICHAR(8199)," "),_xlfn.UNICHAR(8200)," "),_xlfn.UNICHAR(8201)," "),_xlfn.UNICHAR(8202)," "),_xlfn.UNICHAR(8232)," "),_xlfn.UNICHAR(8233)," "),_xlfn.UNICHAR(8239)," "),_xlfn.UNICHAR(8287)," "),_xlfn.UNICHAR(12288)," "))
A6: L-105 | B6: SYN-SHAREHOLDER-E | C6: 2019-20 | D6: true | E6: true | F6: 7 | G6: false | H6: unknown | I6: 0.0537 | J6: 12000 | K6: 0 | L6: 12000 | O6: =IF(TRIM(tblLoans[[#This Row],[out_of_scope_reason]]&"")<>"","SKIPPED",IF(IFERROR(VALUE(LEFT(tblLoans[[#This Row],[Year_made_text]],4))<1998,FALSE),"SKIPPED","REVIEWED")) -> REVIEWED | P6: =IF(OR(LOWER(TRIM(tblLoans[[#This Row],[Year_tested_text]]&""))={"","-","?","n/a","na","unk","unknown"}),tblLoans[[#This Row],[Year_made_text]],tblLoans[[#This Row],[Year_tested_text]]) -> 2019-20 | Q6: =IFERROR(INDEX(tblRates[rate],MATCH(tblLoans[[#This Row],[Floor_year]],tblRates[year_of_income],0)),"") -> 0.0537 | R6: =IF(OR(LOWER(TRIM(tblLoans[[#This Row],[written_agreement]]&""))={"","-","?","n/a","na","unk","unknown"}),"UNKNOWN",IF(OR(LOWER(TRIM(tblLoans[[#This Row],[written_agreement]]&""))={"1","t","true","y","yes"}),"PASS",IF(OR(LOWER(TRIM(tblLoans[[#This Row],[written_agreement]]&""))={"0","f","false","n","no"}),"FAIL","UNKNOWN"))) -> PASS | S6: =IF(OR(LOWER(TRIM(tblLoans[[#This Row],[terms_in_place_before_lodgment_day]]&""))={"","-","?","n/a","na","unk","unknown"}),"UNKNOWN",IF(OR(LOWER(TRIM(tblLoans[[#This Row],[terms_in_place_before_lodgment_day]]&""))={"1","t","true","y","yes"}),"PASS",IF(OR(LOWER(TRIM(tblLoans[[#This Row],[terms_in_place_before_lodgment_day]]&""))={"0","f","false","n","no"}),"FAIL","UNKNOWN"))) -> PASS | T6: =IF(NOT(ISNUMBER(tblLoans[[#This Row],[interest_rate_for_years_after_year_loan_made]])),"UNKNOWN",IF(tblLoans[[#This Row],[Floor_rate]]="","UNKNOWN",IF(tblLoans[[#This Row],[interest_rate_for_years_after_year_loan_made]]>=tblLoans[[#This Row],[Floor_rate]],"PASS","FAIL"))) -> PASS | U6: =IF(OR(LOWER(TRIM(tblLoans[[#This Row],[secured_by_registered_mortgage_over_real_property]]&""))={"","-","?","n/a","na","unk","unknown"}),"UNKNOWN",IF(OR(LOWER(TRIM(tblLoans[[#This Row],[secured_by_registered_mortgage_over_real_property]]&""))={"1","t","true","y","yes"}),"PASS",IF(OR(LOWER(TRIM(tblLoans[[#This Row],[secured_by_registered_mortgage_over_real_property]]&""))={"0","f","false","n","no"}),"FAIL","UNKNOWN"))) -> FAIL | V6: =IF(tblLoans[[#This Row],[Limb_secured]]="FAIL",7,IF(tblLoans[[#This Row],[Limb_secured]]="PASS",IF(ISNUMBER(tblLoans[[#This Row],[security_coverage_at_first_made]]),IF(tblLoans[[#This Row],[security_coverage_at_first_made]]>=1.1,25,7),""),"")) -> 7 | W6: =IF(NOT(ISNUMBER(tblLoans[[#This Row],[maximum_term_years]])),"UNKNOWN",IF(tblLoans[[#This Row],[Allowed_term_raw]]="",IF(tblLoans[[#This Row],[maximum_term_years]]<=7,"PASS","UNKNOWN"),IF(tblLoans[[#This Row],[maximum_term_years]]<=tblLoans[[#This Row],[Allowed_term_raw]],"PASS","FAIL"))) -> PASS | X6: =IF(tblLoans[[#This Row],[Status]]="SKIPPED","",IF(OR(LOWER(TRIM(tblLoans[[#This Row],[Floor_year]]&""))={"","-","?","n/a","na","unk","unknown"}),"UNKNOWN",IF(OR(tblLoans[[#This Row],[Limb_a_written]]="FAIL",tblLoans[[#This Row],[Limb_lodgment]]="FAIL",tblLoans[[#This Row],[Limb_b_rate]]="FAIL",tblLoans[[#This Row],[Limb_c_term]]="FAIL"),"NOT_COMPLYING",IF(OR(tblLoans[[#This Row],[Limb_a_written]]="UNKNOWN",tblLoans[[#This Row],[Limb_lodgment]]="UNKNOWN",tblLoans[[#This Row],[Limb_b_rate]]="UNKNOWN",tblLoans[[#This Row],[Limb_c_term]]="UNKNOWN"),"UNKNOWN","COMPLYING")))) -> COMPLYING | Y6: =IF(OR(tblLoans[[#This Row],[Status]]="SKIPPED",OR(LOWER(TRIM(tblLoans[[#This Row],[Floor_year]]&""))={"","-","?","n/a","na","unk","unknown"})),"",IF(tblLoans[[#This Row],[Allowed_term_raw]]<>"",tblLoans[[#This Row],[Allowed_term_raw]],IF(AND(ISNUMBER(tblLoans[[#This Row],[maximum_term_years]]),tblLoans[[#This Row],[maximum_term_years]]<=7),7,""))) -> 7 | Z6: =IF(tblLoans[[#This Row],[Status]]="SKIPPED","",IF(ISNUMBER(tblLoans[[#This Row],[remaining_term_years]]),ROUNDUP(tblLoans[[#This Row],[remaining_term_years]],0),"")) -> 0 | AA6: =IF(AND(ISNUMBER(tblLoans[[#This Row],[amalgamated_loan_unpaid_at_end_of_previous_year]]),ISNUMBER(Summary!$B$3),Summary!$B$3>0,ISNUMBER(tblLoans[[#This Row],[Term_used]]),tblLoans[[#This Row],[Term_used]]>0),ROUND(tblLoans[[#This Row],[amalgamated_loan_unpaid_at_end_of_previous_year]]*Summary!$B$3/(1-(1/(1+Summary!$B$3))^tblLoans[[#This Row],[Term_used]]),2),"") | AB6: =IF(tblLoans[[#This Row],[Status]]="SKIPPED","",IF(OR(tblLoans[[#This Row],[Gate_verdict]]<>"COMPLYING",AND(NOT(OR(LOWER(TRIM(tblLoans[[#This Row],[Year_made_text]]&""))={"","-","?","n/a","na","unk","unknown"})),tblLoans[[#This Row],[Floor_year]]<>tblLoans[[#This Row],[Year_made_text]]),tblLoans[[#This Row],[Year_made_text]]=Summary!$B$2,IFERROR(VALUE(LEFT(tblLoans[[#This Row],[Year_made_text]],4))>Summary!$B$4,FALSE),AND(ISNUMBER(tblLoans[[#This Row],[Term_used]]),tblLoans[[#This Row],[Term_used]]<=0),AND(ISNUMBER(Summary!$B$3),Summary!$B$3<=0)),"REFUSED",IF(OR(OR(LOWER(TRIM(tblLoans[[#This Row],[Year_made_text]]&""))={"","-","?","n/a","na","unk","unknown"}),NOT(ISNUMBER(Summary!$B$3)),NOT(ISNUMBER(tblLoans[[#This Row],[amalgamated_loan_unpaid_at_end_of_previous_year]])),NOT(ISNUMBER(tblLoans[[#This Row],[payments_applied_during_the_year]])),NOT(ISNUMBER(tblLoans[[#This Row],[Term_used]]))),"UNKNOWN",IF(tblLoans[[#This Row],[MYR_raw]]-ROUND(tblLoans[[#This Row],[payments_applied_during_the_year]],2)<=0,"MYR_MET","MYR_SHORT")))) -> REFUSED | AC6: =IF(tblLoans[[#This Row],[MYR_verdict]]="REFUSED",IF(tblLoans[[#This Row],[Gate_verdict]]<>"COMPLYING","s 109N gate is "&tblLoans[[#This Row],[Gate_verdict]]&", so s 109E produces no repayment figure",IF(tblLoans[[#This Row],[Floor_year]]<>tblLoans[[#This Row],[Year_made_text]],"gate benchmark year differs from year_loan_made",IF(tblLoans[[#This Row],[Year_made_text]]=Summary!$B$2,"year of income is the year the loan was made (s 109E(1)(a), s 109P)",IF(IFERROR(VALUE(LEFT(tblLoans[[#This Row],[Year_made_text]],4))>Summary!$B$4,FALSE),"loan made after the year of income",IF(AND(ISNUMBER(tblLoans[[#This Row],[Term_used]]),tblLoans[[#This Row],[Term_used]]<=0),"nil remaining term under s 109E(6)","nil benchmark rate"))))),IF(tblLoans[[#This Row],[MYR_verdict]]="UNKNOWN",IF(OR(LOWER(TRIM(tblLoans[[#This Row],[Year_made_text]]&""))={"","-","?","n/a","na","unk","unknown"}),"year_loan_made not established",IF(NOT(ISNUMBER(Summary!$B$3)),"no reviewed benchmark rate for the year of income",IF(NOT(ISNUMBER(tblLoans[[#This Row],[amalgamated_loan_unpaid_at_end_of_previous_year]])),"unpaid balance at end of previous year not established",IF(NOT(ISNUMBER(tblLoans[[#This Row],[payments_applied_during_the_year]])),"payments applied not established","remaining term not established")))),"")) -> nil remaining term under s 109E(6) | AD6: =IF(OR(tblLoans[[#This Row],[MYR_verdict]]="MYR_MET",tblLoans[[#This Row],[MYR_verdict]]="MYR_SHORT"),tblLoans[[#This Row],[MYR_raw]],"") | AE6: =IF(OR(tblLoans[[#This Row],[MYR_verdict]]="MYR_MET",tblLoans[[#This Row],[MYR_verdict]]="MYR_SHORT"),MAX(0,ROUND(tblLoans[[#This Row],[MYR_raw]]-ROUND(tblLoans[[#This Row],[payments_applied_during_the_year]],2),2)),"") | AF6: =IF(tblLoans[[#This Row],[MYR_verdict]]="MYR_SHORT",tblLoans[[#This Row],[Shortfall]],"") | AG6: =IF(AND(tblLoans[[#This Row],[Status]]="REVIEWED",OR(tblLoans[[#This Row],[Gate_verdict]]="UNKNOWN",tblLoans[[#This Row],[MYR_verdict]]="UNKNOWN")),1,0) -> 0 | AH6: =IF(OR(_xlfn.ISFORMULA(tblLoans[[#This Row],[loan_id]]),_xlfn.ISFORMULA(tblLoans[[#This Row],[borrower_reference]]),_xlfn.ISFORMULA(tblLoans[[#This Row],[year_loan_made]]),_xlfn.ISFORMULA(tblLoans[[#This Row],[written_agreement]]),_xlfn.ISFORMULA(tblLoans[[#This Row],[terms_in_place_before_lodgment_day]]),_xlfn.ISFORMULA(tblLoans[[#This Row],[maximum_term_years]]),_xlfn.ISFORMULA(tblLoans[[#This Row],[secured_by_registered_mortgage_over_real_property]]),_xlfn.ISFORMULA(tblLoans[[#This Row],[security_coverage_at_first_made]]),_xlfn.ISFORMULA(tblLoans[[#This Row],[interest_rate_for_years_after_year_loan_made]]),_xlfn.ISFORMULA(tblLoans[[#This Row],[amalgamated_loan_unpaid_at_end_of_previous_year]]),_xlfn.ISFORMULA(tblLoans[[#This Row],[remaining_term_years]]),_xlfn.ISFORMULA(tblLoans[[#This Row],[payments_applied_during_the_year]]),_xlfn.ISFORMULA(tblLoans[[#This Row],[out_of_scope_reason]]),_xlfn.ISFORMULA(tblLoans[[#This Row],[year_of_income_being_tested]])),1,0) -> 0 | AI6: =IF(TRIM(tblLoans[[#This Row],[out_of_scope_reason]]&"")<>"","",TRIM(IF(OR(AND(NOT(OR(LOWER(TRIM(tblLoans[[#This Row],[Year_made_text]]&""))={"","-","?","n/a","na","unk","unknown"})),NOT(IFERROR(AND(LEN(tblLoans[[#This Row],[Year_made_text]])=7,MID(tblLoans[[#This Row],[Year_made_text]],5,1)="-",ISNUMBER(VALUE(MID(tblLoans[[#This Row],[Year_made_text]],1,1))),ISNUMBER(VALUE(MID(tblLoans[[#This Row],[Year_made_text]],2,1))),ISNUMBER(VALUE(MID(tblLoans[[#This Row],[Year_made_text]],3,1))),ISNUMBER(VALUE(MID(tblLoans[[#This Row],[Year_made_text]],4,1))),ISNUMBER(VALUE(MID(tblLoans[[#This Row],[Year_made_text]],6,1))),ISNUMBER(VALUE(MID(tblLoans[[#This Row],[Year_made_text]],7,1))),VALUE(RIGHT(tblLoans[[#This Row],[Year_made_text]],2))=MOD(VALUE(LEFT(tblLoans[[#This Row],[Year_made_text]],4))+1,100),VALUE(LEFT(tblLoans[[#This Row],[Year_made_text]],4))>=1900,VALUE(LEFT(tblLoans[[#This Row],[Year_made_text]],4))<=2100),FALSE))),AND(tblLoans[[#This Row],[Status]]="REVIEWED",AND(NOT(OR(LOWER(TRIM(tblLoans[[#This Row],[Year_tested_text]]&""))={"","-","?","n/a","na","unk","unknown"})),NOT(IFERROR(AND(LEN(tblLoans[[#This Row],[Year_tested_text]])=7,MID(tblLoans[[#This Row],[Year_tested_text]],5,1)="-",ISNUMBER(VALUE(MID(tblLoans[[#This Row],[Year_tested_text]],1,1))),ISNUMBER(VALUE(MID(tblLoans[[#This Row],[Year_tested_text]],2,1))),ISNUMBER(VALUE(MID(tblLoans[[#This Row],[Year_tested_text]],3,1))),ISNUMBER(VALUE(MID(tblLoans[[#This Row],[Year_tested_text]],4,1))),ISNUMBER(VALUE(MID(tblLoans[[#This Row],[Year_tested_text]],6,1))),ISNUMBER(VALUE(MID(tblLoans[[#This Row],[Year_tested_text]],7,1))),VALUE(RIGHT(tblLoans[[#This Row],[Year_tested_text]],2))=MOD(VALUE(LEFT(tblLoans[[#This Row],[Year_tested_text]],4))+1,100),VALUE(LEFT(tblLoans[[#This Row],[Year_tested_text]],4))>=1900,VALUE(LEFT(tblLoans[[#This Row],[Year_tested_text]],4))<=2100),FALSE))))),"year label ","")&IF(tblLoans[[#This Row],[Status]]<>"REVIEWED","",IF(OR(AND(NOT(OR(LOWER(TRIM(tblLoans[[#This Row],[written_agreement]]&""))={"","-","?","n/a","na","unk","unknown"})),NOT(OR(LOWER(TRIM(tblLoans[[#This Row],[written_agreement]]&""))={"0","1","f","false","n","no","t","true","y","yes"}))),AND(NOT(OR(LOWER(TRIM(tblLoans[[#This Row],[terms_in_place_before_lodgment_day]]&""))={"","-","?","n/a","na","unk","unknown"})),NOT(OR(LOWER(TRIM(tblLoans[[#This Row],[terms_in_place_before_lodgment_day]]&""))={"0","1","f","false","n","no","t","true","y","yes"}))),AND(NOT(OR(LOWER(TRIM(tblLoans[[#This Row],[secured_by_registered_mortgage_over_real_property]]&""))={"","-","?","n/a","na","unk","unknown"})),NOT(OR(LOWER(TRIM(tblLoans[[#This Row],[secured_by_registered_mortgage_over_real_property]]&""))={"0","1","f","false","n","no","t","true","y","yes"})))),"true/false/unknown ","")&IF(OR(AND(NOT(OR(LOWER(TRIM(tblLoans[[#This Row],[maximum_term_years]]&""))={"","-","?","n/a","na","unk","unknown"})),OR(NOT(ISNUMBER(tblLoans[[#This Row],[maximum_term_years]])),AND(ISNUMBER(tblLoans[[#This Row],[maximum_term_years]]),OR(tblLoans[[#This Row],[maximum_term_years]]<0)))),AND(NOT(OR(LOWER(TRIM(tblLoans[[#This Row],[security_coverage_at_first_made]]&""))={"","-","?","n/a","na","unk","unknown"})),OR(NOT(ISNUMBER(tblLoans[[#This Row],[security_coverage_at_first_made]])),AND(ISNUMBER(tblLoans[[#This Row],[security_coverage_at_first_made]]),OR(tblLoans[[#This Row],[security_coverage_at_first_made]]<0)))),AND(NOT(OR(LOWER(TRIM(tblLoans[[#This Row],[interest_rate_for_years_after_year_loan_made]]&""))={"","-","?","n/a","na","unk","unknown"})),OR(NOT(ISNUMBER(tblLoans[[#This Row],[interest_rate_for_years_after_year_loan_made]])),AND(ISNUMBER(tblLoans[[#This Row],[interest_rate_for_years_after_year_loan_made]]),OR(tblLoans[[#This Row],[interest_rate_for_years_after_year_loan_made]]<0,tblLoans[[#This Row],[interest_rate_for_years_after_year_loan_made]]>1)))),AND(NOT(OR(LOWER(TRIM(tblLoans[[#This Row],[amalgamated_loan_unpaid_at_end_of_previous_year]]&""))={"","-","?","n/a","na","unk","unknown"})),OR(NOT(ISNUMBER(tblLoans[[#This Row],[amalgamated_loan_unpaid_at_end_of_previous_year]])),AND(ISNUMBER(tblLoans[[#This Row],[amalgamated_loan_unpaid_at_end_of_previous_year]]),OR(tblLoans[[#This Row],[amalgamated_loan_unpaid_at_end_of_previous_year]]<0,ROUND(N(tblLoans[[#This Row],[amalgamated_loan_unpaid_at_end_of_previous_year]]),2)<>N(tblLoans[[#This Row],[amalgamated_loan_unpaid_at_end_of_previous_year]]),N(tblLoans[[#This Row],[amalgamated_loan_unpaid_at_end_of_previous_year]])>1000000000000)))),AND(NOT(OR(LOWER(TRIM(tblLoans[[#This Row],[remaining_term_years]]&""))={"","-","?","n/a","na","unk","unknown"})),OR(NOT(ISNUMBER(tblLoans[[#This Row],[remaining_term_years]])),AND(ISNUMBER(tblLoans[[#This Row],[remaining_term_years]]),OR(tblLoans[[#This Row],[remaining_term_years]]<0)))),AND(NOT(OR(LOWER(TRIM(tblLoans[[#This Row],[payments_applied_during_the_year]]&""))={"","-","?","n/a","na","unk","unknown"})),OR(NOT(ISNUMBER(tblLoans[[#This Row],[payments_applied_during_the_year]])),AND(ISNUMBER(tblLoans[[#This Row],[payments_applied_during_the_year]]),OR(tblLoans[[#This Row],[payments_applied_during_the_year]]<0,ROUND(N(tblLoans[[#This Row],[payments_applied_during_the_year]]),2)<>N(tblLoans[[#This Row],[payments_applied_during_the_year]]),N(tblLoans[[#This Row],[payments_applied_during_the_year]])>1000000000000))))),"number ","")))) | AJ6: =IF(SUMPRODUCT((tblLoans[[#This Row],[loan_id]]&""={"L-101","L-102","L-103","L-104","L-105","L-106","L-107","L-108"})*(tblLoans[[#This Row],[Year_made_text]]&""={"2023-24","2022-23","2021-22","2024-25","2019-20","2020-21","2023-24","1996-97"}))>0,1,0) -> 1 | AK6: =TRIM(SUBSTITUTE(SUBSTITUTE(SUBSTITUTE(SUBSTITUTE(SUBSTITUTE(SUBSTITUTE(SUBSTITUTE(SUBSTITUTE(SUBSTITUTE(SUBSTITUTE(SUBSTITUTE(SUBSTITUTE(SUBSTITUTE(SUBSTITUTE(SUBSTITUTE(SUBSTITUTE(SUBSTITUTE(SUBSTITUTE(SUBSTITUTE(SUBSTITUTE(SUBSTITUTE(SUBSTITUTE(SUBSTITUTE(SUBSTITUTE(SUBSTITUTE(SUBSTITUTE(SUBSTITUTE(SUBSTITUTE(tblLoans[[#This Row],[year_loan_made]]&"",_xlfn.UNICHAR(9)," "),_xlfn.UNICHAR(10)," "),_xlfn.UNICHAR(11)," "),_xlfn.UNICHAR(12)," "),_xlfn.UNICHAR(13)," "),_xlfn.UNICHAR(28)," "),_xlfn.UNICHAR(29)," "),_xlfn.UNICHAR(30)," "),_xlfn.UNICHAR(31)," "),_xlfn.UNICHAR(133)," "),_xlfn.UNICHAR(160)," "),_xlfn.UNICHAR(5760)," "),_xlfn.UNICHAR(8192)," "),_xlfn.UNICHAR(8193)," "),_xlfn.UNICHAR(8194)," "),_xlfn.UNICHAR(8195)," "),_xlfn.UNICHAR(8196)," "),_xlfn.UNICHAR(8197)," "),_xlfn.UNICHAR(8198)," "),_xlfn.UNICHAR(8199)," "),_xlfn.UNICHAR(8200)," "),_xlfn.UNICHAR(8201)," "),_xlfn.UNICHAR(8202)," "),_xlfn.UNICHAR(8232)," "),_xlfn.UNICHAR(8233)," "),_xlfn.UNICHAR(8239)," "),_xlfn.UNICHAR(8287)," "),_xlfn.UNICHAR(12288)," ")) -> 2019-20 | AL6: =TRIM(SUBSTITUTE(SUBSTITUTE(SUBSTITUTE(SUBSTITUTE(SUBSTITUTE(SUBSTITUTE(SUBSTITUTE(SUBSTITUTE(SUBSTITUTE(SUBSTITUTE(SUBSTITUTE(SUBSTITUTE(SUBSTITUTE(SUBSTITUTE(SUBSTITUTE(SUBSTITUTE(SUBSTITUTE(SUBSTITUTE(SUBSTITUTE(SUBSTITUTE(SUBSTITUTE(SUBSTITUTE(SUBSTITUTE(SUBSTITUTE(SUBSTITUTE(SUBSTITUTE(SUBSTITUTE(SUBSTITUTE(tblLoans[[#This Row],[year_of_income_being_tested]]&"",_xlfn.UNICHAR(9)," "),_xlfn.UNICHAR(10)," "),_xlfn.UNICHAR(11)," "),_xlfn.UNICHAR(12)," "),_xlfn.UNICHAR(13)," "),_xlfn.UNICHAR(28)," "),_xlfn.UNICHAR(29)," "),_xlfn.UNICHAR(30)," "),_xlfn.UNICHAR(31)," "),_xlfn.UNICHAR(133)," "),_xlfn.UNICHAR(160)," "),_xlfn.UNICHAR(5760)," "),_xlfn.UNICHAR(8192)," "),_xlfn.UNICHAR(8193)," "),_xlfn.UNICHAR(8194)," "),_xlfn.UNICHAR(8195)," "),_xlfn.UNICHAR(8196)," "),_xlfn.UNICHAR(8197)," "),_xlfn.UNICHAR(8198)," "),_xlfn.UNICHAR(8199)," "),_xlfn.UNICHAR(8200)," "),_xlfn.UNICHAR(8201)," "),_xlfn.UNICHAR(8202)," "),_xlfn.UNICHAR(8232)," "),_xlfn.UNICHAR(8233)," "),_xlfn.UNICHAR(8239)," "),_xlfn.UNICHAR(8287)," "),_xlfn.UNICHAR(12288)," "))
A7: L-106 | B7: SYN-ASSOCIATE-F | C7: 2020-21 | D7: true | E7: true | F7: 25 | G7: true | H7: 1.09 | I7: 0.0452 | J7: 300000 | K7: 15 | L7: 30000 | O7: =IF(TRIM(tblLoans[[#This Row],[out_of_scope_reason]]&"")<>"","SKIPPED",IF(IFERROR(VALUE(LEFT(tblLoans[[#This Row],[Year_made_text]],4))<1998,FALSE),"SKIPPED","REVIEWED")) -> REVIEWED | P7: =IF(OR(LOWER(TRIM(tblLoans[[#This Row],[Year_tested_text]]&""))={"","-","?","n/a","na","unk","unknown"}),tblLoans[[#This Row],[Year_made_text]],tblLoans[[#This Row],[Year_tested_text]]) -> 2020-21 | Q7: =IFERROR(INDEX(tblRates[rate],MATCH(tblLoans[[#This Row],[Floor_year]],tblRates[year_of_income],0)),"") -> 0.0452 | R7: =IF(OR(LOWER(TRIM(tblLoans[[#This Row],[written_agreement]]&""))={"","-","?","n/a","na","unk","unknown"}),"UNKNOWN",IF(OR(LOWER(TRIM(tblLoans[[#This Row],[written_agreement]]&""))={"1","t","true","y","yes"}),"PASS",IF(OR(LOWER(TRIM(tblLoans[[#This Row],[written_agreement]]&""))={"0","f","false","n","no"}),"FAIL","UNKNOWN"))) -> PASS | S7: =IF(OR(LOWER(TRIM(tblLoans[[#This Row],[terms_in_place_before_lodgment_day]]&""))={"","-","?","n/a","na","unk","unknown"}),"UNKNOWN",IF(OR(LOWER(TRIM(tblLoans[[#This Row],[terms_in_place_before_lodgment_day]]&""))={"1","t","true","y","yes"}),"PASS",IF(OR(LOWER(TRIM(tblLoans[[#This Row],[terms_in_place_before_lodgment_day]]&""))={"0","f","false","n","no"}),"FAIL","UNKNOWN"))) -> PASS | T7: =IF(NOT(ISNUMBER(tblLoans[[#This Row],[interest_rate_for_years_after_year_loan_made]])),"UNKNOWN",IF(tblLoans[[#This Row],[Floor_rate]]="","UNKNOWN",IF(tblLoans[[#This Row],[interest_rate_for_years_after_year_loan_made]]>=tblLoans[[#This Row],[Floor_rate]],"PASS","FAIL"))) -> PASS | U7: =IF(OR(LOWER(TRIM(tblLoans[[#This Row],[secured_by_registered_mortgage_over_real_property]]&""))={"","-","?","n/a","na","unk","unknown"}),"UNKNOWN",IF(OR(LOWER(TRIM(tblLoans[[#This Row],[secured_by_registered_mortgage_over_real_property]]&""))={"1","t","true","y","yes"}),"PASS",IF(OR(LOWER(TRIM(tblLoans[[#This Row],[secured_by_registered_mortgage_over_real_property]]&""))={"0","f","false","n","no"}),"FAIL","UNKNOWN"))) -> PASS | V7: =IF(tblLoans[[#This Row],[Limb_secured]]="FAIL",7,IF(tblLoans[[#This Row],[Limb_secured]]="PASS",IF(ISNUMBER(tblLoans[[#This Row],[security_coverage_at_first_made]]),IF(tblLoans[[#This Row],[security_coverage_at_first_made]]>=1.1,25,7),""),"")) -> 7 | W7: =IF(NOT(ISNUMBER(tblLoans[[#This Row],[maximum_term_years]])),"UNKNOWN",IF(tblLoans[[#This Row],[Allowed_term_raw]]="",IF(tblLoans[[#This Row],[maximum_term_years]]<=7,"PASS","UNKNOWN"),IF(tblLoans[[#This Row],[maximum_term_years]]<=tblLoans[[#This Row],[Allowed_term_raw]],"PASS","FAIL"))) -> FAIL | X7: =IF(tblLoans[[#This Row],[Status]]="SKIPPED","",IF(OR(LOWER(TRIM(tblLoans[[#This Row],[Floor_year]]&""))={"","-","?","n/a","na","unk","unknown"}),"UNKNOWN",IF(OR(tblLoans[[#This Row],[Limb_a_written]]="FAIL",tblLoans[[#This Row],[Limb_lodgment]]="FAIL",tblLoans[[#This Row],[Limb_b_rate]]="FAIL",tblLoans[[#This Row],[Limb_c_term]]="FAIL"),"NOT_COMPLYING",IF(OR(tblLoans[[#This Row],[Limb_a_written]]="UNKNOWN",tblLoans[[#This Row],[Limb_lodgment]]="UNKNOWN",tblLoans[[#This Row],[Limb_b_rate]]="UNKNOWN",tblLoans[[#This Row],[Limb_c_term]]="UNKNOWN"),"UNKNOWN","COMPLYING")))) -> NOT_COMPLYING | Y7: =IF(OR(tblLoans[[#This Row],[Status]]="SKIPPED",OR(LOWER(TRIM(tblLoans[[#This Row],[Floor_year]]&""))={"","-","?","n/a","na","unk","unknown"})),"",IF(tblLoans[[#This Row],[Allowed_term_raw]]<>"",tblLoans[[#This Row],[Allowed_term_raw]],IF(AND(ISNUMBER(tblLoans[[#This Row],[maximum_term_years]]),tblLoans[[#This Row],[maximum_term_years]]<=7),7,""))) -> 7 | Z7: =IF(tblLoans[[#This Row],[Status]]="SKIPPED","",IF(ISNUMBER(tblLoans[[#This Row],[remaining_term_years]]),ROUNDUP(tblLoans[[#This Row],[remaining_term_years]],0),"")) -> 15 | AA7: =IF(AND(ISNUMBER(tblLoans[[#This Row],[amalgamated_loan_unpaid_at_end_of_previous_year]]),ISNUMBER(Summary!$B$3),Summary!$B$3>0,ISNUMBER(tblLoans[[#This Row],[Term_used]]),tblLoans[[#This Row],[Term_used]]>0),ROUND(tblLoans[[#This Row],[amalgamated_loan_unpaid_at_end_of_previous_year]]*Summary!$B$3/(1-(1/(1+Summary!$B$3))^tblLoans[[#This Row],[Term_used]]),2),"") -> 36713.81 | AB7: =IF(tblLoans[[#This Row],[Status]]="SKIPPED","",IF(OR(tblLoans[[#This Row],[Gate_verdict]]<>"COMPLYING",AND(NOT(OR(LOWER(TRIM(tblLoans[[#This Row],[Year_made_text]]&""))={"","-","?","n/a","na","unk","unknown"})),tblLoans[[#This Row],[Floor_year]]<>tblLoans[[#This Row],[Year_made_text]]),tblLoans[[#This Row],[Year_made_text]]=Summary!$B$2,IFERROR(VALUE(LEFT(tblLoans[[#This Row],[Year_made_text]],4))>Summary!$B$4,FALSE),AND(ISNUMBER(tblLoans[[#This Row],[Term_used]]),tblLoans[[#This Row],[Term_used]]<=0),AND(ISNUMBER(Summary!$B$3),Summary!$B$3<=0)),"REFUSED",IF(OR(OR(LOWER(TRIM(tblLoans[[#This Row],[Year_made_text]]&""))={"","-","?","n/a","na","unk","unknown"}),NOT(ISNUMBER(Summary!$B$3)),NOT(ISNUMBER(tblLoans[[#This Row],[amalgamated_loan_unpaid_at_end_of_previous_year]])),NOT(ISNUMBER(tblLoans[[#This Row],[payments_applied_during_the_year]])),NOT(ISNUMBER(tblLoans[[#This Row],[Term_used]]))),"UNKNOWN",IF(tblLoans[[#This Row],[MYR_raw]]-ROUND(tblLoans[[#This Row],[payments_applied_during_the_year]],2)<=0,"MYR_MET","MYR_SHORT")))) -> REFUSED | AC7: =IF(tblLoans[[#This Row],[MYR_verdict]]="REFUSED",IF(tblLoans[[#This Row],[Gate_verdict]]<>"COMPLYING","s 109N gate is "&tblLoans[[#This Row],[Gate_verdict]]&", so s 109E produces no repayment figure",IF(tblLoans[[#This Row],[Floor_year]]<>tblLoans[[#This Row],[Year_made_text]],"gate benchmark year differs from year_loan_made",IF(tblLoans[[#This Row],[Year_made_text]]=Summary!$B$2,"year of income is the year the loan was made (s 109E(1)(a), s 109P)",IF(IFERROR(VALUE(LEFT(tblLoans[[#This Row],[Year_made_text]],4))>Summary!$B$4,FALSE),"loan made after the year of income",IF(AND(ISNUMBER(tblLoans[[#This Row],[Term_used]]),tblLoans[[#This Row],[Term_used]]<=0),"nil remaining term under s 109E(6)","nil benchmark rate"))))),IF(tblLoans[[#This Row],[MYR_verdict]]="UNKNOWN",IF(OR(LOWER(TRIM(tblLoans[[#This Row],[Year_made_text]]&""))={"","-","?","n/a","na","unk","unknown"}),"year_loan_made not established",IF(NOT(ISNUMBER(Summary!$B$3)),"no reviewed benchmark rate for the year of income",IF(NOT(ISNUMBER(tblLoans[[#This Row],[amalgamated_loan_unpaid_at_end_of_previous_year]])),"unpaid balance at end of previous year not established",IF(NOT(ISNUMBER(tblLoans[[#This Row],[payments_applied_during_the_year]])),"payments applied not established","remaining term not established")))),"")) -> s 109N gate is NOT_COMPLYING, so s 109E produces no repayment figure | AD7: =IF(OR(tblLoans[[#This Row],[MYR_verdict]]="MYR_MET",tblLoans[[#This Row],[MYR_verdict]]="MYR_SHORT"),tblLoans[[#This Row],[MYR_raw]],"") | AE7: =IF(OR(tblLoans[[#This Row],[MYR_verdict]]="MYR_MET",tblLoans[[#This Row],[MYR_verdict]]="MYR_SHORT"),MAX(0,ROUND(tblLoans[[#This Row],[MYR_raw]]-ROUND(tblLoans[[#This Row],[payments_applied_during_the_year]],2),2)),"") | AF7: =IF(tblLoans[[#This Row],[MYR_verdict]]="MYR_SHORT",tblLoans[[#This Row],[Shortfall]],"") | AG7: =IF(AND(tblLoans[[#This Row],[Status]]="REVIEWED",OR(tblLoans[[#This Row],[Gate_verdict]]="UNKNOWN",tblLoans[[#This Row],[MYR_verdict]]="UNKNOWN")),1,0) -> 0 | AH7: =IF(OR(_xlfn.ISFORMULA(tblLoans[[#This Row],[loan_id]]),_xlfn.ISFORMULA(tblLoans[[#This Row],[borrower_reference]]),_xlfn.ISFORMULA(tblLoans[[#This Row],[year_loan_made]]),_xlfn.ISFORMULA(tblLoans[[#This Row],[written_agreement]]),_xlfn.ISFORMULA(tblLoans[[#This Row],[terms_in_place_before_lodgment_day]]),_xlfn.ISFORMULA(tblLoans[[#This Row],[maximum_term_years]]),_xlfn.ISFORMULA(tblLoans[[#This Row],[secured_by_registered_mortgage_over_real_property]]),_xlfn.ISFORMULA(tblLoans[[#This Row],[security_coverage_at_first_made]]),_xlfn.ISFORMULA(tblLoans[[#This Row],[interest_rate_for_years_after_year_loan_made]]),_xlfn.ISFORMULA(tblLoans[[#This Row],[amalgamated_loan_unpaid_at_end_of_previous_year]]),_xlfn.ISFORMULA(tblLoans[[#This Row],[remaining_term_years]]),_xlfn.ISFORMULA(tblLoans[[#This Row],[payments_applied_during_the_year]]),_xlfn.ISFORMULA(tblLoans[[#This Row],[out_of_scope_reason]]),_xlfn.ISFORMULA(tblLoans[[#This Row],[year_of_income_being_tested]])),1,0) -> 0 | AI7: =IF(TRIM(tblLoans[[#This Row],[out_of_scope_reason]]&"")<>"","",TRIM(IF(OR(AND(NOT(OR(LOWER(TRIM(tblLoans[[#This Row],[Year_made_text]]&""))={"","-","?","n/a","na","unk","unknown"})),NOT(IFERROR(AND(LEN(tblLoans[[#This Row],[Year_made_text]])=7,MID(tblLoans[[#This Row],[Year_made_text]],5,1)="-",ISNUMBER(VALUE(MID(tblLoans[[#This Row],[Year_made_text]],1,1))),ISNUMBER(VALUE(MID(tblLoans[[#This Row],[Year_made_text]],2,1))),ISNUMBER(VALUE(MID(tblLoans[[#This Row],[Year_made_text]],3,1))),ISNUMBER(VALUE(MID(tblLoans[[#This Row],[Year_made_text]],4,1))),ISNUMBER(VALUE(MID(tblLoans[[#This Row],[Year_made_text]],6,1))),ISNUMBER(VALUE(MID(tblLoans[[#This Row],[Year_made_text]],7,1))),VALUE(RIGHT(tblLoans[[#This Row],[Year_made_text]],2))=MOD(VALUE(LEFT(tblLoans[[#This Row],[Year_made_text]],4))+1,100),VALUE(LEFT(tblLoans[[#This Row],[Year_made_text]],4))>=1900,VALUE(LEFT(tblLoans[[#This Row],[Year_made_text]],4))<=2100),FALSE))),AND(tblLoans[[#This Row],[Status]]="REVIEWED",AND(NOT(OR(LOWER(TRIM(tblLoans[[#This Row],[Year_tested_text]]&""))={"","-","?","n/a","na","unk","unknown"})),NOT(IFERROR(AND(LEN(tblLoans[[#This Row],[Year_tested_text]])=7,MID(tblLoans[[#This Row],[Year_tested_text]],5,1)="-",ISNUMBER(VALUE(MID(tblLoans[[#This Row],[Year_tested_text]],1,1))),ISNUMBER(VALUE(MID(tblLoans[[#This Row],[Year_tested_text]],2,1))),ISNUMBER(VALUE(MID(tblLoans[[#This Row],[Year_tested_text]],3,1))),ISNUMBER(VALUE(MID(tblLoans[[#This Row],[Year_tested_text]],4,1))),ISNUMBER(VALUE(MID(tblLoans[[#This Row],[Year_tested_text]],6,1))),ISNUMBER(VALUE(MID(tblLoans[[#This Row],[Year_tested_text]],7,1))),VALUE(RIGHT(tblLoans[[#This Row],[Year_tested_text]],2))=MOD(VALUE(LEFT(tblLoans[[#This Row],[Year_tested_text]],4))+1,100),VALUE(LEFT(tblLoans[[#This Row],[Year_tested_text]],4))>=1900,VALUE(LEFT(tblLoans[[#This Row],[Year_tested_text]],4))<=2100),FALSE))))),"year label ","")&IF(tblLoans[[#This Row],[Status]]<>"REVIEWED","",IF(OR(AND(NOT(OR(LOWER(TRIM(tblLoans[[#This Row],[written_agreement]]&""))={"","-","?","n/a","na","unk","unknown"})),NOT(OR(LOWER(TRIM(tblLoans[[#This Row],[written_agreement]]&""))={"0","1","f","false","n","no","t","true","y","yes"}))),AND(NOT(OR(LOWER(TRIM(tblLoans[[#This Row],[terms_in_place_before_lodgment_day]]&""))={"","-","?","n/a","na","unk","unknown"})),NOT(OR(LOWER(TRIM(tblLoans[[#This Row],[terms_in_place_before_lodgment_day]]&""))={"0","1","f","false","n","no","t","true","y","yes"}))),AND(NOT(OR(LOWER(TRIM(tblLoans[[#This Row],[secured_by_registered_mortgage_over_real_property]]&""))={"","-","?","n/a","na","unk","unknown"})),NOT(OR(LOWER(TRIM(tblLoans[[#This Row],[secured_by_registered_mortgage_over_real_property]]&""))={"0","1","f","false","n","no","t","true","y","yes"})))),"true/false/unknown ","")&IF(OR(AND(NOT(OR(LOWER(TRIM(tblLoans[[#This Row],[maximum_term_years]]&""))={"","-","?","n/a","na","unk","unknown"})),OR(NOT(ISNUMBER(tblLoans[[#This Row],[maximum_term_years]])),AND(ISNUMBER(tblLoans[[#This Row],[maximum_term_years]]),OR(tblLoans[[#This Row],[maximum_term_years]]<0)))),AND(NOT(OR(LOWER(TRIM(tblLoans[[#This Row],[security_coverage_at_first_made]]&""))={"","-","?","n/a","na","unk","unknown"})),OR(NOT(ISNUMBER(tblLoans[[#This Row],[security_coverage_at_first_made]])),AND(ISNUMBER(tblLoans[[#This Row],[security_coverage_at_first_made]]),OR(tblLoans[[#This Row],[security_coverage_at_first_made]]<0)))),AND(NOT(OR(LOWER(TRIM(tblLoans[[#This Row],[interest_rate_for_years_after_year_loan_made]]&""))={"","-","?","n/a","na","unk","unknown"})),OR(NOT(ISNUMBER(tblLoans[[#This Row],[interest_rate_for_years_after_year_loan_made]])),AND(ISNUMBER(tblLoans[[#This Row],[interest_rate_for_years_after_year_loan_made]]),OR(tblLoans[[#This Row],[interest_rate_for_years_after_year_loan_made]]<0,tblLoans[[#This Row],[interest_rate_for_years_after_year_loan_made]]>1)))),AND(NOT(OR(LOWER(TRIM(tblLoans[[#This Row],[amalgamated_loan_unpaid_at_end_of_previous_year]]&""))={"","-","?","n/a","na","unk","unknown"})),OR(NOT(ISNUMBER(tblLoans[[#This Row],[amalgamated_loan_unpaid_at_end_of_previous_year]])),AND(ISNUMBER(tblLoans[[#This Row],[amalgamated_loan_unpaid_at_end_of_previous_year]]),OR(tblLoans[[#This Row],[amalgamated_loan_unpaid_at_end_of_previous_year]]<0,ROUND(N(tblLoans[[#This Row],[amalgamated_loan_unpaid_at_end_of_previous_year]]),2)<>N(tblLoans[[#This Row],[amalgamated_loan_unpaid_at_end_of_previous_year]]),N(tblLoans[[#This Row],[amalgamated_loan_unpaid_at_end_of_previous_year]])>1000000000000)))),AND(NOT(OR(LOWER(TRIM(tblLoans[[#This Row],[remaining_term_years]]&""))={"","-","?","n/a","na","unk","unknown"})),OR(NOT(ISNUMBER(tblLoans[[#This Row],[remaining_term_years]])),AND(ISNUMBER(tblLoans[[#This Row],[remaining_term_years]]),OR(tblLoans[[#This Row],[remaining_term_years]]<0)))),AND(NOT(OR(LOWER(TRIM(tblLoans[[#This Row],[payments_applied_during_the_year]]&""))={"","-","?","n/a","na","unk","unknown"})),OR(NOT(ISNUMBER(tblLoans[[#This Row],[payments_applied_during_the_year]])),AND(ISNUMBER(tblLoans[[#This Row],[payments_applied_during_the_year]]),OR(tblLoans[[#This Row],[payments_applied_during_the_year]]<0,ROUND(N(tblLoans[[#This Row],[payments_applied_during_the_year]]),2)<>N(tblLoans[[#This Row],[payments_applied_during_the_year]]),N(tblLoans[[#This Row],[payments_applied_during_the_year]])>1000000000000))))),"number ","")))) | AJ7: =IF(SUMPRODUCT((tblLoans[[#This Row],[loan_id]]&""={"L-101","L-102","L-103","L-104","L-105","L-106","L-107","L-108"})*(tblLoans[[#This Row],[Year_made_text]]&""={"2023-24","2022-23","2021-22","2024-25","2019-20","2020-21","2023-24","1996-97"}))>0,1,0) -> 1 | AK7: =TRIM(SUBSTITUTE(SUBSTITUTE(SUBSTITUTE(SUBSTITUTE(SUBSTITUTE(SUBSTITUTE(SUBSTITUTE(SUBSTITUTE(SUBSTITUTE(SUBSTITUTE(SUBSTITUTE(SUBSTITUTE(SUBSTITUTE(SUBSTITUTE(SUBSTITUTE(SUBSTITUTE(SUBSTITUTE(SUBSTITUTE(SUBSTITUTE(SUBSTITUTE(SUBSTITUTE(SUBSTITUTE(SUBSTITUTE(SUBSTITUTE(SUBSTITUTE(SUBSTITUTE(SUBSTITUTE(SUBSTITUTE(tblLoans[[#This Row],[year_loan_made]]&"",_xlfn.UNICHAR(9)," "),_xlfn.UNICHAR(10)," "),_xlfn.UNICHAR(11)," "),_xlfn.UNICHAR(12)," "),_xlfn.UNICHAR(13)," "),_xlfn.UNICHAR(28)," "),_xlfn.UNICHAR(29)," "),_xlfn.UNICHAR(30)," "),_xlfn.UNICHAR(31)," "),_xlfn.UNICHAR(133)," "),_xlfn.UNICHAR(160)," "),_xlfn.UNICHAR(5760)," "),_xlfn.UNICHAR(8192)," "),_xlfn.UNICHAR(8193)," "),_xlfn.UNICHAR(8194)," "),_xlfn.UNICHAR(8195)," "),_xlfn.UNICHAR(8196)," "),_xlfn.UNICHAR(8197)," "),_xlfn.UNICHAR(8198)," "),_xlfn.UNICHAR(8199)," "),_xlfn.UNICHAR(8200)," "),_xlfn.UNICHAR(8201)," "),_xlfn.UNICHAR(8202)," "),_xlfn.UNICHAR(8232)," "),_xlfn.UNICHAR(8233)," "),_xlfn.UNICHAR(8239)," "),_xlfn.UNICHAR(8287)," "),_xlfn.UNICHAR(12288)," ")) -> 2020-21 | AL7: =TRIM(SUBSTITUTE(SUBSTITUTE(SUBSTITUTE(SUBSTITUTE(SUBSTITUTE(SUBSTITUTE(SUBSTITUTE(SUBSTITUTE(SUBSTITUTE(SUBSTITUTE(SUBSTITUTE(SUBSTITUTE(SUBSTITUTE(SUBSTITUTE(SUBSTITUTE(SUBSTITUTE(SUBSTITUTE(SUBSTITUTE(SUBSTITUTE(SUBSTITUTE(SUBSTITUTE(SUBSTITUTE(SUBSTITUTE(SUBSTITUTE(SUBSTITUTE(SUBSTITUTE(SUBSTITUTE(SUBSTITUTE(tblLoans[[#This Row],[year_of_income_being_tested]]&"",_xlfn.UNICHAR(9)," "),_xlfn.UNICHAR(10)," "),_xlfn.UNICHAR(11)," "),_xlfn.UNICHAR(12)," "),_xlfn.UNICHAR(13)," "),_xlfn.UNICHAR(28)," "),_xlfn.UNICHAR(29)," "),_xlfn.UNICHAR(30)," "),_xlfn.UNICHAR(31)," "),_xlfn.UNICHAR(133)," "),_xlfn.UNICHAR(160)," "),_xlfn.UNICHAR(5760)," "),_xlfn.UNICHAR(8192)," "),_xlfn.UNICHAR(8193)," "),_xlfn.UNICHAR(8194)," "),_xlfn.UNICHAR(8195)," "),_xlfn.UNICHAR(8196)," "),_xlfn.UNICHAR(8197)," "),_xlfn.UNICHAR(8198)," "),_xlfn.UNICHAR(8199)," "),_xlfn.UNICHAR(8200)," "),_xlfn.UNICHAR(8201)," "),_xlfn.UNICHAR(8202)," "),_xlfn.UNICHAR(8232)," "),_xlfn.UNICHAR(8233)," "),_xlfn.UNICHAR(8239)," "),_xlfn.UNICHAR(8287)," "),_xlfn.UNICHAR(12288)," "))
A8: L-107 | B8: SYN-TRUST-G | C8: 2023-24 | D8: unknown | E8: unknown | F8: unknown | G8: unknown | H8: unknown | I8: unknown | J8: unknown | K8: unknown | L8: unknown | M8: Unpaid present entitlement under s 109XA; sub-trust arrangement not reviewed by this engine | O8: =IF(TRIM(tblLoans[[#This Row],[out_of_scope_reason]]&"")<>"","SKIPPED",IF(IFERROR(VALUE(LEFT(tblLoans[[#This Row],[Year_made_text]],4))<1998,FALSE),"SKIPPED","REVIEWED")) -> SKIPPED | P8: =IF(OR(LOWER(TRIM(tblLoans[[#This Row],[Year_tested_text]]&""))={"","-","?","n/a","na","unk","unknown"}),tblLoans[[#This Row],[Year_made_text]],tblLoans[[#This Row],[Year_tested_text]]) -> 2023-24 | Q8: =IFERROR(INDEX(tblRates[rate],MATCH(tblLoans[[#This Row],[Floor_year]],tblRates[year_of_income],0)),"") -> 0.0827 | R8: =IF(OR(LOWER(TRIM(tblLoans[[#This Row],[written_agreement]]&""))={"","-","?","n/a","na","unk","unknown"}),"UNKNOWN",IF(OR(LOWER(TRIM(tblLoans[[#This Row],[written_agreement]]&""))={"1","t","true","y","yes"}),"PASS",IF(OR(LOWER(TRIM(tblLoans[[#This Row],[written_agreement]]&""))={"0","f","false","n","no"}),"FAIL","UNKNOWN"))) -> UNKNOWN | S8: =IF(OR(LOWER(TRIM(tblLoans[[#This Row],[terms_in_place_before_lodgment_day]]&""))={"","-","?","n/a","na","unk","unknown"}),"UNKNOWN",IF(OR(LOWER(TRIM(tblLoans[[#This Row],[terms_in_place_before_lodgment_day]]&""))={"1","t","true","y","yes"}),"PASS",IF(OR(LOWER(TRIM(tblLoans[[#This Row],[terms_in_place_before_lodgment_day]]&""))={"0","f","false","n","no"}),"FAIL","UNKNOWN"))) -> UNKNOWN | T8: =IF(NOT(ISNUMBER(tblLoans[[#This Row],[interest_rate_for_years_after_year_loan_made]])),"UNKNOWN",IF(tblLoans[[#This Row],[Floor_rate]]="","UNKNOWN",IF(tblLoans[[#This Row],[interest_rate_for_years_after_year_loan_made]]>=tblLoans[[#This Row],[Floor_rate]],"PASS","FAIL"))) -> UNKNOWN | U8: =IF(OR(LOWER(TRIM(tblLoans[[#This Row],[secured_by_registered_mortgage_over_real_property]]&""))={"","-","?","n/a","na","unk","unknown"}),"UNKNOWN",IF(OR(LOWER(TRIM(tblLoans[[#This Row],[secured_by_registered_mortgage_over_real_property]]&""))={"1","t","true","y","yes"}),"PASS",IF(OR(LOWER(TRIM(tblLoans[[#This Row],[secured_by_registered_mortgage_over_real_property]]&""))={"0","f","false","n","no"}),"FAIL","UNKNOWN"))) -> UNKNOWN | V8: =IF(tblLoans[[#This Row],[Limb_secured]]="FAIL",7,IF(tblLoans[[#This Row],[Limb_secured]]="PASS",IF(ISNUMBER(tblLoans[[#This Row],[security_coverage_at_first_made]]),IF(tblLoans[[#This Row],[security_coverage_at_first_made]]>=1.1,25,7),""),"")) | W8: =IF(NOT(ISNUMBER(tblLoans[[#This Row],[maximum_term_years]])),"UNKNOWN",IF(tblLoans[[#This Row],[Allowed_term_raw]]="",IF(tblLoans[[#This Row],[maximum_term_years]]<=7,"PASS","UNKNOWN"),IF(tblLoans[[#This Row],[maximum_term_years]]<=tblLoans[[#This Row],[Allowed_term_raw]],"PASS","FAIL"))) -> UNKNOWN | X8: =IF(tblLoans[[#This Row],[Status]]="SKIPPED","",IF(OR(LOWER(TRIM(tblLoans[[#This Row],[Floor_year]]&""))={"","-","?","n/a","na","unk","unknown"}),"UNKNOWN",IF(OR(tblLoans[[#This Row],[Limb_a_written]]="FAIL",tblLoans[[#This Row],[Limb_lodgment]]="FAIL",tblLoans[[#This Row],[Limb_b_rate]]="FAIL",tblLoans[[#This Row],[Limb_c_term]]="FAIL"),"NOT_COMPLYING",IF(OR(tblLoans[[#This Row],[Limb_a_written]]="UNKNOWN",tblLoans[[#This Row],[Limb_lodgment]]="UNKNOWN",tblLoans[[#This Row],[Limb_b_rate]]="UNKNOWN",tblLoans[[#This Row],[Limb_c_term]]="UNKNOWN"),"UNKNOWN","COMPLYING")))) | Y8: =IF(OR(tblLoans[[#This Row],[Status]]="SKIPPED",OR(LOWER(TRIM(tblLoans[[#This Row],[Floor_year]]&""))={"","-","?","n/a","na","unk","unknown"})),"",IF(tblLoans[[#This Row],[Allowed_term_raw]]<>"",tblLoans[[#This Row],[Allowed_term_raw]],IF(AND(ISNUMBER(tblLoans[[#This Row],[maximum_term_years]]),tblLoans[[#This Row],[maximum_term_years]]<=7),7,""))) | Z8: =IF(tblLoans[[#This Row],[Status]]="SKIPPED","",IF(ISNUMBER(tblLoans[[#This Row],[remaining_term_years]]),ROUNDUP(tblLoans[[#This Row],[remaining_term_years]],0),"")) | AA8: =IF(AND(ISNUMBER(tblLoans[[#This Row],[amalgamated_loan_unpaid_at_end_of_previous_year]]),ISNUMBER(Summary!$B$3),Summary!$B$3>0,ISNUMBER(tblLoans[[#This Row],[Term_used]]),tblLoans[[#This Row],[Term_used]]>0),ROUND(tblLoans[[#This Row],[amalgamated_loan_unpaid_at_end_of_previous_year]]*Summary!$B$3/(1-(1/(1+Summary!$B$3))^tblLoans[[#This Row],[Term_used]]),2),"") | AB8: =IF(tblLoans[[#This Row],[Status]]="SKIPPED","",IF(OR(tblLoans[[#This Row],[Gate_verdict]]<>"COMPLYING",AND(NOT(OR(LOWER(TRIM(tblLoans[[#This Row],[Year_made_text]]&""))={"","-","?","n/a","na","unk","unknown"})),tblLoans[[#This Row],[Floor_year]]<>tblLoans[[#This Row],[Year_made_text]]),tblLoans[[#This Row],[Year_made_text]]=Summary!$B$2,IFERROR(VALUE(LEFT(tblLoans[[#This Row],[Year_made_text]],4))>Summary!$B$4,FALSE),AND(ISNUMBER(tblLoans[[#This Row],[Term_used]]),tblLoans[[#This Row],[Term_used]]<=0),AND(ISNUMBER(Summary!$B$3),Summary!$B$3<=0)),"REFUSED",IF(OR(OR(LOWER(TRIM(tblLoans[[#This Row],[Year_made_text]]&""))={"","-","?","n/a","na","unk","unknown"}),NOT(ISNUMBER(Summary!$B$3)),NOT(ISNUMBER(tblLoans[[#This Row],[amalgamated_loan_unpaid_at_end_of_previous_year]])),NOT(ISNUMBER(tblLoans[[#This Row],[payments_applied_during_the_year]])),NOT(ISNUMBER(tblLoans[[#This Row],[Term_used]]))),"UNKNOWN",IF(tblLoans[[#This Row],[MYR_raw]]-ROUND(tblLoans[[#This Row],[payments_applied_during_the_year]],2)<=0,"MYR_MET","MYR_SHORT")))) | AC8: =IF(tblLoans[[#This Row],[MYR_verdict]]="REFUSED",IF(tblLoans[[#This Row],[Gate_verdict]]<>"COMPLYING","s 109N gate is "&tblLoans[[#This Row],[Gate_verdict]]&", so s 109E produces no repayment figure",IF(tblLoans[[#This Row],[Floor_year]]<>tblLoans[[#This Row],[Year_made_text]],"gate benchmark year differs from year_loan_made",IF(tblLoans[[#This Row],[Year_made_text]]=Summary!$B$2,"year of income is the year the loan was made (s 109E(1)(a), s 109P)",IF(IFERROR(VALUE(LEFT(tblLoans[[#This Row],[Year_made_text]],4))>Summary!$B$4,FALSE),"loan made after the year of income",IF(AND(ISNUMBER(tblLoans[[#This Row],[Term_used]]),tblLoans[[#This Row],[Term_used]]<=0),"nil remaining term under s 109E(6)","nil benchmark rate"))))),IF(tblLoans[[#This Row],[MYR_verdict]]="UNKNOWN",IF(OR(LOWER(TRIM(tblLoans[[#This Row],[Year_made_text]]&""))={"","-","?","n/a","na","unk","unknown"}),"year_loan_made not established",IF(NOT(ISNUMBER(Summary!$B$3)),"no reviewed benchmark rate for the year of income",IF(NOT(ISNUMBER(tblLoans[[#This Row],[amalgamated_loan_unpaid_at_end_of_previous_year]])),"unpaid balance at end of previous year not established",IF(NOT(ISNUMBER(tblLoans[[#This Row],[payments_applied_during_the_year]])),"payments applied not established","remaining term not established")))),"")) | AD8: =IF(OR(tblLoans[[#This Row],[MYR_verdict]]="MYR_MET",tblLoans[[#This Row],[MYR_verdict]]="MYR_SHORT"),tblLoans[[#This Row],[MYR_raw]],"") | AE8: =IF(OR(tblLoans[[#This Row],[MYR_verdict]]="MYR_MET",tblLoans[[#This Row],[MYR_verdict]]="MYR_SHORT"),MAX(0,ROUND(tblLoans[[#This Row],[MYR_raw]]-ROUND(tblLoans[[#This Row],[payments_applied_during_the_year]],2),2)),"") | AF8: =IF(tblLoans[[#This Row],[MYR_verdict]]="MYR_SHORT",tblLoans[[#This Row],[Shortfall]],"") | AG8: =IF(AND(tblLoans[[#This Row],[Status]]="REVIEWED",OR(tblLoans[[#This Row],[Gate_verdict]]="UNKNOWN",tblLoans[[#This Row],[MYR_verdict]]="UNKNOWN")),1,0) -> 0 | AH8: =IF(OR(_xlfn.ISFORMULA(tblLoans[[#This Row],[loan_id]]),_xlfn.ISFORMULA(tblLoans[[#This Row],[borrower_reference]]),_xlfn.ISFORMULA(tblLoans[[#This Row],[year_loan_made]]),_xlfn.ISFORMULA(tblLoans[[#This Row],[written_agreement]]),_xlfn.ISFORMULA(tblLoans[[#This Row],[terms_in_place_before_lodgment_day]]),_xlfn.ISFORMULA(tblLoans[[#This Row],[maximum_term_years]]),_xlfn.ISFORMULA(tblLoans[[#This Row],[secured_by_registered_mortgage_over_real_property]]),_xlfn.ISFORMULA(tblLoans[[#This Row],[security_coverage_at_first_made]]),_xlfn.ISFORMULA(tblLoans[[#This Row],[interest_rate_for_years_after_year_loan_made]]),_xlfn.ISFORMULA(tblLoans[[#This Row],[amalgamated_loan_unpaid_at_end_of_previous_year]]),_xlfn.ISFORMULA(tblLoans[[#This Row],[remaining_term_years]]),_xlfn.ISFORMULA(tblLoans[[#This Row],[payments_applied_during_the_year]]),_xlfn.ISFORMULA(tblLoans[[#This Row],[out_of_scope_reason]]),_xlfn.ISFORMULA(tblLoans[[#This Row],[year_of_income_being_tested]])),1,0) -> 0 | AI8: =IF(TRIM(tblLoans[[#This Row],[out_of_scope_reason]]&"")<>"","",TRIM(IF(OR(AND(NOT(OR(LOWER(TRIM(tblLoans[[#This Row],[Year_made_text]]&""))={"","-","?","n/a","na","unk","unknown"})),NOT(IFERROR(AND(LEN(tblLoans[[#This Row],[Year_made_text]])=7,MID(tblLoans[[#This Row],[Year_made_text]],5,1)="-",ISNUMBER(VALUE(MID(tblLoans[[#This Row],[Year_made_text]],1,1))),ISNUMBER(VALUE(MID(tblLoans[[#This Row],[Year_made_text]],2,1))),ISNUMBER(VALUE(MID(tblLoans[[#This Row],[Year_made_text]],3,1))),ISNUMBER(VALUE(MID(tblLoans[[#This Row],[Year_made_text]],4,1))),ISNUMBER(VALUE(MID(tblLoans[[#This Row],[Year_made_text]],6,1))),ISNUMBER(VALUE(MID(tblLoans[[#This Row],[Year_made_text]],7,1))),VALUE(RIGHT(tblLoans[[#This Row],[Year_made_text]],2))=MOD(VALUE(LEFT(tblLoans[[#This Row],[Year_made_text]],4))+1,100),VALUE(LEFT(tblLoans[[#This Row],[Year_made_text]],4))>=1900,VALUE(LEFT(tblLoans[[#This Row],[Year_made_text]],4))<=2100),FALSE))),AND(tblLoans[[#This Row],[Status]]="REVIEWED",AND(NOT(OR(LOWER(TRIM(tblLoans[[#This Row],[Year_tested_text]]&""))={"","-","?","n/a","na","unk","unknown"})),NOT(IFERROR(AND(LEN(tblLoans[[#This Row],[Year_tested_text]])=7,MID(tblLoans[[#This Row],[Year_tested_text]],5,1)="-",ISNUMBER(VALUE(MID(tblLoans[[#This Row],[Year_tested_text]],1,1))),ISNUMBER(VALUE(MID(tblLoans[[#This Row],[Year_tested_text]],2,1))),ISNUMBER(VALUE(MID(tblLoans[[#This Row],[Year_tested_text]],3,1))),ISNUMBER(VALUE(MID(tblLoans[[#This Row],[Year_tested_text]],4,1))),ISNUMBER(VALUE(MID(tblLoans[[#This Row],[Year_tested_text]],6,1))),ISNUMBER(VALUE(MID(tblLoans[[#This Row],[Year_tested_text]],7,1))),VALUE(RIGHT(tblLoans[[#This Row],[Year_tested_text]],2))=MOD(VALUE(LEFT(tblLoans[[#This Row],[Year_tested_text]],4))+1,100),VALUE(LEFT(tblLoans[[#This Row],[Year_tested_text]],4))>=1900,VALUE(LEFT(tblLoans[[#This Row],[Year_tested_text]],4))<=2100),FALSE))))),"year label ","")&IF(tblLoans[[#This Row],[Status]]<>"REVIEWED","",IF(OR(AND(NOT(OR(LOWER(TRIM(tblLoans[[#This Row],[written_agreement]]&""))={"","-","?","n/a","na","unk","unknown"})),NOT(OR(LOWER(TRIM(tblLoans[[#This Row],[written_agreement]]&""))={"0","1","f","false","n","no","t","true","y","yes"}))),AND(NOT(OR(LOWER(TRIM(tblLoans[[#This Row],[terms_in_place_before_lodgment_day]]&""))={"","-","?","n/a","na","unk","unknown"})),NOT(OR(LOWER(TRIM(tblLoans[[#This Row],[terms_in_place_before_lodgment_day]]&""))={"0","1","f","false","n","no","t","true","y","yes"}))),AND(NOT(OR(LOWER(TRIM(tblLoans[[#This Row],[secured_by_registered_mortgage_over_real_property]]&""))={"","-","?","n/a","na","unk","unknown"})),NOT(OR(LOWER(TRIM(tblLoans[[#This Row],[secured_by_registered_mortgage_over_real_property]]&""))={"0","1","f","false","n","no","t","true","y","yes"})))),"true/false/unknown ","")&IF(OR(AND(NOT(OR(LOWER(TRIM(tblLoans[[#This Row],[maximum_term_years]]&""))={"","-","?","n/a","na","unk","unknown"})),OR(NOT(ISNUMBER(tblLoans[[#This Row],[maximum_term_years]])),AND(ISNUMBER(tblLoans[[#This Row],[maximum_term_years]]),OR(tblLoans[[#This Row],[maximum_term_years]]<0)))),AND(NOT(OR(LOWER(TRIM(tblLoans[[#This Row],[security_coverage_at_first_made]]&""))={"","-","?","n/a","na","unk","unknown"})),OR(NOT(ISNUMBER(tblLoans[[#This Row],[security_coverage_at_first_made]])),AND(ISNUMBER(tblLoans[[#This Row],[security_coverage_at_first_made]]),OR(tblLoans[[#This Row],[security_coverage_at_first_made]]<0)))),AND(NOT(OR(LOWER(TRIM(tblLoans[[#This Row],[interest_rate_for_years_after_year_loan_made]]&""))={"","-","?","n/a","na","unk","unknown"})),OR(NOT(ISNUMBER(tblLoans[[#This Row],[interest_rate_for_years_after_year_loan_made]])),AND(ISNUMBER(tblLoans[[#This Row],[interest_rate_for_years_after_year_loan_made]]),OR(tblLoans[[#This Row],[interest_rate_for_years_after_year_loan_made]]<0,tblLoans[[#This Row],[interest_rate_for_years_after_year_loan_made]]>1)))),AND(NOT(OR(LOWER(TRIM(tblLoans[[#This Row],[amalgamated_loan_unpaid_at_end_of_previous_year]]&""))={"","-","?","n/a","na","unk","unknown"})),OR(NOT(ISNUMBER(tblLoans[[#This Row],[amalgamated_loan_unpaid_at_end_of_previous_year]])),AND(ISNUMBER(tblLoans[[#This Row],[amalgamated_loan_unpaid_at_end_of_previous_year]]),OR(tblLoans[[#This Row],[amalgamated_loan_unpaid_at_end_of_previous_year]]<0,ROUND(N(tblLoans[[#This Row],[amalgamated_loan_unpaid_at_end_of_previous_year]]),2)<>N(tblLoans[[#This Row],[amalgamated_loan_unpaid_at_end_of_previous_year]]),N(tblLoans[[#This Row],[amalgamated_loan_unpaid_at_end_of_previous_year]])>1000000000000)))),AND(NOT(OR(LOWER(TRIM(tblLoans[[#This Row],[remaining_term_years]]&""))={"","-","?","n/a","na","unk","unknown"})),OR(NOT(ISNUMBER(tblLoans[[#This Row],[remaining_term_years]])),AND(ISNUMBER(tblLoans[[#This Row],[remaining_term_years]]),OR(tblLoans[[#This Row],[remaining_term_years]]<0)))),AND(NOT(OR(LOWER(TRIM(tblLoans[[#This Row],[payments_applied_during_the_year]]&""))={"","-","?","n/a","na","unk","unknown"})),OR(NOT(ISNUMBER(tblLoans[[#This Row],[payments_applied_during_the_year]])),AND(ISNUMBER(tblLoans[[#This Row],[payments_applied_during_the_year]]),OR(tblLoans[[#This Row],[payments_applied_during_the_year]]<0,ROUND(N(tblLoans[[#This Row],[payments_applied_during_the_year]]),2)<>N(tblLoans[[#This Row],[payments_applied_during_the_year]]),N(tblLoans[[#This Row],[payments_applied_during_the_year]])>1000000000000))))),"number ","")))) | AJ8: =IF(SUMPRODUCT((tblLoans[[#This Row],[loan_id]]&""={"L-101","L-102","L-103","L-104","L-105","L-106","L-107","L-108"})*(tblLoans[[#This Row],[Year_made_text]]&""={"2023-24","2022-23","2021-22","2024-25","2019-20","2020-21","2023-24","1996-97"}))>0,1,0) -> 1 | AK8: =TRIM(SUBSTITUTE(SUBSTITUTE(SUBSTITUTE(SUBSTITUTE(SUBSTITUTE(SUBSTITUTE(SUBSTITUTE(SUBSTITUTE(SUBSTITUTE(SUBSTITUTE(SUBSTITUTE(SUBSTITUTE(SUBSTITUTE(SUBSTITUTE(SUBSTITUTE(SUBSTITUTE(SUBSTITUTE(SUBSTITUTE(SUBSTITUTE(SUBSTITUTE(SUBSTITUTE(SUBSTITUTE(SUBSTITUTE(SUBSTITUTE(SUBSTITUTE(SUBSTITUTE(SUBSTITUTE(SUBSTITUTE(tblLoans[[#This Row],[year_loan_made]]&"",_xlfn.UNICHAR(9)," "),_xlfn.UNICHAR(10)," "),_xlfn.UNICHAR(11)," "),_xlfn.UNICHAR(12)," "),_xlfn.UNICHAR(13)," "),_xlfn.UNICHAR(28)," "),_xlfn.UNICHAR(29)," "),_xlfn.UNICHAR(30)," "),_xlfn.UNICHAR(31)," "),_xlfn.UNICHAR(133)," "),_xlfn.UNICHAR(160)," "),_xlfn.UNICHAR(5760)," "),_xlfn.UNICHAR(8192)," "),_xlfn.UNICHAR(8193)," "),_xlfn.UNICHAR(8194)," "),_xlfn.UNICHAR(8195)," "),_xlfn.UNICHAR(8196)," "),_xlfn.UNICHAR(8197)," "),_xlfn.UNICHAR(8198)," "),_xlfn.UNICHAR(8199)," "),_xlfn.UNICHAR(8200)," "),_xlfn.UNICHAR(8201)," "),_xlfn.UNICHAR(8202)," "),_xlfn.UNICHAR(8232)," "),_xlfn.UNICHAR(8233)," "),_xlfn.UNICHAR(8239)," "),_xlfn.UNICHAR(8287)," "),_xlfn.UNICHAR(12288)," ")) -> 2023-24 | AL8: =TRIM(SUBSTITUTE(SUBSTITUTE(SUBSTITUTE(SUBSTITUTE(SUBSTITUTE(SUBSTITUTE(SUBSTITUTE(SUBSTITUTE(SUBSTITUTE(SUBSTITUTE(SUBSTITUTE(SUBSTITUTE(SUBSTITUTE(SUBSTITUTE(SUBSTITUTE(SUBSTITUTE(SUBSTITUTE(SUBSTITUTE(SUBSTITUTE(SUBSTITUTE(SUBSTITUTE(SUBSTITUTE(SUBSTITUTE(SUBSTITUTE(SUBSTITUTE(SUBSTITUTE(SUBSTITUTE(SUBSTITUTE(tblLoans[[#This Row],[year_of_income_being_tested]]&"",_xlfn.UNICHAR(9)," "),_xlfn.UNICHAR(10)," "),_xlfn.UNICHAR(11)," "),_xlfn.UNICHAR(12)," "),_xlfn.UNICHAR(13)," "),_xlfn.UNICHAR(28)," "),_xlfn.UNICHAR(29)," "),_xlfn.UNICHAR(30)," "),_xlfn.UNICHAR(31)," "),_xlfn.UNICHAR(133)," "),_xlfn.UNICHAR(160)," "),_xlfn.UNICHAR(5760)," "),_xlfn.UNICHAR(8192)," "),_xlfn.UNICHAR(8193)," "),_xlfn.UNICHAR(8194)," "),_xlfn.UNICHAR(8195)," "),_xlfn.UNICHAR(8196)," "),_xlfn.UNICHAR(8197)," "),_xlfn.UNICHAR(8198)," "),_xlfn.UNICHAR(8199)," "),_xlfn.UNICHAR(8200)," "),_xlfn.UNICHAR(8201)," "),_xlfn.UNICHAR(8202)," "),_xlfn.UNICHAR(8232)," "),_xlfn.UNICHAR(8233)," "),_xlfn.UNICHAR(8239)," "),_xlfn.UNICHAR(8287)," "),_xlfn.UNICHAR(12288)," "))
A9: L-108 | B9: SYN-SHAREHOLDER-H | C9: 1996-97 | D9: true | E9: true | F9: 7 | G9: false | H9: unknown | I9: 0.07 | J9: 40000 | K9: 3 | L9: 10000 | O9: =IF(TRIM(tblLoans[[#This Row],[out_of_scope_reason]]&"")<>"","SKIPPED",IF(IFERROR(VALUE(LEFT(tblLoans[[#This Row],[Year_made_text]],4))<1998,FALSE),"SKIPPED","REVIEWED")) -> SKIPPED | P9: =IF(OR(LOWER(TRIM(tblLoans[[#This Row],[Year_tested_text]]&""))={"","-","?","n/a","na","unk","unknown"}),tblLoans[[#This Row],[Year_made_text]],tblLoans[[#This Row],[Year_tested_text]]) -> 1996-97 | Q9: =IFERROR(INDEX(tblRates[rate],MATCH(tblLoans[[#This Row],[Floor_year]],tblRates[year_of_income],0)),"") | R9: =IF(OR(LOWER(TRIM(tblLoans[[#This Row],[written_agreement]]&""))={"","-","?","n/a","na","unk","unknown"}),"UNKNOWN",IF(OR(LOWER(TRIM(tblLoans[[#This Row],[written_agreement]]&""))={"1","t","true","y","yes"}),"PASS",IF(OR(LOWER(TRIM(tblLoans[[#This Row],[written_agreement]]&""))={"0","f","false","n","no"}),"FAIL","UNKNOWN"))) -> PASS | S9: =IF(OR(LOWER(TRIM(tblLoans[[#This Row],[terms_in_place_before_lodgment_day]]&""))={"","-","?","n/a","na","unk","unknown"}),"UNKNOWN",IF(OR(LOWER(TRIM(tblLoans[[#This Row],[terms_in_place_before_lodgment_day]]&""))={"1","t","true","y","yes"}),"PASS",IF(OR(LOWER(TRIM(tblLoans[[#This Row],[terms_in_place_before_lodgment_day]]&""))={"0","f","false","n","no"}),"FAIL","UNKNOWN"))) -> PASS | T9: =IF(NOT(ISNUMBER(tblLoans[[#This Row],[interest_rate_for_years_after_year_loan_made]])),"UNKNOWN",IF(tblLoans[[#This Row],[Floor_rate]]="","UNKNOWN",IF(tblLoans[[#This Row],[interest_rate_for_years_after_year_loan_made]]>=tblLoans[[#This Row],[Floor_rate]],"PASS","FAIL"))) -> UNKNOWN | U9: =IF(OR(LOWER(TRIM(tblLoans[[#This Row],[secured_by_registered_mortgage_over_real_property]]&""))={"","-","?","n/a","na","unk","unknown"}),"UNKNOWN",IF(OR(LOWER(TRIM(tblLoans[[#This Row],[secured_by_registered_mortgage_over_real_property]]&""))={"1","t","true","y","yes"}),"PASS",IF(OR(LOWER(TRIM(tblLoans[[#This Row],[secured_by_registered_mortgage_over_real_property]]&""))={"0","f","false","n","no"}),"FAIL","UNKNOWN"))) -> FAIL | V9: =IF(tblLoans[[#This Row],[Limb_secured]]="FAIL",7,IF(tblLoans[[#This Row],[Limb_secured]]="PASS",IF(ISNUMBER(tblLoans[[#This Row],[security_coverage_at_first_made]]),IF(tblLoans[[#This Row],[security_coverage_at_first_made]]>=1.1,25,7),""),"")) -> 7 | W9: =IF(NOT(ISNUMBER(tblLoans[[#This Row],[maximum_term_years]])),"UNKNOWN",IF(tblLoans[[#This Row],[Allowed_term_raw]]="",IF(tblLoans[[#This Row],[maximum_term_years]]<=7,"PASS","UNKNOWN"),IF(tblLoans[[#This Row],[maximum_term_years]]<=tblLoans[[#This Row],[Allowed_term_raw]],"PASS","FAIL"))) -> PASS | X9: =IF(tblLoans[[#This Row],[Status]]="SKIPPED","",IF(OR(LOWER(TRIM(tblLoans[[#This Row],[Floor_year]]&""))={"","-","?","n/a","na","unk","unknown"}),"UNKNOWN",IF(OR(tblLoans[[#This Row],[Limb_a_written]]="FAIL",tblLoans[[#This Row],[Limb_lodgment]]="FAIL",tblLoans[[#This Row],[Limb_b_rate]]="FAIL",tblLoans[[#This Row],[Limb_c_term]]="FAIL"),"NOT_COMPLYING",IF(OR(tblLoans[[#This Row],[Limb_a_written]]="UNKNOWN",tblLoans[[#This Row],[Limb_lodgment]]="UNKNOWN",tblLoans[[#This Row],[Limb_b_rate]]="UNKNOWN",tblLoans[[#This Row],[Limb_c_term]]="UNKNOWN"),"UNKNOWN","COMPLYING")))) | Y9: =IF(OR(tblLoans[[#This Row],[Status]]="SKIPPED",OR(LOWER(TRIM(tblLoans[[#This Row],[Floor_year]]&""))={"","-","?","n/a","na","unk","unknown"})),"",IF(tblLoans[[#This Row],[Allowed_term_raw]]<>"",tblLoans[[#This Row],[Allowed_term_raw]],IF(AND(ISNUMBER(tblLoans[[#This Row],[maximum_term_years]]),tblLoans[[#This Row],[maximum_term_years]]<=7),7,""))) | Z9: =IF(tblLoans[[#This Row],[Status]]="SKIPPED","",IF(ISNUMBER(tblLoans[[#This Row],[remaining_term_years]]),ROUNDUP(tblLoans[[#This Row],[remaining_term_years]],0),"")) | AA9: =IF(AND(ISNUMBER(tblLoans[[#This Row],[amalgamated_loan_unpaid_at_end_of_previous_year]]),ISNUMBER(Summary!$B$3),Summary!$B$3>0,ISNUMBER(tblLoans[[#This Row],[Term_used]]),tblLoans[[#This Row],[Term_used]]>0),ROUND(tblLoans[[#This Row],[amalgamated_loan_unpaid_at_end_of_previous_year]]*Summary!$B$3/(1-(1/(1+Summary!$B$3))^tblLoans[[#This Row],[Term_used]]),2),"") | AB9: =IF(tblLoans[[#This Row],[Status]]="SKIPPED","",IF(OR(tblLoans[[#This Row],[Gate_verdict]]<>"COMPLYING",AND(NOT(OR(LOWER(TRIM(tblLoans[[#This Row],[Year_made_text]]&""))={"","-","?","n/a","na","unk","unknown"})),tblLoans[[#This Row],[Floor_year]]<>tblLoans[[#This Row],[Year_made_text]]),tblLoans[[#This Row],[Year_made_text]]=Summary!$B$2,IFERROR(VALUE(LEFT(tblLoans[[#This Row],[Year_made_text]],4))>Summary!$B$4,FALSE),AND(ISNUMBER(tblLoans[[#This Row],[Term_used]]),tblLoans[[#This Row],[Term_used]]<=0),AND(ISNUMBER(Summary!$B$3),Summary!$B$3<=0)),"REFUSED",IF(OR(OR(LOWER(TRIM(tblLoans[[#This Row],[Year_made_text]]&""))={"","-","?","n/a","na","unk","unknown"}),NOT(ISNUMBER(Summary!$B$3)),NOT(ISNUMBER(tblLoans[[#This Row],[amalgamated_loan_unpaid_at_end_of_previous_year]])),NOT(ISNUMBER(tblLoans[[#This Row],[payments_applied_during_the_year]])),NOT(ISNUMBER(tblLoans[[#This Row],[Term_used]]))),"UNKNOWN",IF(tblLoans[[#This Row],[MYR_raw]]-ROUND(tblLoans[[#This Row],[payments_applied_during_the_year]],2)<=0,"MYR_MET","MYR_SHORT")))) | AC9: =IF(tblLoans[[#This Row],[MYR_verdict]]="REFUSED",IF(tblLoans[[#This Row],[Gate_verdict]]<>"COMPLYING","s 109N gate is "&tblLoans[[#This Row],[Gate_verdict]]&", so s 109E produces no repayment figure",IF(tblLoans[[#This Row],[Floor_year]]<>tblLoans[[#This Row],[Year_made_text]],"gate benchmark year differs from year_loan_made",IF(tblLoans[[#This Row],[Year_made_text]]=Summary!$B$2,"year of income is the year the loan was made (s 109E(1)(a), s 109P)",IF(IFERROR(VALUE(LEFT(tblLoans[[#This Row],[Year_made_text]],4))>Summary!$B$4,FALSE),"loan made after the year of income",IF(AND(ISNUMBER(tblLoans[[#This Row],[Term_used]]),tblLoans[[#This Row],[Term_used]]<=0),"nil remaining term under s 109E(6)","nil benchmark rate"))))),IF(tblLoans[[#This Row],[MYR_verdict]]="UNKNOWN",IF(OR(LOWER(TRIM(tblLoans[[#This Row],[Year_made_text]]&""))={"","-","?","n/a","na","unk","unknown"}),"year_loan_made not established",IF(NOT(ISNUMBER(Summary!$B$3)),"no reviewed benchmark rate for the year of income",IF(NOT(ISNUMBER(tblLoans[[#This Row],[amalgamated_loan_unpaid_at_end_of_previous_year]])),"unpaid balance at end of previous year not established",IF(NOT(ISNUMBER(tblLoans[[#This Row],[payments_applied_during_the_year]])),"payments applied not established","remaining term not established")))),"")) | AD9: =IF(OR(tblLoans[[#This Row],[MYR_verdict]]="MYR_MET",tblLoans[[#This Row],[MYR_verdict]]="MYR_SHORT"),tblLoans[[#This Row],[MYR_raw]],"") | AE9: =IF(OR(tblLoans[[#This Row],[MYR_verdict]]="MYR_MET",tblLoans[[#This Row],[MYR_verdict]]="MYR_SHORT"),MAX(0,ROUND(tblLoans[[#This Row],[MYR_raw]]-ROUND(tblLoans[[#This Row],[payments_applied_during_the_year]],2),2)),"") | AF9: =IF(tblLoans[[#This Row],[MYR_verdict]]="MYR_SHORT",tblLoans[[#This Row],[Shortfall]],"") | AG9: =IF(AND(tblLoans[[#This Row],[Status]]="REVIEWED",OR(tblLoans[[#This Row],[Gate_verdict]]="UNKNOWN",tblLoans[[#This Row],[MYR_verdict]]="UNKNOWN")),1,0) -> 0 | AH9: =IF(OR(_xlfn.ISFORMULA(tblLoans[[#This Row],[loan_id]]),_xlfn.ISFORMULA(tblLoans[[#This Row],[borrower_reference]]),_xlfn.ISFORMULA(tblLoans[[#This Row],[year_loan_made]]),_xlfn.ISFORMULA(tblLoans[[#This Row],[written_agreement]]),_xlfn.ISFORMULA(tblLoans[[#This Row],[terms_in_place_before_lodgment_day]]),_xlfn.ISFORMULA(tblLoans[[#This Row],[maximum_term_years]]),_xlfn.ISFORMULA(tblLoans[[#This Row],[secured_by_registered_mortgage_over_real_property]]),_xlfn.ISFORMULA(tblLoans[[#This Row],[security_coverage_at_first_made]]),_xlfn.ISFORMULA(tblLoans[[#This Row],[interest_rate_for_years_after_year_loan_made]]),_xlfn.ISFORMULA(tblLoans[[#This Row],[amalgamated_loan_unpaid_at_end_of_previous_year]]),_xlfn.ISFORMULA(tblLoans[[#This Row],[remaining_term_years]]),_xlfn.ISFORMULA(tblLoans[[#This Row],[payments_applied_during_the_year]]),_xlfn.ISFORMULA(tblLoans[[#This Row],[out_of_scope_reason]]),_xlfn.ISFORMULA(tblLoans[[#This Row],[year_of_income_being_tested]])),1,0) -> 0 | AI9: =IF(TRIM(tblLoans[[#This Row],[out_of_scope_reason]]&"")<>"","",TRIM(IF(OR(AND(NOT(OR(LOWER(TRIM(tblLoans[[#This Row],[Year_made_text]]&""))={"","-","?","n/a","na","unk","unknown"})),NOT(IFERROR(AND(LEN(tblLoans[[#This Row],[Year_made_text]])=7,MID(tblLoans[[#This Row],[Year_made_text]],5,1)="-",ISNUMBER(VALUE(MID(tblLoans[[#This Row],[Year_made_text]],1,1))),ISNUMBER(VALUE(MID(tblLoans[[#This Row],[Year_made_text]],2,1))),ISNUMBER(VALUE(MID(tblLoans[[#This Row],[Year_made_text]],3,1))),ISNUMBER(VALUE(MID(tblLoans[[#This Row],[Year_made_text]],4,1))),ISNUMBER(VALUE(MID(tblLoans[[#This Row],[Year_made_text]],6,1))),ISNUMBER(VALUE(MID(tblLoans[[#This Row],[Year_made_text]],7,1))),VALUE(RIGHT(tblLoans[[#This Row],[Year_made_text]],2))=MOD(VALUE(LEFT(tblLoans[[#This Row],[Year_made_text]],4))+1,100),VALUE(LEFT(tblLoans[[#This Row],[Year_made_text]],4))>=1900,VALUE(LEFT(tblLoans[[#This Row],[Year_made_text]],4))<=2100),FALSE))),AND(tblLoans[[#This Row],[Status]]="REVIEWED",AND(NOT(OR(LOWER(TRIM(tblLoans[[#This Row],[Year_tested_text]]&""))={"","-","?","n/a","na","unk","unknown"})),NOT(IFERROR(AND(LEN(tblLoans[[#This Row],[Year_tested_text]])=7,MID(tblLoans[[#This Row],[Year_tested_text]],5,1)="-",ISNUMBER(VALUE(MID(tblLoans[[#This Row],[Year_tested_text]],1,1))),ISNUMBER(VALUE(MID(tblLoans[[#This Row],[Year_tested_text]],2,1))),ISNUMBER(VALUE(MID(tblLoans[[#This Row],[Year_tested_text]],3,1))),ISNUMBER(VALUE(MID(tblLoans[[#This Row],[Year_tested_text]],4,1))),ISNUMBER(VALUE(MID(tblLoans[[#This Row],[Year_tested_text]],6,1))),ISNUMBER(VALUE(MID(tblLoans[[#This Row],[Year_tested_text]],7,1))),VALUE(RIGHT(tblLoans[[#This Row],[Year_tested_text]],2))=MOD(VALUE(LEFT(tblLoans[[#This Row],[Year_tested_text]],4))+1,100),VALUE(LEFT(tblLoans[[#This Row],[Year_tested_text]],4))>=1900,VALUE(LEFT(tblLoans[[#This Row],[Year_tested_text]],4))<=2100),FALSE))))),"year label ","")&IF(tblLoans[[#This Row],[Status]]<>"REVIEWED","",IF(OR(AND(NOT(OR(LOWER(TRIM(tblLoans[[#This Row],[written_agreement]]&""))={"","-","?","n/a","na","unk","unknown"})),NOT(OR(LOWER(TRIM(tblLoans[[#This Row],[written_agreement]]&""))={"0","1","f","false","n","no","t","true","y","yes"}))),AND(NOT(OR(LOWER(TRIM(tblLoans[[#This Row],[terms_in_place_before_lodgment_day]]&""))={"","-","?","n/a","na","unk","unknown"})),NOT(OR(LOWER(TRIM(tblLoans[[#This Row],[terms_in_place_before_lodgment_day]]&""))={"0","1","f","false","n","no","t","true","y","yes"}))),AND(NOT(OR(LOWER(TRIM(tblLoans[[#This Row],[secured_by_registered_mortgage_over_real_property]]&""))={"","-","?","n/a","na","unk","unknown"})),NOT(OR(LOWER(TRIM(tblLoans[[#This Row],[secured_by_registered_mortgage_over_real_property]]&""))={"0","1","f","false","n","no","t","true","y","yes"})))),"true/false/unknown ","")&IF(OR(AND(NOT(OR(LOWER(TRIM(tblLoans[[#This Row],[maximum_term_years]]&""))={"","-","?","n/a","na","unk","unknown"})),OR(NOT(ISNUMBER(tblLoans[[#This Row],[maximum_term_years]])),AND(ISNUMBER(tblLoans[[#This Row],[maximum_term_years]]),OR(tblLoans[[#This Row],[maximum_term_years]]<0)))),AND(NOT(OR(LOWER(TRIM(tblLoans[[#This Row],[security_coverage_at_first_made]]&""))={"","-","?","n/a","na","unk","unknown"})),OR(NOT(ISNUMBER(tblLoans[[#This Row],[security_coverage_at_first_made]])),AND(ISNUMBER(tblLoans[[#This Row],[security_coverage_at_first_made]]),OR(tblLoans[[#This Row],[security_coverage_at_first_made]]<0)))),AND(NOT(OR(LOWER(TRIM(tblLoans[[#This Row],[interest_rate_for_years_after_year_loan_made]]&""))={"","-","?","n/a","na","unk","unknown"})),OR(NOT(ISNUMBER(tblLoans[[#This Row],[interest_rate_for_years_after_year_loan_made]])),AND(ISNUMBER(tblLoans[[#This Row],[interest_rate_for_years_after_year_loan_made]]),OR(tblLoans[[#This Row],[interest_rate_for_years_after_year_loan_made]]<0,tblLoans[[#This Row],[interest_rate_for_years_after_year_loan_made]]>1)))),AND(NOT(OR(LOWER(TRIM(tblLoans[[#This Row],[amalgamated_loan_unpaid_at_end_of_previous_year]]&""))={"","-","?","n/a","na","unk","unknown"})),OR(NOT(ISNUMBER(tblLoans[[#This Row],[amalgamated_loan_unpaid_at_end_of_previous_year]])),AND(ISNUMBER(tblLoans[[#This Row],[amalgamated_loan_unpaid_at_end_of_previous_year]]),OR(tblLoans[[#This Row],[amalgamated_loan_unpaid_at_end_of_previous_year]]<0,ROUND(N(tblLoans[[#This Row],[amalgamated_loan_unpaid_at_end_of_previous_year]]),2)<>N(tblLoans[[#This Row],[amalgamated_loan_unpaid_at_end_of_previous_year]]),N(tblLoans[[#This Row],[amalgamated_loan_unpaid_at_end_of_previous_year]])>1000000000000)))),AND(NOT(OR(LOWER(TRIM(tblLoans[[#This Row],[remaining_term_years]]&""))={"","-","?","n/a","na","unk","unknown"})),OR(NOT(ISNUMBER(tblLoans[[#This Row],[remaining_term_years]])),AND(ISNUMBER(tblLoans[[#This Row],[remaining_term_years]]),OR(tblLoans[[#This Row],[remaining_term_years]]<0)))),AND(NOT(OR(LOWER(TRIM(tblLoans[[#This Row],[payments_applied_during_the_year]]&""))={"","-","?","n/a","na","unk","unknown"})),OR(NOT(ISNUMBER(tblLoans[[#This Row],[payments_applied_during_the_year]])),AND(ISNUMBER(tblLoans[[#This Row],[payments_applied_during_the_year]]),OR(tblLoans[[#This Row],[payments_applied_during_the_year]]<0,ROUND(N(tblLoans[[#This Row],[payments_applied_during_the_year]]),2)<>N(tblLoans[[#This Row],[payments_applied_during_the_year]]),N(tblLoans[[#This Row],[payments_applied_during_the_year]])>1000000000000))))),"number ","")))) | AJ9: =IF(SUMPRODUCT((tblLoans[[#This Row],[loan_id]]&""={"L-101","L-102","L-103","L-104","L-105","L-106","L-107","L-108"})*(tblLoans[[#This Row],[Year_made_text]]&""={"2023-24","2022-23","2021-22","2024-25","2019-20","2020-21","2023-24","1996-97"}))>0,1,0) -> 1 | AK9: =TRIM(SUBSTITUTE(SUBSTITUTE(SUBSTITUTE(SUBSTITUTE(SUBSTITUTE(SUBSTITUTE(SUBSTITUTE(SUBSTITUTE(SUBSTITUTE(SUBSTITUTE(SUBSTITUTE(SUBSTITUTE(SUBSTITUTE(SUBSTITUTE(SUBSTITUTE(SUBSTITUTE(SUBSTITUTE(SUBSTITUTE(SUBSTITUTE(SUBSTITUTE(SUBSTITUTE(SUBSTITUTE(SUBSTITUTE(SUBSTITUTE(SUBSTITUTE(SUBSTITUTE(SUBSTITUTE(SUBSTITUTE(tblLoans[[#This Row],[year_loan_made]]&"",_xlfn.UNICHAR(9)," "),_xlfn.UNICHAR(10)," "),_xlfn.UNICHAR(11)," "),_xlfn.UNICHAR(12)," "),_xlfn.UNICHAR(13)," "),_xlfn.UNICHAR(28)," "),_xlfn.UNICHAR(29)," "),_xlfn.UNICHAR(30)," "),_xlfn.UNICHAR(31)," "),_xlfn.UNICHAR(133)," "),_xlfn.UNICHAR(160)," "),_xlfn.UNICHAR(5760)," "),_xlfn.UNICHAR(8192)," "),_xlfn.UNICHAR(8193)," "),_xlfn.UNICHAR(8194)," "),_xlfn.UNICHAR(8195)," "),_xlfn.UNICHAR(8196)," "),_xlfn.UNICHAR(8197)," "),_xlfn.UNICHAR(8198)," "),_xlfn.UNICHAR(8199)," "),_xlfn.UNICHAR(8200)," "),_xlfn.UNICHAR(8201)," "),_xlfn.UNICHAR(8202)," "),_xlfn.UNICHAR(8232)," "),_xlfn.UNICHAR(8233)," "),_xlfn.UNICHAR(8239)," "),_xlfn.UNICHAR(8287)," "),_xlfn.UNICHAR(12288)," ")) -> 1996-97 | AL9: =TRIM(SUBSTITUTE(SUBSTITUTE(SUBSTITUTE(SUBSTITUTE(SUBSTITUTE(SUBSTITUTE(SUBSTITUTE(SUBSTITUTE(SUBSTITUTE(SUBSTITUTE(SUBSTITUTE(SUBSTITUTE(SUBSTITUTE(SUBSTITUTE(SUBSTITUTE(SUBSTITUTE(SUBSTITUTE(SUBSTITUTE(SUBSTITUTE(SUBSTITUTE(SUBSTITUTE(SUBSTITUTE(SUBSTITUTE(SUBSTITUTE(SUBSTITUTE(SUBSTITUTE(SUBSTITUTE(SUBSTITUTE(tblLoans[[#This Row],[year_of_income_being_tested]]&"",_xlfn.UNICHAR(9)," "),_xlfn.UNICHAR(10)," "),_xlfn.UNICHAR(11)," "),_xlfn.UNICHAR(12)," "),_xlfn.UNICHAR(13)," "),_xlfn.UNICHAR(28)," "),_xlfn.UNICHAR(29)," "),_xlfn.UNICHAR(30)," "),_xlfn.UNICHAR(31)," "),_xlfn.UNICHAR(133)," "),_xlfn.UNICHAR(160)," "),_xlfn.UNICHAR(5760)," "),_xlfn.UNICHAR(8192)," "),_xlfn.UNICHAR(8193)," "),_xlfn.UNICHAR(8194)," "),_xlfn.UNICHAR(8195)," "),_xlfn.UNICHAR(8196)," "),_xlfn.UNICHAR(8197)," "),_xlfn.UNICHAR(8198)," "),_xlfn.UNICHAR(8199)," "),_xlfn.UNICHAR(8200)," "),_xlfn.UNICHAR(8201)," "),_xlfn.UNICHAR(8202)," "),_xlfn.UNICHAR(8232)," "),_xlfn.UNICHAR(8233)," "),_xlfn.UNICHAR(8239)," "),_xlfn.UNICHAR(8287)," "),_xlfn.UNICHAR(12288)," "))

Sheet Rates
A1: year_of_income | B1: rate | C1: rba_table | D1: rba_series | E1: rba_month | F1: source | G1: seen
A2: 2019-20 | B2: 0.0537 | C2: F5 | D2: FILRHLBVS | E2: 2019-05 | F2: RBA statistical table F5 Indicator Lending Rates, series FILRHLBVS (Housing loans; Banks; Variable; Standard; Owner-occupier), figure for May 2019; cross-checked against the published Division 7A benchmark rate table. Automated comparison 23 September 2026: xl/worksheets/sheet1.xml!D736, series identifier D11. | G2: 2026-08-28
A3: 2020-21 | B3: 0.0452 | C3: F5 | D3: FILRHLBVS | E3: 2020-05 | F3: RBA statistical table F5 Indicator Lending Rates, series FILRHLBVS (Housing loans; Banks; Variable; Standard; Owner-occupier), figure for May 2020; cross-checked against the published Division 7A benchmark rate table. Automated comparison 23 September 2026: xl/worksheets/sheet1.xml!D748, series identifier D11. | G3: 2026-08-28
A4: 2021-22 | B4: 0.0452 | C4: F5 | D4: FILRHLBVS | E4: 2021-05 | F4: RBA statistical table F5 Indicator Lending Rates, series FILRHLBVS (Housing loans; Banks; Variable; Standard; Owner-occupier), figure for May 2021; cross-checked against the published Division 7A benchmark rate table. Automated comparison 23 September 2026: xl/worksheets/sheet1.xml!D760, series identifier D11. | G4: 2026-08-28
A5: 2022-23 | B5: 0.0477 | C5: F5 | D5: FILRHLBVS | E5: 2022-05 | F5: RBA statistical table F5 Indicator Lending Rates, series FILRHLBVS (Housing loans; Banks; Variable; Standard; Owner-occupier), figure for May 2022; cross-checked against the published Division 7A benchmark rate table. Automated comparison 23 September 2026: xl/worksheets/sheet1.xml!D772, series identifier D11. | G5: 2026-08-28
A6: 2023-24 | B6: 0.0827 | C6: F5 | D6: FILRHLBVS | E6: 2023-05 | F6: RBA statistical table F5 Indicator Lending Rates, series FILRHLBVS (Housing loans; Banks; Variable; Standard; Owner-occupier), figure for May 2023; cross-checked against the published Division 7A benchmark rate table. Automated comparison 23 September 2026: xl/worksheets/sheet1.xml!D784, series identifier D11. | G6: 2026-08-28
A7: 2024-25 | B7: 0.0877 | C7: F5 | D7: FILRHLBVS | E7: 2024-05 | F7: RBA statistical table F5 Indicator Lending Rates, series FILRHLBVS (Housing loans; Banks; Variable; Standard; Owner-occupier), figure for May 2024; cross-checked against the published Division 7A benchmark rate table. Automated comparison 23 September 2026: xl/worksheets/sheet1.xml!D796, series identifier D11. | G7: 2026-08-28
A8: 2025-26 | B8: 0.0837 | C8: F5 | D8: FILRHLBVS | E8: 2025-05 | F8: RBA statistical table F5 Indicator Lending Rates, series FILRHLBVS (Housing loans; Banks; Variable; Standard; Owner-occupier), figure for May 2025 (8.37 per cent). June 2025 was 8.27 per cent and is not the benchmark rate: it was published after the year of income began. Automated comparison 23 September 2026: xl/worksheets/sheet1.xml!D808, series identifier D11. | G8: 2026-08-28
A9: 2026-27 | B9: 0.0877 | C9: F5 | D9: FILRHLBVS | E9: 2026-05 | F9: RBA statistical table F5 Indicator Lending Rates, series FILRHLBVS (Housing loans; Banks; Variable; Standard; Owner-occupier), figure for May 2026; cross-checked against the published Division 7A benchmark rate table. Automated comparison 23 September 2026: xl/worksheets/sheet1.xml!D820, series identifier D11. | G9: 2026-08-28
A12: To review a year outside this table, add a row with the May RBA F5 FILRHLBVS figure and cite where you read it. A blank source is not a review.

Sheet Summary
A1: Review
A2: Year of income under review | B2: 2026-27
A3: Benchmark interest rate for that year (s 109N(2)) | B3: =IFERROR(INDEX(tblRates[rate],MATCH(B2,tblRates[year_of_income],0)),"") -> 0.0877
A4: Year start | B4: =IFERROR(VALUE(LEFT(B2,4)),"") -> 2026
A6: Summary (counts are per question, not per row)
A7: rows_reviewed | B7: =COUNTIF(tblLoans[Status],"REVIEWED") -> 6
A8: COMPLYING | B8: =COUNTIF(tblLoans[Gate_verdict],"COMPLYING") -> 3
A9: NOT_COMPLYING | B9: =COUNTIF(tblLoans[Gate_verdict],"NOT_COMPLYING") -> 2
A10: MYR_MET | B10: =COUNTIF(tblLoans[MYR_verdict],"MYR_MET") -> 0
A11: MYR_SHORT | B11: =COUNTIF(tblLoans[MYR_verdict],"MYR_SHORT") -> 1
A12: UNKNOWN | B12: =SUM(tblLoans[Undecided]) -> 2
A13: REFUSED | B13: =COUNTIF(tblLoans[MYR_verdict],"REFUSED") -> 4
A14: SKIPPED | B14: =COUNTIF(tblLoans[Status],"SKIPPED") -> 2
A15: experimental_total_exposure | B15: =SUM(tblLoans[Exposure]) -> 2212.37
A17: Overall status | B17: ='Review Checks'!B10 -> REVIEW

Sheet Review Checks
A1: Check | B1: Result | C1: Count or value | D1: Example loan
A2: Every register value can be read | B2: =IF(C2=0,"PASS","BLOCKED") -> PASS | C2: =SUMPRODUCT(--(tblLoans[Input_problem]<>"")) -> 0 | D2: {=IF(C2=0,"",INDEX(tblLoans[loan_id],SUMPRODUCT(MAX((tblLoans[Input_problem]<>"")*(ROW(tblLoans[loan_id])-1)))))}
A3: No formula in an input cell | B3: =IF(C3=0,"PASS","BLOCKED") -> PASS | C3: =SUM(tblLoans[Guard]) -> 0 | D3: {=IF(C3=0,"",INDEX(tblLoans[loan_id],SUMPRODUCT(MAX((tblLoans[Guard]=1)*(ROW(tblLoans[loan_id])-1)))))}
A4: A reviewed benchmark exists, rate years are unique and rates are from zero to one | B4: =IFERROR(IF(AND(ISNUMBER(Summary!B3),COUNT(tblRates[rate])=ROWS(tblRates[rate]),SUMPRODUCT(--(COUNTIF(tblRates[year_of_income],tblRates[year_of_income])<>1))=0,MIN(tblRates[rate])>=0,MAX(tblRates[rate])<=1),"PASS","BLOCKED"),"BLOCKED") -> PASS | C4: =Summary!B2 -> 2026-27
A5: Every reviewed loan is on s 109N terms | B5: =IF(C5=0,"PASS","REVIEW") -> REVIEW | C5: =COUNTIF(tblLoans[Gate_verdict],"NOT_COMPLYING") -> 2 | D5: {=IF(C5=0,"",INDEX(tblLoans[loan_id],SUMPRODUCT(MAX((tblLoans[Gate_verdict]="NOT_COMPLYING")*(ROW(tblLoans[loan_id])-1)))))} -> L-106
A6: No minimum yearly repayment is short | B6: =IF(C6=0,"PASS","REVIEW") -> REVIEW | C6: =COUNTIF(tblLoans[MYR_verdict],"MYR_SHORT") -> 1 | D6: {=IF(C6=0,"",INDEX(tblLoans[loan_id],SUMPRODUCT(MAX((tblLoans[MYR_verdict]="MYR_SHORT")*(ROW(tblLoans[loan_id])-1)))))} -> L-101
A7: No row is undecided (UNKNOWN) | B7: =IF(C7=0,"PASS","REVIEW") -> REVIEW | C7: =SUM(tblLoans[Undecided]) -> 2 | D7: {=IF(C7=0,"",INDEX(tblLoans[loan_id],SUMPRODUCT(MAX((tblLoans[Undecided]=1)*(ROW(tblLoans[loan_id])-1)))))} -> L-104
A8: Rows refused a repayment figure (read the reason; not a breach by itself) | B8: =IF(C8=0,"PASS","REVIEW") -> REVIEW | C8: =COUNTIF(tblLoans[MYR_verdict],"REFUSED") -> 4 | D8: {=IF(C8=0,"",INDEX(tblLoans[loan_id],SUMPRODUCT(MAX((tblLoans[MYR_verdict]="REFUSED")*(ROW(tblLoans[loan_id])-1)))))} -> L-106
A9: No fabricated example loan from the shipped sample remains in the register | B9: =IF(C9=0,"PASS","REVIEW") -> REVIEW | C9: =SUM(tblLoans[Sample_row]) -> 8 | D9: {=IF(C9=0,"",INDEX(tblLoans[loan_id],SUMPRODUCT(MAX((tblLoans[Sample_row]=1)*(ROW(tblLoans[loan_id])-1)))))} -> L-108
A10: Overall status | B10: =IF(COUNTIF(B2:B9,"BLOCKED")>0,"BLOCKED",IF(COUNTIF(B2:B9,"REVIEW")>0,"REVIEW","PASS")) -> REVIEW
A12: Caveats the engine attaches to every result
A13: Interest-floor interpretation unresolved: ATO guidance requires the benchmark interest rate for each year of the loan. This workbook compares one selected year's benchmark and defaults to the year the loan was made. COMPLYING does not establish that the agreement meets the annual interest requirement. Review the agreement and relevant years before relying on this result. See docs/primary-source-review-2026-08-31.md. The lodgment day (s 109D(6)) is asserted, not computed. Refinancing reductions to the maximum term (s 109N(3A) to (3D)) and the other Subdivision D exclusions are not modelled.
A14: s 109R: the workbook does not decide whether the payments applied are genuine repayments. The figure used is the operator's assertion.
A15: Any shortfall shown is an experimental review aid, not an ATO assessment and not a s 109E(1) determination. s 109E(2) makes the dividend the shortfall subject to s 109Y, and s 109E(1)(d) removes it where s 109Q applies. Neither is modelled, nor is s 109RB.
A16: The s 109E(6) amount is rounded to cents half up. The Act prescribes no rounding; this is the engine's documented choice. A fractional remaining term is rounded up to a whole number under the closing words of s 109E(6).
A17: A loan year before 1998-99 is skipped: Division 7A reaches a loan made before 4 December 1997 only where its terms were varied on or after that day (s 109D(5)).

Sheet Sources & Version
A1: Item | B1: Value
A2: Workbook engine version | B2: 0.3.1
A3: Desktop Excel build used to calculate cached values | B3: Excel 16.0 build 20527
A4: Law | B4: Income Tax Assessment Act 1936 (Cth) Part III Division 7A, C1936A00027, compilation in force 1 July 2026: s 109D, 109E, 109N, 109P, 109R
A5: Law source | B5: https://www.legislation.gov.au/C1936A00027/2026-07-01/text
A6: Benchmark rates | B6: RBA statistical table F5 Indicator Lending Rates, series FILRHLBVS, May figure for each year of income (s 109N(2))
A7: Rates reviewed until | B7: 2026-27
A8: Rates reviewed on | B8: 2026-08-28
A9: Rates explainer | B9: https://duguid.com.au/rates/div7a-benchmark-rate/
A10: Disclaimer | B10: Experimental review aid. Not a Division 7A determination, not an ATO assessment, and not tax, legal or financial advice.
